Workbook

Sheet Welcome
B6: Buy or Rent model V8 David Bartoš
B17: last updated May 2026
B19: Buy-versus-Rent Decision Support Model. Excel financial model developed for the Master's thesis Buy or Rent? Development of a Decision Support Tool for Czech Households (VŠE Prague, David Bartos, May 2026). Calibrated to Prague apartment market conditions as of Q1 2026 . Web version at https://vse-buyorrent.github.io/decision-tool/. Maintenance documented in Annex 1 of the thesis.
C20: The excel includes:
C21: Input sheet: | D21: This is where all the relevant user facing variables are. Changing them influences the result and contorls the model. The sheet also includes basic graphs showing the progression of networth
C22: Calculations: | D22: Here the main claculations are located and the logic of the model can be understood based on the formulas here
C23: Results: | D23: Include the sensitivity decomposition (hardcoded from decompositon sheet E42 outputs), decomposition of the cashflows; initial result sheet that is used for the outputs and graphs.;annual cost matrix logic is used for the costdecompositon in years
C24: Data: | D24: Price data from Sreality; rent price from sreality and toplak;flat price from CSU; Damodaran SP500 data

Sheet Input sheet(dashboard)
B1: Input assumption | C1: Unit
B2: Buying | E2: (monthly reculculation if applicable)
B3: Flatprice | C3: czk | D3: 8868530
B4: LTV | C4: % | D4: 0.9
B5: Interest(annual) | C5: % | D5: 0.0446 | E5: =((1+D5)^(1/12))-1 -> 0.0036427886
B6: Time to maturity | C6: years | D6: 30
B7: Mortgage Insurance (% of mortgage payment) | C7: % | D7: 0.08 | E7: =((1+D7)^(1/12))-1 -> 0.0064340301
B8: Repairs(annual % of property value) | C8: % | D8: 0.0125 | E8: =((1+D8)^(1/12))-1 -> 0.001035746
B9: Other fees(house admin, repair fund, monthly) | C9: czk | D9: 3000
B10: Purchase costs | C10: % | D10: 0.01
B11: Selling costs | C11: % | D11: 0.01
B12: Relestate tax (annual) | C12: czk | D12: =D30*D31*D32*D33*D34 -> 2310
B13: Interest Tax deduction limit | C13: czk | D13: 150000
B14: DSTI | C14: % | D14: 0.45
B15: Property insurance (annual) | C15: czk | D15: 4000 | E15: =D15/12 -> 333.33333
B16: Renting
B17: Monthly rent | C17: czk | D17: 25905
B18: Deposit | C18: months of rent | D18: 2
B19: Moving(how often) | C19: years | D19: =52/12 -> 4.3333333
B20: Moving cost | C20: czk | D20: 8000
B21: Macro
B22: Inflation | C22: % | D22: 0.025 | E22: =((1+D22)^(1/12))-1 -> 0.0020598363
B23: Rent growth | C23: % | D23: 0.05 | E23: =((1+D23)^(1/12))-1 -> 0.0040741238
B24: Real estate price growth | C24: % | D24: 0.05 | E24: =((1+D24)^(1/12))-1 -> 0.0040741238
B25: Investment growth | C25: % | D25: 0.08 | E25: =((1+D25)^(1/12))-1 -> 0.0064340301
B26: Further assumptions
B27: Time horizont | C27: years | D27: 40
B28: tax rate | C28: % | D28: 0.15
B29: Real estate tax
B30: Area adjustment | C30: # | D30: 1.2
B31: Cost | C31: # | D31: 3.5
B32: Base coefieicent | C32: # | D32: 5
B33: Local coeficient | C33: # | D33: 2
B34: Flat area | C34: sqm | D34: 55
G35: Outputs | H35: Buy | I35: Rent | J35: Difference | K35: Winner | L35: Buy liquidity | M35: Buy liqudity in % | N35: Net worth Crossover year | O35: Annual costs Crossover year | P35: Monthly mortgage payment | Q35: Required net income(based on DSTI)
G36: Terminal netwroth | H36: =INDEX(Calculations!W:W,MATCH(D27*12,Calculations!B:B,0),1) -> 79496192 | I36: =INDEX(Calculations!AH:AH,MATCH(D27*12,Calculations!B:B,0),1) -> 74271374 | J36: =ABS(H36-I36) -> 5224817.6 | K36: =IF(H36>I36,"BUY","RENT") -> BUY | L36: =INDEX(Calculations!V:V,MATCH(D27*12,Calculations!B:B,0),1) -> 17686184 | M36: =L36/H36 -> 0.22247838 | N36: =IF(IFERROR(MIN(Results!$K$5:$K$64),"-")>D27,"",IFERROR(MIN(Results!$K$5:$K$64),"-")) | O36: =IF(IFERROR(MIN(Results!$L$5:$L$64),"-")>D27,"",IFERROR(MIN(Results!$L$5:$L$64),"-")) -> 22 | P36: =Calculations!$E$4 -> 39834.138 | Q36: =$P$36/$D$14 -> 88520.306
G37: Annual costs in year
G38: 1 | H38: =INDEX(Results!$G:$H,MATCH('Input sheet(dashboard)'!$G38,Results!$D:$D,0),1) -> 738474.94 | I38: =INDEX(Results!$G:$H,MATCH('Input sheet(dashboard)'!$G38,Results!$D:$D,0),2) -> 369731.12
G39: 10 | H39: =INDEX(Results!$G:$H,MATCH('Input sheet(dashboard)'!$G39,Results!$D:$D,0),1) -> 722283.06 | I39: =INDEX(Results!$G:$H,MATCH('Input sheet(dashboard)'!$G39,Results!$D:$D,0),2) -> 493200.01
G40: 20 | H40: =INDEX(Results!$G:$H,MATCH('Input sheet(dashboard)'!$G40,Results!$D:$D,0),1) -> 846893.55 | I40: =INDEX(Results!$G:$H,MATCH('Input sheet(dashboard)'!$G40,Results!$D:$D,0),2) -> 803370.84
G41: 30 | H41: =INDEX(Results!$G:$H,MATCH('Input sheet(dashboard)'!$G41,Results!$D:$D,0),1) -> 1066773.4 | I41: =INDEX(Results!$G:$H,MATCH('Input sheet(dashboard)'!$G41,Results!$D:$D,0),2) -> 1308606.4
G42: 31 | H42: =INDEX(Results!$G:$H,MATCH('Input sheet(dashboard)'!$G42,Results!$D:$D,0),1) -> 576543.47 | I42: =INDEX(Results!$G:$H,MATCH('Input sheet(dashboard)'!$G42,Results!$D:$D,0),2) -> 1390990.8
G43: 40 | H43: =INDEX(Results!$G:$H,MATCH('Input sheet(dashboard)'!$G43,Results!$D:$D,0),1) -> 1491758.1 | I43: =INDEX(Results!$G:$H,MATCH('Input sheet(dashboard)'!$G43,Results!$D:$D,0),2) -> 1789319.9

Sheet Calculations>>>

Sheet Calculations
E1: Mortgage | X1: Renting | AI1: Output
B2: period | C2: year | D2: Month | E2: Mortgage payment | F2: Mortgage interest | G2: Mortgage insurance | H2: Mortgage principal | I2: Mortgage debt | J2: Property value | K2: house repairs | L2: OR/ flat fees/other fees | M2: purchase cost | N2: selling cost | O2: Interest Tax benefit COST | P2: Interest Tax benefit CF | Q2: Realestate tax | R2: property insurance | S2: Costs before investing | T2: annual costs before investing | U2: New investment | V2: Investment hodling | W2: NETWORTH | X2: Rent | Y2: Insurance | AB2: Deposit CF | AC2: moving cost | AD2: costs before investing | AE2: annual costs before investing | AF2: Saving vs Mo. | AG2: new investment | AH2: NETWORTH(invest.) | AI2: Totalvalue | AJ2: Annual costs | AK2: Annual CF | AL2: Cumulative CF
B3: 0 | C3: 1 | D3: 0 | I3: ='Input sheet(dashboard)'!D3*'Input sheet(dashboard)'!D4 -> 7981677 | J3: =IF(B3<='Input sheet(dashboard)'!$D$27*12,'Input sheet(dashboard)'!$D$3*(1+'Input sheet(dashboard)'!$E$24)^B3,0) -> 8868530 | V3: 0 | W3: =IF(B3<='Input sheet(dashboard)'!$D$27*12,J3-I3+V3-N3,0) -> 886853 | AH3: =IF(B3<='Input sheet(dashboard)'!$D$27*12,'Input sheet(dashboard)'!$D$3*(1-'Input sheet(dashboard)'!$D$4)," ") -> 886853
B4: =B3+1 -> 1 | C4: 1 | D4: 1 | E4: =IF(C4<='Input sheet(dashboard)'!$D$6, -PMT('Input sheet(dashboard)'!$E$5,'Input sheet(dashboard)'!$D$6*12,'Input sheet(dashboard)'!$D$3*'Input sheet(dashboard)'!$D$4),0) -> 39834.138 | F4: =I3*'Input sheet(dashboard)'!$E$5 -> 29075.562 | G4: =IF(C4<='Input sheet(dashboard)'!$D$6,E4*'Input sheet(dashboard)'!$D$7,0) -> 3186.731 | H4: =E4-F4 -> 10758.576 | I4: =I3-H4 -> 7970918.4 | J4: =IF(B4<='Input sheet(dashboard)'!$D$27*12,'Input sheet(dashboard)'!$D$3*(1+'Input sheet(dashboard)'!$E$24)^B4,0) -> 8904661.5 | K4: =IF(B4<='Input sheet(dashboard)'!$D$27*12,J4*'Input sheet(dashboard)'!$E$8,0) -> 9222.9676 | L4: =IF(B4<='Input sheet(dashboard)'!$D$27*12,'Input sheet(dashboard)'!$D$9*(1+'Input sheet(dashboard)'!$E$22)^B4,0) -> 3006.1795 | M4: =IF(B4=1,'Input sheet(dashboard)'!$D$3*'Input sheet(dashboard)'!$D$10,0) -> 88685.3 | N4: =IF(B4='Input sheet(dashboard)'!$D$27*12,J4*'Input sheet(dashboard)'!$D$11,0) -> 0 | O4: =IF(SUM(F4:F15)>=150000,150000/12*'Input sheet(dashboard)'!$D$28,SUM(F4:F15)/12*'Input sheet(dashboard)'!$D$28) -> 1875 | Q4: =IF(B4<='Input sheet(dashboard)'!$D$27*12,'Input sheet(dashboard)'!$D$12/12,0) -> 192.5 | R4: =IF(B4<='Input sheet(dashboard)'!$D$27*12,('Input sheet(dashboard)'!$D$15/12)*(1+'Input sheet(dashboard)'!$E$22)^Calculations!B4,0) -> 334.01995 | S4: =IF(B4<='Input sheet(dashboard)'!$D$27*12,(E4+G4+K4+L4-O4+M4+Q4+R4),0) -> 142586.84 | U4: =IF(B4<='Input sheet(dashboard)'!$D$27*12,IF(S4<AD4,AD4-S4,0),0) -> 0 | V4: =IF(B4<='Input sheet(dashboard)'!$D$27*12,V3*(1+'Input sheet(dashboard)'!$E$25)+U4,0) -> 0 | W4: =IF(B4<='Input sheet(dashboard)'!$D$27*12,J4-I4+V4-N4,0) -> 933743.06 | X4: =IF(B4<='Input sheet(dashboard)'!$D$27*12,'Input sheet(dashboard)'!$D$17*(1+'Input sheet(dashboard)'!$E$23)^(B4-1),0) -> 25905 | AB4: =IF(B4=1,'Input sheet(dashboard)'!$D$18*Calculations!X4,IF(Calculations!B4=12*'Input sheet(dashboard)'!$D$27,'Input sheet(dashboard)'!$D$18*-Calculations!X4,0)) -> 51810 | AD4: =X4+Y4+AB4+AC4 -> 77715 | AF4: =S4-AD4 -> 64871.836 | AG4: =IF(AF4>0,AF4,0) -> 64871.836 | AH4: =IF(B4<='Input sheet(dashboard)'!$D$27*12,AH3*(1+'Input sheet(dashboard)'!$E$25)+AG4," ") -> 957430.87
B5: =B4+1 -> 2 | C5: 1 | D5: 2 | E5: =IF(C5<='Input sheet(dashboard)'!$D$6, -PMT('Input sheet(dashboard)'!$E$5,'Input sheet(dashboard)'!$D$6*12,'Input sheet(dashboard)'!$D$3*'Input sheet(dashboard)'!$D$4),0) -> 39834.138 | F5: =I4*'Input sheet(dashboard)'!$E$5 -> 29036.371 | G5: =IF(C5<='Input sheet(dashboard)'!$D$6,E5*'Input sheet(dashboard)'!$D$7,0) -> 3186.731 | H5: =E5-F5 -> 10797.767 | I5: =I4-H5 -> 7960120.7 | J5: =IF(B5<='Input sheet(dashboard)'!$D$27*12,'Input sheet(dashboard)'!$D$3*(1+'Input sheet(dashboard)'!$E$24)^B5,0) -> 8940940.2 | K5: =IF(B5<='Input sheet(dashboard)'!$D$27*12,J5*'Input sheet(dashboard)'!$E$8,0) -> 9260.5432 | L5: =IF(B5<='Input sheet(dashboard)'!$D$27*12,'Input sheet(dashboard)'!$D$9*(1+'Input sheet(dashboard)'!$E$22)^B5,0) -> 3012.3717 | M5: =IF(B5=1,'Input sheet(dashboard)'!$D$3*'Input sheet(dashboard)'!$D$10,0) -> 0 | N5: =IF(B5='Input sheet(dashboard)'!$D$27*12,J5*'Input sheet(dashboard)'!$D$11,0) -> 0 | O5: =IF(SUM(F5:F16)>=150000,150000/12*'Input sheet(dashboard)'!$D$28,SUM(F5:F16)/12*'Input sheet(dashboard)'!$D$28) -> 1875 | Q5: =IF(B5<='Input sheet(dashboard)'!$D$27*12,'Input sheet(dashboard)'!$D$12/12,0) -> 192.5 | R5: =IF(B5<='Input sheet(dashboard)'!$D$27*12,('Input sheet(dashboard)'!$D$15/12)*(1+'Input sheet(dashboard)'!$E$22)^Calculations!B5,0) -> 334.70797 | S5: =IF(B5<='Input sheet(dashboard)'!$D$27*12,(E5+G5+K5+L5-O5+M5+Q5+R5),0) -> 53945.992 | U5: =IF(B5<='Input sheet(dashboard)'!$D$27*12,IF(S5<AD5,AD5-S5,0),0) -> 0 | V5: =IF(B5<='Input sheet(dashboard)'!$D$27*12,V4*(1+'Input sheet(dashboard)'!$E$25)+U5,0) -> 0 | W5: =IF(B5<='Input sheet(dashboard)'!$D$27*12,J5-I5+V5-N5,0) -> 980819.52 | X5: =IF(B5<='Input sheet(dashboard)'!$D$27*12,'Input sheet(dashboard)'!$D$17*(1+'Input sheet(dashboard)'!$E$23)^(B5-1),0) -> 26010.54 | AB5: =IF(B5=1,'Input sheet(dashboard)'!$D$18*Calculations!X5,IF(Calculations!B5=12*'Input sheet(dashboard)'!$D$27,'Input sheet(dashboard)'!$D$18*-Calculations!X5,0)) -> 0 | AC5: =IF(B5<='Input sheet(dashboard)'!$D$27*12,IF(MOD(B4,'Input sheet(dashboard)'!$D$19*12),0,'Input sheet(dashboard)'!$D$20*(1+'Input sheet(dashboard)'!$E$22)^Calculations!B5),0) -> 0 | AD5: =X5+Y5+AB5+AC5 -> 26010.54 | AF5: =S5-AD5 -> 27935.452 | AG5: =IF(AF5>0,AF5,0) -> 27935.452 | AH5: =IF(B5<='Input sheet(dashboard)'!$D$27*12,AH4*(1+'Input sheet(dashboard)'!$E$25)+AG5," ") -> 991526.47
B6: =B5+1 -> 3 | C6: 1 | D6: 3 | E6: =IF(C6<='Input sheet(dashboard)'!$D$6, -PMT('Input sheet(dashboard)'!$E$5,'Input sheet(dashboard)'!$D$6*12,'Input sheet(dashboard)'!$D$3*'Input sheet(dashboard)'!$D$4),0) -> 39834.138 | F6: =I5*'Input sheet(dashboard)'!$E$5 -> 28997.037 | G6: =IF(C6<='Input sheet(dashboard)'!$D$6,E6*'Input sheet(dashboard)'!$D$7,0) -> 3186.731 | H6: =E6-F6 -> 10837.101 | I6: =I5-H6 -> 7949283.6 | J6: =IF(B6<='Input sheet(dashboard)'!$D$27*12,'Input sheet(dashboard)'!$D$3*(1+'Input sheet(dashboard)'!$E$24)^B6,0) -> 8977366.7 | K6: =IF(B6<='Input sheet(dashboard)'!$D$27*12,J6*'Input sheet(dashboard)'!$E$8,0) -> 9298.2718 | L6: =IF(B6<='Input sheet(dashboard)'!$D$27*12,'Input sheet(dashboard)'!$D$9*(1+'Input sheet(dashboard)'!$E$22)^B6,0) -> 3018.5767 | M6: =IF(B6=1,'Input sheet(dashboard)'!$D$3*'Input sheet(dashboard)'!$D$10,0) -> 0 | N6: =IF(B6='Input sheet(dashboard)'!$D$27*12,J6*'Input sheet(dashboard)'!$D$11,0) -> 0 | O6: =IF(SUM(F6:F17)>=150000,150000/12*'Input sheet(dashboard)'!$D$28,SUM(F6:F17)/12*'Input sheet(dashboard)'!$D$28) -> 1875 | Q6: =IF(B6<='Input sheet(dashboard)'!$D$27*12,'Input sheet(dashboard)'!$D$12/12,0) -> 192.5 | R6: =IF(B6<='Input sheet(dashboard)'!$D$27*12,('Input sheet(dashboard)'!$D$15/12)*(1+'Input sheet(dashboard)'!$E$22)^Calculations!B6,0) -> 335.39742 | S6: =IF(B6<='Input sheet(dashboard)'!$D$27*12,(E6+G6+K6+L6-O6+M6+Q6+R6),0) -> 53990.615 | U6: =IF(B6<='Input sheet(dashboard)'!$D$27*12,IF(S6<AD6,AD6-S6,0),0) -> 0 | V6: =IF(B6<='Input sheet(dashboard)'!$D$27*12,V5*(1+'Input sheet(dashboard)'!$E$25)+U6,0) -> 0 | W6: =IF(B6<='Input sheet(dashboard)'!$D$27*12,J6-I6+V6-N6,0) -> 1028083.1 | X6: =IF(B6<='Input sheet(dashboard)'!$D$27*12,'Input sheet(dashboard)'!$D$17*(1+'Input sheet(dashboard)'!$E$23)^(B6-1),0) -> 26116.51 | AB6: =IF(B6=1,'Input sheet(dashboard)'!$D$18*Calculations!X6,IF(Calculations!B6=12*'Input sheet(dashboard)'!$D$27,'Input sheet(dashboard)'!$D$18*-Calculations!X6,0)) -> 0 | AC6: =IF(B6<='Input sheet(dashboard)'!$D$27*12,IF(MOD(B5,'Input sheet(dashboard)'!$D$19*12),0,'Input sheet(dashboard)'!$D$20*(1+'Input sheet(dashboard)'!$E$22)^Calculations!B6),0) -> 0 | AD6: =X6+Y6+AB6+AC6 -> 26116.51 | AF6: =S6-AD6 -> 27874.105 | AG6: =IF(AF6>0,AF6,0) -> 27874.105 | AH6: =IF(B6<='Input sheet(dashboard)'!$D$27*12,AH5*(1+'Input sheet(dashboard)'!$E$25)+AG6," ") -> 1025780.1
B7: =B6+1 -> 4 | C7: 1 | D7: 4 | E7: =IF(C7<='Input sheet(dashboard)'!$D$6, -PMT('Input sheet(dashboard)'!$E$5,'Input sheet(dashboard)'!$D$6*12,'Input sheet(dashboard)'!$D$3*'Input sheet(dashboard)'!$D$4),0) -> 39834.138 | F7: =I6*'Input sheet(dashboard)'!$E$5 -> 28957.56 | G7: =IF(C7<='Input sheet(dashboard)'!$D$6,E7*'Input sheet(dashboard)'!$D$7,0) -> 3186.731 | H7: =E7-F7 -> 10876.578 | I7: =I6-H7 -> 7938407 | J7: =IF(B7<='Input sheet(dashboard)'!$D$27*12,'Input sheet(dashboard)'!$D$3*(1+'Input sheet(dashboard)'!$E$24)^B7,0) -> 9013941.6 | K7: =IF(B7<='Input sheet(dashboard)'!$D$27*12,J7*'Input sheet(dashboard)'!$E$8,0) -> 9336.1541 | L7: =IF(B7<='Input sheet(dashboard)'!$D$27*12,'Input sheet(dashboard)'!$D$9*(1+'Input sheet(dashboard)'!$E$22)^B7,0) -> 3024.7945 | M7: =IF(B7=1,'Input sheet(dashboard)'!$D$3*'Input sheet(dashboard)'!$D$10,0) -> 0 | N7: =IF(B7='Input sheet(dashboard)'!$D$27*12,J7*'Input sheet(dashboard)'!$D$11,0) -> 0 | O7: =IF(SUM(F7:F18)>=150000,150000/12*'Input sheet(dashboard)'!$D$28,SUM(F7:F18)/12*'Input sheet(dashboard)'!$D$28) -> 1875 | Q7: =IF(B7<='Input sheet(dashboard)'!$D$27*12,'Input sheet(dashboard)'!$D$12/12,0) -> 192.5 | R7: =IF(B7<='Input sheet(dashboard)'!$D$27*12,('Input sheet(dashboard)'!$D$15/12)*(1+'Input sheet(dashboard)'!$E$22)^Calculations!B7,0) -> 336.08828 | S7: =IF(B7<='Input sheet(dashboard)'!$D$27*12,(E7+G7+K7+L7-O7+M7+Q7+R7),0) -> 54035.406 | U7: =IF(B7<='Input sheet(dashboard)'!$D$27*12,IF(S7<AD7,AD7-S7,0),0) -> 0 | V7: =IF(B7<='Input sheet(dashboard)'!$D$27*12,V6*(1+'Input sheet(dashboard)'!$E$25)+U7,0) -> 0 | W7: =IF(B7<='Input sheet(dashboard)'!$D$27*12,J7-I7+V7-N7,0) -> 1075534.6 | X7: =IF(B7<='Input sheet(dashboard)'!$D$27*12,'Input sheet(dashboard)'!$D$17*(1+'Input sheet(dashboard)'!$E$23)^(B7-1),0) -> 26222.912 | AB7: =IF(B7=1,'Input sheet(dashboard)'!$D$18*Calculations!X7,IF(Calculations!B7=12*'Input sheet(dashboard)'!$D$27,'Input sheet(dashboard)'!$D$18*-Calculations!X7,0)) -> 0 | AC7: =IF(B7<='Input sheet(dashboard)'!$D$27*12,IF(MOD(B6,'Input sheet(dashboard)'!$D$19*12),0,'Input sheet(dashboard)'!$D$20*(1+'Input sheet(dashboard)'!$E$22)^Calculations!B7),0) -> 0 | AD7: =X7+Y7+AB7+AC7 -> 26222.912 | AF7: =S7-AD7 -> 27812.494 | AG7: =IF(AF7>0,AF7,0) -> 27812.494 | AH7: =IF(B7<='Input sheet(dashboard)'!$D$27*12,AH6*(1+'Input sheet(dashboard)'!$E$25)+AG7," ") -> 1060192.5
B8: =B7+1 -> 5 | C8: 1 | D8: 5 | E8: =IF(C8<='Input sheet(dashboard)'!$D$6, -PMT('Input sheet(dashboard)'!$E$5,'Input sheet(dashboard)'!$D$6*12,'Input sheet(dashboard)'!$D$3*'Input sheet(dashboard)'!$D$4),0) -> 39834.138 | F8: =I7*'Input sheet(dashboard)'!$E$5 -> 28917.939 | G8: =IF(C8<='Input sheet(dashboard)'!$D$6,E8*'Input sheet(dashboard)'!$D$7,0) -> 3186.731 | H8: =E8-F8 -> 10916.199 | I8: =I7-H8 -> 7927490.8 | J8: =IF(B8<='Input sheet(dashboard)'!$D$27*12,'Input sheet(dashboard)'!$D$3*(1+'Input sheet(dashboard)'!$E$24)^B8,0) -> 9050665.5 | K8: =IF(B8<='Input sheet(dashboard)'!$D$27*12,J8*'Input sheet(dashboard)'!$E$8,0) -> 9374.1907 | L8: =IF(B8<='Input sheet(dashboard)'!$D$27*12,'Input sheet(dashboard)'!$D$9*(1+'Input sheet(dashboard)'!$E$22)^B8,0) -> 3031.0251 | M8: =IF(B8=1,'Input sheet(dashboard)'!$D$3*'Input sheet(dashboard)'!$D$10,0) -> 0 | N8: =IF(B8='Input sheet(dashboard)'!$D$27*12,J8*'Input sheet(dashboard)'!$D$11,0) -> 0 | O8: =IF(SUM(F8:F19)>=150000,150000/12*'Input sheet(dashboard)'!$D$28,SUM(F8:F19)/12*'Input sheet(dashboard)'!$D$28) -> 1875 | Q8: =IF(B8<='Input sheet(dashboard)'!$D$27*12,'Input sheet(dashboard)'!$D$12/12,0) -> 192.5 | R8: =IF(B8<='Input sheet(dashboard)'!$D$27*12,('Input sheet(dashboard)'!$D$15/12)*(1+'Input sheet(dashboard)'!$E$22)^Calculations!B8,0) -> 336.78057 | S8: =IF(B8<='Input sheet(dashboard)'!$D$27*12,(E8+G8+K8+L8-O8+M8+Q8+R8),0) -> 54080.365 | U8: =IF(B8<='Input sheet(dashboard)'!$D$27*12,IF(S8<AD8,AD8-S8,0),0) -> 0 | V8: =IF(B8<='Input sheet(dashboard)'!$D$27*12,V7*(1+'Input sheet(dashboard)'!$E$25)+U8,0) -> 0 | W8: =IF(B8<='Input sheet(dashboard)'!$D$27*12,J8-I8+V8-N8,0) -> 1123174.7 | X8: =IF(B8<='Input sheet(dashboard)'!$D$27*12,'Input sheet(dashboard)'!$D$17*(1+'Input sheet(dashboard)'!$E$23)^(B8-1),0) -> 26329.748 | AB8: =IF(B8=1,'Input sheet(dashboard)'!$D$18*Calculations!X8,IF(Calculations!B8=12*'Input sheet(dashboard)'!$D$27,'Input sheet(dashboard)'!$D$18*-Calculations!X8,0)) -> 0 | AC8: =IF(B8<='Input sheet(dashboard)'!$D$27*12,IF(MOD(B7,'Input sheet(dashboard)'!$D$19*12),0,'Input sheet(dashboard)'!$D$20*(1+'Input sheet(dashboard)'!$E$22)^Calculations!B8),0) -> 0 | AD8: =X8+Y8+AB8+AC8 -> 26329.748 | AF8: =S8-AD8 -> 27750.618 | AG8: =IF(AF8>0,AF8,0) -> 27750.618 | AH8: =IF(B8<='Input sheet(dashboard)'!$D$27*12,AH7*(1+'Input sheet(dashboard)'!$E$25)+AG8," ") -> 1094764.4
B9: =B8+1 -> 6 | C9: 1 | D9: 6 | E9: =IF(C9<='Input sheet(dashboard)'!$D$6, -PMT('Input sheet(dashboard)'!$E$5,'Input sheet(dashboard)'!$D$6*12,'Input sheet(dashboard)'!$D$3*'Input sheet(dashboard)'!$D$4),0) -> 39834.138 | F9: =I8*'Input sheet(dashboard)'!$E$5 -> 28878.173 | G9: =IF(C9<='Input sheet(dashboard)'!$D$6,E9*'Input sheet(dashboard)'!$D$7,0) -> 3186.731 | H9: =E9-F9 -> 10955.965 | I9: =I8-H9 -> 7916534.8 | J9: =IF(B9<='Input sheet(dashboard)'!$D$27*12,'Input sheet(dashboard)'!$D$3*(1+'Input sheet(dashboard)'!$E$24)^B9,0) -> 9087539 | K9: =IF(B9<='Input sheet(dashboard)'!$D$27*12,J9*'Input sheet(dashboard)'!$E$8,0) -> 9412.3823 | L9: =IF(B9<='Input sheet(dashboard)'!$D$27*12,'Input sheet(dashboard)'!$D$9*(1+'Input sheet(dashboard)'!$E$22)^B9,0) -> 3037.2685 | M9: =IF(B9=1,'Input sheet(dashboard)'!$D$3*'Input sheet(dashboard)'!$D$10,0) -> 0 | N9: =IF(B9='Input sheet(dashboard)'!$D$27*12,J9*'Input sheet(dashboard)'!$D$11,0) -> 0 | O9: =IF(SUM(F9:F20)>=150000,150000/12*'Input sheet(dashboard)'!$D$28,SUM(F9:F20)/12*'Input sheet(dashboard)'!$D$28) -> 1875 | Q9: =IF(B9<='Input sheet(dashboard)'!$D$27*12,'Input sheet(dashboard)'!$D$12/12,0) -> 192.5 | R9: =IF(B9<='Input sheet(dashboard)'!$D$27*12,('Input sheet(dashboard)'!$D$15/12)*(1+'Input sheet(dashboard)'!$E$22)^Calculations!B9,0) -> 337.47428 | S9: =IF(B9<='Input sheet(dashboard)'!$D$27*12,(E9+G9+K9+L9-O9+M9+Q9+R9),0) -> 54125.494 | U9: =IF(B9<='Input sheet(dashboard)'!$D$27*12,IF(S9<AD9,AD9-S9,0),0) -> 0 | V9: =IF(B9<='Input sheet(dashboard)'!$D$27*12,V8*(1+'Input sheet(dashboard)'!$E$25)+U9,0) -> 0 | W9: =IF(B9<='Input sheet(dashboard)'!$D$27*12,J9-I9+V9-N9,0) -> 1171004.2 | X9: =IF(B9<='Input sheet(dashboard)'!$D$27*12,'Input sheet(dashboard)'!$D$17*(1+'Input sheet(dashboard)'!$E$23)^(B9-1),0) -> 26437.018 | AB9: =IF(B9=1,'Input sheet(dashboard)'!$D$18*Calculations!X9,IF(Calculations!B9=12*'Input sheet(dashboard)'!$D$27,'Input sheet(dashboard)'!$D$18*-Calculations!X9,0)) -> 0 | AC9: =IF(B9<='Input sheet(dashboard)'!$D$27*12,IF(MOD(B8,'Input sheet(dashboard)'!$D$19*12),0,'Input sheet(dashboard)'!$D$20*(1+'Input sheet(dashboard)'!$E$22)^Calculations!B9),0) -> 0 | AD9: =X9+Y9+AB9+AC9 -> 26437.018 | AF9: =S9-AD9 -> 27688.476 | AG9: =IF(AF9>0,AF9,0) -> 27688.476 | AH9: =IF(B9<='Input sheet(dashboard)'!$D$27*12,AH8*(1+'Input sheet(dashboard)'!$E$25)+AG9," ") -> 1129496.6
B10: =B9+1 -> 7 | C10: 1 | D10: 7 | E10: =IF(C10<='Input sheet(dashboard)'!$D$6, -PMT('Input sheet(dashboard)'!$E$5,'Input sheet(dashboard)'!$D$6*12,'Input sheet(dashboard)'!$D$3*'Input sheet(dashboard)'!$D$4),0) -> 39834.138 | F10: =I9*'Input sheet(dashboard)'!$E$5 -> 28838.263 | G10: =IF(C10<='Input sheet(dashboard)'!$D$6,E10*'Input sheet(dashboard)'!$D$7,0) -> 3186.731 | H10: =E10-F10 -> 10995.875 | I10: =I9-H10 -> 7905538.9 | J10: =IF(B10<='Input sheet(dashboard)'!$D$27*12,'Input sheet(dashboard)'!$D$3*(1+'Input sheet(dashboard)'!$E$24)^B10,0) -> 9124562.8 | K10: =IF(B10<='Input sheet(dashboard)'!$D$27*12,J10*'Input sheet(dashboard)'!$E$8,0) -> 9450.7295 | L10: =IF(B10<='Input sheet(dashboard)'!$D$27*12,'Input sheet(dashboard)'!$D$9*(1+'Input sheet(dashboard)'!$E$22)^B10,0) -> 3043.5248 | M10: =IF(B10=1,'Input sheet(dashboard)'!$D$3*'Input sheet(dashboard)'!$D$10,0) -> 0 | N10: =IF(B10='Input sheet(dashboard)'!$D$27*12,J10*'Input sheet(dashboard)'!$D$11,0) -> 0 | O10: =IF(SUM(F10:F21)>=150000,150000/12*'Input sheet(dashboard)'!$D$28,SUM(F10:F21)/12*'Input sheet(dashboard)'!$D$28) -> 1875 | Q10: =IF(B10<='Input sheet(dashboard)'!$D$27*12,'Input sheet(dashboard)'!$D$12/12,0) -> 192.5 | R10: =IF(B10<='Input sheet(dashboard)'!$D$27*12,('Input sheet(dashboard)'!$D$15/12)*(1+'Input sheet(dashboard)'!$E$22)^Calculations!B10,0) -> 338.16942 | S10: =IF(B10<='Input sheet(dashboard)'!$D$27*12,(E10+G10+K10+L10-O10+M10+Q10+R10),0) -> 54170.793 | U10: =IF(B10<='Input sheet(dashboard)'!$D$27*12,IF(S10<AD10,AD10-S10,0),0) -> 0 | V10: =IF(B10<='Input sheet(dashboard)'!$D$27*12,V9*(1+'Input sheet(dashboard)'!$E$25)+U10,0) -> 0 | W10: =IF(B10<='Input sheet(dashboard)'!$D$27*12,J10-I10+V10-N10,0) -> 1219023.8 | X10: =IF(B10<='Input sheet(dashboard)'!$D$27*12,'Input sheet(dashboard)'!$D$17*(1+'Input sheet(dashboard)'!$E$23)^(B10-1),0) -> 26544.726 | AB10: =IF(B10=1,'Input sheet(dashboard)'!$D$18*Calculations!X10,IF(Calculations!B10=12*'Input sheet(dashboard)'!$D$27,'Input sheet(dashboard)'!$D$18*-Calculations!X10,0)) -> 0 | AC10: =IF(B10<='Input sheet(dashboard)'!$D$27*12,IF(MOD(B9,'Input sheet(dashboard)'!$D$19*12),0,'Input sheet(dashboard)'!$D$20*(1+'Input sheet(dashboard)'!$E$22)^Calculations!B10),0) -> 0 | AD10: =X10+Y10+AB10+AC10 -> 26544.726 | AF10: =S10-AD10 -> 27626.067 | AG10: =IF(AF10>0,AF10,0) -> 27626.067 | AH10: =IF(B10<='Input sheet(dashboard)'!$D$27*12,AH9*(1+'Input sheet(dashboard)'!$E$25)+AG10," ") -> 1164389.9
B11: =B10+1 -> 8 | C11: 1 | D11: 8 | E11: =IF(C11<='Input sheet(dashboard)'!$D$6, -PMT('Input sheet(dashboard)'!$E$5,'Input sheet(dashboard)'!$D$6*12,'Input sheet(dashboard)'!$D$3*'Input sheet(dashboard)'!$D$4),0) -> 39834.138 | F11: =I10*'Input sheet(dashboard)'!$E$5 -> 28798.207 | G11: =IF(C11<='Input sheet(dashboard)'!$D$6,E11*'Input sheet(dashboard)'!$D$7,0) -> 3186.731 | H11: =E11-F11 -> 11035.931 | I11: =I10-H11 -> 7894503 | J11: =IF(B11<='Input sheet(dashboard)'!$D$27*12,'Input sheet(dashboard)'!$D$3*(1+'Input sheet(dashboard)'!$E$24)^B11,0) -> 9161737.4 | K11: =IF(B11<='Input sheet(dashboard)'!$D$27*12,J11*'Input sheet(dashboard)'!$E$8,0) -> 9489.233 | L11: =IF(B11<='Input sheet(dashboard)'!$D$27*12,'Input sheet(dashboard)'!$D$9*(1+'Input sheet(dashboard)'!$E$22)^B11,0) -> 3049.7939 | M11: =IF(B11=1,'Input sheet(dashboard)'!$D$3*'Input sheet(dashboard)'!$D$10,0) -> 0 | N11: =IF(B11='Input sheet(dashboard)'!$D$27*12,J11*'Input sheet(dashboard)'!$D$11,0) -> 0 | O11: =IF(SUM(F11:F22)>=150000,150000/12*'Input sheet(dashboard)'!$D$28,SUM(F11:F22)/12*'Input sheet(dashboard)'!$D$28) -> 1875 | Q11: =IF(B11<='Input sheet(dashboard)'!$D$27*12,'Input sheet(dashboard)'!$D$12/12,0) -> 192.5 | R11: =IF(B11<='Input sheet(dashboard)'!$D$27*12,('Input sheet(dashboard)'!$D$15/12)*(1+'Input sheet(dashboard)'!$E$22)^Calculations!B11,0) -> 338.86599 | S11: =IF(B11<='Input sheet(dashboard)'!$D$27*12,(E11+G11+K11+L11-O11+M11+Q11+R11),0) -> 54216.262 | U11: =IF(B11<='Input sheet(dashboard)'!$D$27*12,IF(S11<AD11,AD11-S11,0),0) -> 0 | V11: =IF(B11<='Input sheet(dashboard)'!$D$27*12,V10*(1+'Input sheet(dashboard)'!$E$25)+U11,0) -> 0 | W11: =IF(B11<='Input sheet(dashboard)'!$D$27*12,J11-I11+V11-N11,0) -> 1267234.4 | X11: =IF(B11<='Input sheet(dashboard)'!$D$27*12,'Input sheet(dashboard)'!$D$17*(1+'Input sheet(dashboard)'!$E$23)^(B11-1),0) -> 26652.872 | AB11: =IF(B11=1,'Input sheet(dashboard)'!$D$18*Calculations!X11,IF(Calculations!B11=12*'Input sheet(dashboard)'!$D$27,'Input sheet(dashboard)'!$D$18*-Calculations!X11,0)) -> 0 | AC11: =IF(B11<='Input sheet(dashboard)'!$D$27*12,IF(MOD(B10,'Input sheet(dashboard)'!$D$19*12),0,'Input sheet(dashboard)'!$D$20*(1+'Input sheet(dashboard)'!$E$22)^Calculations!B11),0) -> 0 | AD11: =X11+Y11+AB11+AC11 -> 26652.872 | AF11: =S11-AD11 -> 27563.389 | AG11: =IF(AF11>0,AF11,0) -> 27563.389 | AH11: =IF(B11<='Input sheet(dashboard)'!$D$27*12,AH10*(1+'Input sheet(dashboard)'!$E$25)+AG11," ") -> 1199445
B12: =B11+1 -> 9 | C12: 1 | D12: 9 | E12: =IF(C12<='Input sheet(dashboard)'!$D$6, -PMT('Input sheet(dashboard)'!$E$5,'Input sheet(dashboard)'!$D$6*12,'Input sheet(dashboard)'!$D$3*'Input sheet(dashboard)'!$D$4),0) -> 39834.138 | F12: =I11*'Input sheet(dashboard)'!$E$5 -> 28758.006 | G12: =IF(C12<='Input sheet(dashboard)'!$D$6,E12*'Input sheet(dashboard)'!$D$7,0) -> 3186.731 | H12: =E12-F12 -> 11076.132 | I12: =I11-H12 -> 7883426.9 | J12: =IF(B12<='Input sheet(dashboard)'!$D$27*12,'Input sheet(dashboard)'!$D$3*(1+'Input sheet(dashboard)'!$E$24)^B12,0) -> 9199063.4 | K12: =IF(B12<='Input sheet(dashboard)'!$D$27*12,J12*'Input sheet(dashboard)'!$E$8,0) -> 9527.8933 | L12: =IF(B12<='Input sheet(dashboard)'!$D$27*12,'Input sheet(dashboard)'!$D$9*(1+'Input sheet(dashboard)'!$E$22)^B12,0) -> 3056.076 | M12: =IF(B12=1,'Input sheet(dashboard)'!$D$3*'Input sheet(dashboard)'!$D$10,0) -> 0 | N12: =IF(B12='Input sheet(dashboard)'!$D$27*12,J12*'Input sheet(dashboard)'!$D$11,0) -> 0 | O12: =IF(SUM(F12:F23)>=150000,150000/12*'Input sheet(dashboard)'!$D$28,SUM(F12:F23)/12*'Input sheet(dashboard)'!$D$28) -> 1875 | Q12: =IF(B12<='Input sheet(dashboard)'!$D$27*12,'Input sheet(dashboard)'!$D$12/12,0) -> 192.5 | R12: =IF(B12<='Input sheet(dashboard)'!$D$27*12,('Input sheet(dashboard)'!$D$15/12)*(1+'Input sheet(dashboard)'!$E$22)^Calculations!B12,0) -> 339.564 | S12: =IF(B12<='Input sheet(dashboard)'!$D$27*12,(E12+G12+K12+L12-O12+M12+Q12+R12),0) -> 54261.902 | U12: =IF(B12<='Input sheet(dashboard)'!$D$27*12,IF(S12<AD12,AD12-S12,0),0) -> 0 | V12: =IF(B12<='Input sheet(dashboard)'!$D$27*12,V11*(1+'Input sheet(dashboard)'!$E$25)+U12,0) -> 0 | W12: =IF(B12<='Input sheet(dashboard)'!$D$27*12,J12-I12+V12-N12,0) -> 1315636.6 | X12: =IF(B12<='Input sheet(dashboard)'!$D$27*12,'Input sheet(dashboard)'!$D$17*(1+'Input sheet(dashboard)'!$E$23)^(B12-1),0) -> 26761.46 | AB12: =IF(B12=1,'Input sheet(dashboard)'!$D$18*Calculations!X12,IF(Calculations!B12=12*'Input sheet(dashboard)'!$D$27,'Input sheet(dashboard)'!$D$18*-Calculations!X12,0)) -> 0 | AC12: =IF(B12<='Input sheet(dashboard)'!$D$27*12,IF(MOD(B11,'Input sheet(dashboard)'!$D$19*12),0,'Input sheet(dashboard)'!$D$20*(1+'Input sheet(dashboard)'!$E$22)^Calculations!B12),0) -> 0 | AD12: =X12+Y12+AB12+AC12 -> 26761.46 | AF12: =S12-AD12 -> 27500.443 | AG12: =IF(AF12>0,AF12,0) -> 27500.443 | AH12: =IF(B12<='Input sheet(dashboard)'!$D$27*12,AH11*(1+'Input sheet(dashboard)'!$E$25)+AG12," ") -> 1234662.7
B13: =B12+1 -> 10 | C13: 1 | D13: 10 | E13: =IF(C13<='Input sheet(dashboard)'!$D$6, -PMT('Input sheet(dashboard)'!$E$5,'Input sheet(dashboard)'!$D$6*12,'Input sheet(dashboard)'!$D$3*'Input sheet(dashboard)'!$D$4),0) -> 39834.138 | F13: =I12*'Input sheet(dashboard)'!$E$5 -> 28717.658 | G13: =IF(C13<='Input sheet(dashboard)'!$D$6,E13*'Input sheet(dashboard)'!$D$7,0) -> 3186.731 | H13: =E13-F13 -> 11116.48 | I13: =I12-H13 -> 7872310.4 | J13: =IF(B13<='Input sheet(dashboard)'!$D$27*12,'Input sheet(dashboard)'!$D$3*(1+'Input sheet(dashboard)'!$E$24)^B13,0) -> 9236541.6 | K13: =IF(B13<='Input sheet(dashboard)'!$D$27*12,J13*'Input sheet(dashboard)'!$E$8,0) -> 9566.7111 | L13: =IF(B13<='Input sheet(dashboard)'!$D$27*12,'Input sheet(dashboard)'!$D$9*(1+'Input sheet(dashboard)'!$E$22)^B13,0) -> 3062.371 | M13: =IF(B13=1,'Input sheet(dashboard)'!$D$3*'Input sheet(dashboard)'!$D$10,0) -> 0 | N13: =IF(B13='Input sheet(dashboard)'!$D$27*12,J13*'Input sheet(dashboard)'!$D$11,0) -> 0 | O13: =IF(SUM(F13:F24)>=150000,150000/12*'Input sheet(dashboard)'!$D$28,SUM(F13:F24)/12*'Input sheet(dashboard)'!$D$28) -> 1875 | Q13: =IF(B13<='Input sheet(dashboard)'!$D$27*12,'Input sheet(dashboard)'!$D$12/12,0) -> 192.5 | R13: =IF(B13<='Input sheet(dashboard)'!$D$27*12,('Input sheet(dashboard)'!$D$15/12)*(1+'Input sheet(dashboard)'!$E$22)^Calculations!B13,0) -> 340.26345 | S13: =IF(B13<='Input sheet(dashboard)'!$D$27*12,(E13+G13+K13+L13-O13+M13+Q13+R13),0) -> 54307.715 | U13: =IF(B13<='Input sheet(dashboard)'!$D$27*12,IF(S13<AD13,AD13-S13,0),0) -> 0 | V13: =IF(B13<='Input sheet(dashboard)'!$D$27*12,V12*(1+'Input sheet(dashboard)'!$E$25)+U13,0) -> 0 | W13: =IF(B13<='Input sheet(dashboard)'!$D$27*12,J13-I13+V13-N13,0) -> 1364231.2 | X13: =IF(B13<='Input sheet(dashboard)'!$D$27*12,'Input sheet(dashboard)'!$D$17*(1+'Input sheet(dashboard)'!$E$23)^(B13-1),0) -> 26870.489 | AB13: =IF(B13=1,'Input sheet(dashboard)'!$D$18*Calculations!X13,IF(Calculations!B13=12*'Input sheet(dashboard)'!$D$27,'Input sheet(dashboard)'!$D$18*-Calculations!X13,0)) -> 0 | AC13: =IF(B13<='Input sheet(dashboard)'!$D$27*12,IF(MOD(B12,'Input sheet(dashboard)'!$D$19*12),0,'Input sheet(dashboard)'!$D$20*(1+'Input sheet(dashboard)'!$E$22)^Calculations!B13),0) -> 0 | AD13: =X13+Y13+AB13+AC13 -> 26870.489 | AF13: =S13-AD13 -> 27437.225 | AG13: =IF(AF13>0,AF13,0) -> 27437.225 | AH13: =IF(B13<='Input sheet(dashboard)'!$D$27*12,AH12*(1+'Input sheet(dashboard)'!$E$25)+AG13," ") -> 1270043.8
B14: =B13+1 -> 11 | C14: 1 | D14: 11 | E14: =IF(C14<='Input sheet(dashboard)'!$D$6, -PMT('Input sheet(dashboard)'!$E$5,'Input sheet(dashboard)'!$D$6*12,'Input sheet(dashboard)'!$D$3*'Input sheet(dashboard)'!$D$4),0) -> 39834.138 | F14: =I13*'Input sheet(dashboard)'!$E$5 -> 28677.163 | G14: =IF(C14<='Input sheet(dashboard)'!$D$6,E14*'Input sheet(dashboard)'!$D$7,0) -> 3186.731 | H14: =E14-F14 -> 11156.975 | I14: =I13-H14 -> 7861153.4 | J14: =IF(B14<='Input sheet(dashboard)'!$D$27*12,'Input sheet(dashboard)'!$D$3*(1+'Input sheet(dashboard)'!$E$24)^B14,0) -> 9274172.4 | K14: =IF(B14<='Input sheet(dashboard)'!$D$27*12,J14*'Input sheet(dashboard)'!$E$8,0) -> 9605.6871 | L14: =IF(B14<='Input sheet(dashboard)'!$D$27*12,'Input sheet(dashboard)'!$D$9*(1+'Input sheet(dashboard)'!$E$22)^B14,0) -> 3068.679 | M14: =IF(B14=1,'Input sheet(dashboard)'!$D$3*'Input sheet(dashboard)'!$D$10,0) -> 0 | N14: =IF(B14='Input sheet(dashboard)'!$D$27*12,J14*'Input sheet(dashboard)'!$D$11,0) -> 0 | O14: =IF(SUM(F14:F25)>=150000,150000/12*'Input sheet(dashboard)'!$D$28,SUM(F14:F25)/12*'Input sheet(dashboard)'!$D$28) -> 1875 | Q14: =IF(B14<='Input sheet(dashboard)'!$D$27*12,'Input sheet(dashboard)'!$D$12/12,0) -> 192.5 | R14: =IF(B14<='Input sheet(dashboard)'!$D$27*12,('Input sheet(dashboard)'!$D$15/12)*(1+'Input sheet(dashboard)'!$E$22)^Calculations!B14,0) -> 340.96434 | S14: =IF(B14<='Input sheet(dashboard)'!$D$27*12,(E14+G14+K14+L14-O14+M14+Q14+R14),0) -> 54353.699 | U14: =IF(B14<='Input sheet(dashboard)'!$D$27*12,IF(S14<AD14,AD14-S14,0),0) -> 0 | V14: =IF(B14<='Input sheet(dashboard)'!$D$27*12,V13*(1+'Input sheet(dashboard)'!$E$25)+U14,0) -> 0 | W14: =IF(B14<='Input sheet(dashboard)'!$D$27*12,J14-I14+V14-N14,0) -> 1413019 | X14: =IF(B14<='Input sheet(dashboard)'!$D$27*12,'Input sheet(dashboard)'!$D$17*(1+'Input sheet(dashboard)'!$E$23)^(B14-1),0) -> 26979.963 | AB14: =IF(B14=1,'Input sheet(dashboard)'!$D$18*Calculations!X14,IF(Calculations!B14=12*'Input sheet(dashboard)'!$D$27,'Input sheet(dashboard)'!$D$18*-Calculations!X14,0)) -> 0 | AC14: =IF(B14<='Input sheet(dashboard)'!$D$27*12,IF(MOD(B13,'Input sheet(dashboard)'!$D$19*12),0,'Input sheet(dashboard)'!$D$20*(1+'Input sheet(dashboard)'!$E$22)^Calculations!B14),0) -> 0 | AD14: =X14+Y14+AB14+AC14 -> 26979.963 | AF14: =S14-AD14 -> 27373.737 | AG14: =IF(AF14>0,AF14,0) -> 27373.737 | AH14: =IF(B14<='Input sheet(dashboard)'!$D$27*12,AH13*(1+'Input sheet(dashboard)'!$E$25)+AG14," ") -> 1305589
B15: =B14+1 -> 12 | C15: 1 | D15: 12 | E15: =IF(C15<='Input sheet(dashboard)'!$D$6, -PMT('Input sheet(dashboard)'!$E$5,'Input sheet(dashboard)'!$D$6*12,'Input sheet(dashboard)'!$D$3*'Input sheet(dashboard)'!$D$4),0) -> 39834.138 | F15: =I14*'Input sheet(dashboard)'!$E$5 -> 28636.52 | G15: =IF(C15<='Input sheet(dashboard)'!$D$6,E15*'Input sheet(dashboard)'!$D$7,0) -> 3186.731 | H15: =E15-F15 -> 11197.618 | I15: =I14-H15 -> 7849955.8 | J15: =IF(B15<='Input sheet(dashboard)'!$D$27*12,'Input sheet(dashboard)'!$D$3*(1+'Input sheet(dashboard)'!$E$24)^B15,0) -> 9311956.5 | K15: =IF(B15<='Input sheet(dashboard)'!$D$27*12,J15*'Input sheet(dashboard)'!$E$8,0) -> 9644.8218 | L15: =IF(B15<='Input sheet(dashboard)'!$D$27*12,'Input sheet(dashboard)'!$D$9*(1+'Input sheet(dashboard)'!$E$22)^B15,0) -> 3075 | M15: =IF(B15=1,'Input sheet(dashboard)'!$D$3*'Input sheet(dashboard)'!$D$10,0) -> 0 | N15: =IF(B15='Input sheet(dashboard)'!$D$27*12,J15*'Input sheet(dashboard)'!$D$11,0) -> 0 | O15: =IF(SUM(F15:F26)>=150000,150000/12*'Input sheet(dashboard)'!$D$28,SUM(F15:F26)/12*'Input sheet(dashboard)'!$D$28) -> 1875 | P15: =IF(D15=12,IF(SUM(F4:F16)>=150000,150000*0.15,SUM(F4:F16)*0.15),0) -> 22500 | Q15: =IF(B15<='Input sheet(dashboard)'!$D$27*12,'Input sheet(dashboard)'!$D$12/12,0) -> 192.5 | R15: =IF(B15<='Input sheet(dashboard)'!$D$27*12,('Input sheet(dashboard)'!$D$15/12)*(1+'Input sheet(dashboard)'!$E$22)^Calculations!B15,0) -> 341.66667 | S15: =IF(B15<='Input sheet(dashboard)'!$D$27*12,(E15+G15+K15+L15-O15+M15+Q15+R15),0) -> 54399.857 | T15: =IF(B15<='Input sheet(dashboard)'!$D$27*12,IF(D15=12,SUM(S4:S15),0),0) -> 738474.94 | U15: =IF(B15<='Input sheet(dashboard)'!$D$27*12,IF(S15<AD15,AD15-S15,0),0) -> 0 | V15: =IF(B15<='Input sheet(dashboard)'!$D$27*12,V14*(1+'Input sheet(dashboard)'!$E$25)+U15,0) -> 0 | W15: =IF(B15<='Input sheet(dashboard)'!$D$27*12,J15-I15+V15-N15,0) -> 1462000.7 | X15: =IF(B15<='Input sheet(dashboard)'!$D$27*12,'Input sheet(dashboard)'!$D$17*(1+'Input sheet(dashboard)'!$E$23)^(B15-1),0) -> 27089.882 | AB15: =IF(B15=1,'Input sheet(dashboard)'!$D$18*Calculations!X15,IF(Calculations!B15=12*'Input sheet(dashboard)'!$D$27,'Input sheet(dashboard)'!$D$18*-Calculations!X15,0)) -> 0 | AC15: =IF(B15<='Input sheet(dashboard)'!$D$27*12,IF(MOD(B14,'Input sheet(dashboard)'!$D$19*12),0,'Input sheet(dashboard)'!$D$20*(1+'Input sheet(dashboard)'!$E$22)^Calculations!B15),0) -> 0 | AD15: =X15+Y15+AB15+AC15 -> 27089.882 | AE15: =IF(B15<='Input sheet(dashboard)'!$D$27*12,IF(D15=12,SUM(AD4:AD15),0),0) -> 369731.12 | AF15: =S15-AD15 -> 27309.975 | AG15: =IF(AF15>0,AF15,0) -> 27309.975 | AH15: =IF(B15<='Input sheet(dashboard)'!$D$27*12,AH14*(1+'Input sheet(dashboard)'!$E$25)+AG15," ") -> 1341299.2
B16: =B15+1 -> 13 | C16: =C4+1 -> 2 | D16: =D4 -> 1 | E16: =IF(C16<='Input sheet(dashboard)'!$D$6, -PMT('Input sheet(dashboard)'!$E$5,'Input sheet(dashboard)'!$D$6*12,'Input sheet(dashboard)'!$D$3*'Input sheet(dashboard)'!$D$4),0) -> 39834.138 | F16: =I15*'Input sheet(dashboard)'!$E$5 -> 28595.73 | G16: =IF(C16<='Input sheet(dashboard)'!$D$6,E16*'Input sheet(dashboard)'!$D$7,0) -> 3186.731 | H16: =E16-F16 -> 11238.408 | I16: =I15-H16 -> 7838717.4 | J16: =IF(B16<='Input sheet(dashboard)'!$D$27*12,'Input sheet(dashboard)'!$D$3*(1+'Input sheet(dashboard)'!$E$24)^B16,0) -> 9349894.6 | K16: =IF(B16<='Input sheet(dashboard)'!$D$27*12,J16*'Input sheet(dashboard)'!$E$8,0) -> 9684.116 | L16: =IF(B16<='Input sheet(dashboard)'!$D$27*12,'Input sheet(dashboard)'!$D$9*(1+'Input sheet(dashboard)'!$E$22)^B16,0) -> 3081.334 | M16: =IF(B16=1,'Input sheet(dashboard)'!$D$3*'Input sheet(dashboard)'!$D$10,0) -> 0 | N16: =IF(B16='Input sheet(dashboard)'!$D$27*12,J16*'Input sheet(dashboard)'!$D$11,0) -> 0 | O16: =IF(SUM(F16:F27)>=150000,150000/12*'Input sheet(dashboard)'!$D$28,SUM(F16:F27)/12*'Input sheet(dashboard)'!$D$28) -> 1875 | P16: =IF(D16=12,IF(SUM(F5:F17)>=150000,150000*0.15,SUM(F5:F17)*0.15),0) -> 0 | Q16: =IF(B16<='Input sheet(dashboard)'!$D$27*12,'Input sheet(dashboard)'!$D$12/12,0) -> 192.5 | R16: =IF(B16<='Input sheet(dashboard)'!$D$27*12,('Input sheet(dashboard)'!$D$15/12)*(1+'Input sheet(dashboard)'!$E$22)^Calculations!B16,0) -> 342.37044 | S16: =IF(B16<='Input sheet(dashboard)'!$D$27*12,(E16+G16+K16+L16-O16+M16+Q16+R16),0) -> 54446.189 | T16: =IF(B16<='Input sheet(dashboard)'!$D$27*12,IF(D16=12,SUM(S5:S16),0),0) -> 0 | U16: =IF(B16<='Input sheet(dashboard)'!$D$27*12,IF(S16<AD16,AD16-S16,0),0) -> 0 | V16: =IF(B16<='Input sheet(dashboard)'!$D$27*12,V15*(1+'Input sheet(dashboard)'!$E$25)+U16,0) -> 0 | W16: =IF(B16<='Input sheet(dashboard)'!$D$27*12,J16-I16+V16-N16,0) -> 1511177.2 | X16: =IF(B16<='Input sheet(dashboard)'!$D$27*12,'Input sheet(dashboard)'!$D$17*(1+'Input sheet(dashboard)'!$E$23)^(B16-1),0) -> 27200.25 | AB16: =IF(B16=1,'Input sheet(dashboard)'!$D$18*Calculations!X16,IF(Calculations!B16=12*'Input sheet(dashboard)'!$D$27,'Input sheet(dashboard)'!$D$18*-Calculations!X16,0)) -> 0 | AC16: =IF(B16<='Input sheet(dashboard)'!$D$27*12,IF(MOD(B15,'Input sheet(dashboard)'!$D$19*12),0,'Input sheet(dashboard)'!$D$20*(1+'Input sheet(dashboard)'!$E$22)^Calculations!B16),0) -> 0 | AD16: =X16+Y16+AB16+AC16 -> 27200.25 | AE16: =IF(B16<='Input sheet(dashboard)'!$D$27*12,IF(D16=12,SUM(AD5:AD16),0),0) -> 0 | AF16: =S16-AD16 -> 27245.939 | AG16: =IF(AF16>0,AF16,0) -> 27245.939 | AH16: =IF(B16<='Input sheet(dashboard)'!$D$27*12,AH15*(1+'Input sheet(dashboard)'!$E$25)+AG16," ") -> 1377175.1
B17: =B16+1 -> 14 | C17: =C5+1 -> 2 | D17: =D5 -> 2 | E17: =IF(C17<='Input sheet(dashboard)'!$D$6, -PMT('Input sheet(dashboard)'!$E$5,'Input sheet(dashboard)'!$D$6*12,'Input sheet(dashboard)'!$D$3*'Input sheet(dashboard)'!$D$4),0) -> 39834.138 | F17: =I16*'Input sheet(dashboard)'!$E$5 -> 28554.791 | G17: =IF(C17<='Input sheet(dashboard)'!$D$6,E17*'Input sheet(dashboard)'!$D$7,0) -> 3186.731 | H17: =E17-F17 -> 11279.347 | I17: =I16-H17 -> 7827438 | J17: =IF(B17<='Input sheet(dashboard)'!$D$27*12,'Input sheet(dashboard)'!$D$3*(1+'Input sheet(dashboard)'!$E$24)^B17,0) -> 9387987.2 | K17: =IF(B17<='Input sheet(dashboard)'!$D$27*12,J17*'Input sheet(dashboard)'!$E$8,0) -> 9723.5703 | L17: =IF(B17<='Input sheet(dashboard)'!$D$27*12,'Input sheet(dashboard)'!$D$9*(1+'Input sheet(dashboard)'!$E$22)^B17,0) -> 3087.681 | M17: =IF(B17=1,'Input sheet(dashboard)'!$D$3*'Input sheet(dashboard)'!$D$10,0) -> 0 | N17: =IF(B17='Input sheet(dashboard)'!$D$27*12,J17*'Input sheet(dashboard)'!$D$11,0) -> 0 | O17: =IF(SUM(F17:F28)>=150000,150000/12*'Input sheet(dashboard)'!$D$28,SUM(F17:F28)/12*'Input sheet(dashboard)'!$D$28) -> 1875 | P17: =IF(D17=12,IF(SUM(F6:F18)>=150000,150000*0.15,SUM(F6:F18)*0.15),0) -> 0 | Q17: =IF(B17<='Input sheet(dashboard)'!$D$27*12,'Input sheet(dashboard)'!$D$12/12,0) -> 192.5 | R17: =IF(B17<='Input sheet(dashboard)'!$D$27*12,('Input sheet(dashboard)'!$D$15/12)*(1+'Input sheet(dashboard)'!$E$22)^Calculations!B17,0) -> 343.07567 | S17: =IF(B17<='Input sheet(dashboard)'!$D$27*12,(E17+G17+K17+L17-O17+M17+Q17+R17),0) -> 54492.696 | T17: =IF(B17<='Input sheet(dashboard)'!$D$27*12,IF(D17=12,SUM(S6:S17),0),0) -> 0 | U17: =IF(B17<='Input sheet(dashboard)'!$D$27*12,IF(S17<AD17,AD17-S17,0),0) -> 0 | V17: =IF(B17<='Input sheet(dashboard)'!$D$27*12,V16*(1+'Input sheet(dashboard)'!$E$25)+U17,0) -> 0 | W17: =IF(B17<='Input sheet(dashboard)'!$D$27*12,J17-I17+V17-N17,0) -> 1560549.1 | X17: =IF(B17<='Input sheet(dashboard)'!$D$27*12,'Input sheet(dashboard)'!$D$17*(1+'Input sheet(dashboard)'!$E$23)^(B17-1),0) -> 27311.067 | AB17: =IF(B17=1,'Input sheet(dashboard)'!$D$18*Calculations!X17,IF(Calculations!B17=12*'Input sheet(dashboard)'!$D$27,'Input sheet(dashboard)'!$D$18*-Calculations!X17,0)) -> 0 | AC17: =IF(B17<='Input sheet(dashboard)'!$D$27*12,IF(MOD(B16,'Input sheet(dashboard)'!$D$19*12),0,'Input sheet(dashboard)'!$D$20*(1+'Input sheet(dashboard)'!$E$22)^Calculations!B17),0) -> 0 | AD17: =X17+Y17+AB17+AC17 -> 27311.067 | AE17: =IF(B17<='Input sheet(dashboard)'!$D$27*12,IF(D17=12,SUM(AD6:AD17),0),0) -> 0 | AF17: =S17-AD17 -> 27181.629 | AG17: =IF(AF17>0,AF17,0) -> 27181.629 | AH17: =IF(B17<='Input sheet(dashboard)'!$D$27*12,AH16*(1+'Input sheet(dashboard)'!$E$25)+AG17," ") -> 1413217.5
B18: =B17+1 -> 15 | C18: =C6+1 -> 2 | D18: =D6 -> 3 | E18: =IF(C18<='Input sheet(dashboard)'!$D$6, -PMT('Input sheet(dashboard)'!$E$5,'Input sheet(dashboard)'!$D$6*12,'Input sheet(dashboard)'!$D$3*'Input sheet(dashboard)'!$D$4),0) -> 39834.138 | F18: =I17*'Input sheet(dashboard)'!$E$5 -> 28513.702 | G18: =IF(C18<='Input sheet(dashboard)'!$D$6,E18*'Input sheet(dashboard)'!$D$7,0) -> 3186.731 | H18: =E18-F18 -> 11320.436 | I18: =I17-H18 -> 7816117.6 | J18: =IF(B18<='Input sheet(dashboard)'!$D$27*12,'Input sheet(dashboard)'!$D$3*(1+'Input sheet(dashboard)'!$E$24)^B18,0) -> 9426235 | K18: =IF(B18<='Input sheet(dashboard)'!$D$27*12,J18*'Input sheet(dashboard)'!$E$8,0) -> 9763.1853 | L18: =IF(B18<='Input sheet(dashboard)'!$D$27*12,'Input sheet(dashboard)'!$D$9*(1+'Input sheet(dashboard)'!$E$22)^B18,0) -> 3094.0412 | M18: =IF(B18=1,'Input sheet(dashboard)'!$D$3*'Input sheet(dashboard)'!$D$10,0) -> 0 | N18: =IF(B18='Input sheet(dashboard)'!$D$27*12,J18*'Input sheet(dashboard)'!$D$11,0) -> 0 | O18: =IF(SUM(F18:F29)>=150000,150000/12*'Input sheet(dashboard)'!$D$28,SUM(F18:F29)/12*'Input sheet(dashboard)'!$D$28) -> 1875 | P18: =IF(D18=12,IF(SUM(F7:F19)>=150000,150000*0.15,SUM(F7:F19)*0.15),0) -> 0 | Q18: =IF(B18<='Input sheet(dashboard)'!$D$27*12,'Input sheet(dashboard)'!$D$12/12,0) -> 192.5 | R18: =IF(B18<='Input sheet(dashboard)'!$D$27*12,('Input sheet(dashboard)'!$D$15/12)*(1+'Input sheet(dashboard)'!$E$22)^Calculations!B18,0) -> 343.78235 | S18: =IF(B18<='Input sheet(dashboard)'!$D$27*12,(E18+G18+K18+L18-O18+M18+Q18+R18),0) -> 54539.378 | T18: =IF(B18<='Input sheet(dashboard)'!$D$27*12,IF(D18=12,SUM(S7:S18),0),0) -> 0 | U18: =IF(B18<='Input sheet(dashboard)'!$D$27*12,IF(S18<AD18,AD18-S18,0),0) -> 0 | V18: =IF(B18<='Input sheet(dashboard)'!$D$27*12,V17*(1+'Input sheet(dashboard)'!$E$25)+U18,0) -> 0 | W18: =IF(B18<='Input sheet(dashboard)'!$D$27*12,J18-I18+V18-N18,0) -> 1610117.4 | X18: =IF(B18<='Input sheet(dashboard)'!$D$27*12,'Input sheet(dashboard)'!$D$17*(1+'Input sheet(dashboard)'!$E$23)^(B18-1),0) -> 27422.336 | AB18: =IF(B18=1,'Input sheet(dashboard)'!$D$18*Calculations!X18,IF(Calculations!B18=12*'Input sheet(dashboard)'!$D$27,'Input sheet(dashboard)'!$D$18*-Calculations!X18,0)) -> 0 | AC18: =IF(B18<='Input sheet(dashboard)'!$D$27*12,IF(MOD(B17,'Input sheet(dashboard)'!$D$19*12),0,'Input sheet(dashboard)'!$D$20*(1+'Input sheet(dashboard)'!$E$22)^Calculations!B18),0) -> 0 | AD18: =X18+Y18+AB18+AC18 -> 27422.336 | AE18: =IF(B18<='Input sheet(dashboard)'!$D$27*12,IF(D18=12,SUM(AD7:AD18),0),0) -> 0 | AF18: =S18-AD18 -> 27117.042 | AG18: =IF(AF18>0,AF18,0) -> 27117.042 | AH18: =IF(B18<='Input sheet(dashboard)'!$D$27*12,AH17*(1+'Input sheet(dashboard)'!$E$25)+AG18," ") -> 1449427.3
B19: =B18+1 -> 16 | C19: =C7+1 -> 2 | D19: =D7 -> 4 | E19: =IF(C19<='Input sheet(dashboard)'!$D$6, -PMT('Input sheet(dashboard)'!$E$5,'Input sheet(dashboard)'!$D$6*12,'Input sheet(dashboard)'!$D$3*'Input sheet(dashboard)'!$D$4),0) -> 39834.138 | F19: =I18*'Input sheet(dashboard)'!$E$5 -> 28472.464 | G19: =IF(C19<='Input sheet(dashboard)'!$D$6,E19*'Input sheet(dashboard)'!$D$7,0) -> 3186.731 | H19: =E19-F19 -> 11361.673 | I19: =I18-H19 -> 7804755.9 | J19: =IF(B19<='Input sheet(dashboard)'!$D$27*12,'Input sheet(dashboard)'!$D$3*(1+'Input sheet(dashboard)'!$E$24)^B19,0) -> 9464638.7 | K19: =IF(B19<='Input sheet(dashboard)'!$D$27*12,J19*'Input sheet(dashboard)'!$E$8,0) -> 9802.9618 | L19: =IF(B19<='Input sheet(dashboard)'!$D$27*12,'Input sheet(dashboard)'!$D$9*(1+'Input sheet(dashboard)'!$E$22)^B19,0) -> 3100.4144 | M19: =IF(B19=1,'Input sheet(dashboard)'!$D$3*'Input sheet(dashboard)'!$D$10,0) -> 0 | N19: =IF(B19='Input sheet(dashboard)'!$D$27*12,J19*'Input sheet(dashboard)'!$D$11,0) -> 0 | O19: =IF(SUM(F19:F30)>=150000,150000/12*'Input sheet(dashboard)'!$D$28,SUM(F19:F30)/12*'Input sheet(dashboard)'!$D$28) -> 1875 | P19: =IF(D19=12,IF(SUM(F8:F20)>=150000,150000*0.15,SUM(F8:F20)*0.15),0) -> 0 | Q19: =IF(B19<='Input sheet(dashboard)'!$D$27*12,'Input sheet(dashboard)'!$D$12/12,0) -> 192.5 | R19: =IF(B19<='Input sheet(dashboard)'!$D$27*12,('Input sheet(dashboard)'!$D$15/12)*(1+'Input sheet(dashboard)'!$E$22)^Calculations!B19,0) -> 344.49049 | S19: =IF(B19<='Input sheet(dashboard)'!$D$27*12,(E19+G19+K19+L19-O19+M19+Q19+R19),0) -> 54586.236 | T19: =IF(B19<='Input sheet(dashboard)'!$D$27*12,IF(D19=12,SUM(S8:S19),0),0) -> 0 | U19: =IF(B19<='Input sheet(dashboard)'!$D$27*12,IF(S19<AD19,AD19-S19,0),0) -> 0 | V19: =IF(B19<='Input sheet(dashboard)'!$D$27*12,V18*(1+'Input sheet(dashboard)'!$E$25)+U19,0) -> 0 | W19: =IF(B19<='Input sheet(dashboard)'!$D$27*12,J19-I19+V19-N19,0) -> 1659882.7 | X19: =IF(B19<='Input sheet(dashboard)'!$D$27*12,'Input sheet(dashboard)'!$D$17*(1+'Input sheet(dashboard)'!$E$23)^(B19-1),0) -> 27534.058 | AB19: =IF(B19=1,'Input sheet(dashboard)'!$D$18*Calculations!X19,IF(Calculations!B19=12*'Input sheet(dashboard)'!$D$27,'Input sheet(dashboard)'!$D$18*-Calculations!X19,0)) -> 0 | AC19: =IF(B19<='Input sheet(dashboard)'!$D$27*12,IF(MOD(B18,'Input sheet(dashboard)'!$D$19*12),0,'Input sheet(dashboard)'!$D$20*(1+'Input sheet(dashboard)'!$E$22)^Calculations!B19),0) -> 0 | AD19: =X19+Y19+AB19+AC19 -> 27534.058 | AE19: =IF(B19<='Input sheet(dashboard)'!$D$27*12,IF(D19=12,SUM(AD8:AD19),0),0) -> 0 | AF19: =S19-AD19 -> 27052.178 | AG19: =IF(AF19>0,AF19,0) -> 27052.178 | AH19: =IF(B19<='Input sheet(dashboard)'!$D$27*12,AH18*(1+'Input sheet(dashboard)'!$E$25)+AG19," ") -> 1485805.1
B20: =B19+1 -> 17 | C20: =C8+1 -> 2 | D20: =D8 -> 5 | E20: =IF(C20<='Input sheet(dashboard)'!$D$6, -PMT('Input sheet(dashboard)'!$E$5,'Input sheet(dashboard)'!$D$6*12,'Input sheet(dashboard)'!$D$3*'Input sheet(dashboard)'!$D$4),0) -> 39834.138 | F20: =I19*'Input sheet(dashboard)'!$E$5 -> 28431.076 | G20: =IF(C20<='Input sheet(dashboard)'!$D$6,E20*'Input sheet(dashboard)'!$D$7,0) -> 3186.731 | H20: =E20-F20 -> 11403.062 | I20: =I19-H20 -> 7793352.9 | J20: =IF(B20<='Input sheet(dashboard)'!$D$27*12,'Input sheet(dashboard)'!$D$3*(1+'Input sheet(dashboard)'!$E$24)^B20,0) -> 9503198.8 | K20: =IF(B20<='Input sheet(dashboard)'!$D$27*12,J20*'Input sheet(dashboard)'!$E$8,0) -> 9842.9003 | L20: =IF(B20<='Input sheet(dashboard)'!$D$27*12,'Input sheet(dashboard)'!$D$9*(1+'Input sheet(dashboard)'!$E$22)^B20,0) -> 3106.8007 | M20: =IF(B20=1,'Input sheet(dashboard)'!$D$3*'Input sheet(dashboard)'!$D$10,0) -> 0 | N20: =IF(B20='Input sheet(dashboard)'!$D$27*12,J20*'Input sheet(dashboard)'!$D$11,0) -> 0 | O20: =IF(SUM(F20:F31)>=150000,150000/12*'Input sheet(dashboard)'!$D$28,SUM(F20:F31)/12*'Input sheet(dashboard)'!$D$28) -> 1875 | P20: =IF(D20=12,IF(SUM(F9:F21)>=150000,150000*0.15,SUM(F9:F21)*0.15),0) -> 0 | Q20: =IF(B20<='Input sheet(dashboard)'!$D$27*12,'Input sheet(dashboard)'!$D$12/12,0) -> 192.5 | R20: =IF(B20<='Input sheet(dashboard)'!$D$27*12,('Input sheet(dashboard)'!$D$15/12)*(1+'Input sheet(dashboard)'!$E$22)^Calculations!B20,0) -> 345.20008 | S20: =IF(B20<='Input sheet(dashboard)'!$D$27*12,(E20+G20+K20+L20-O20+M20+Q20+R20),0) -> 54633.27 | T20: =IF(B20<='Input sheet(dashboard)'!$D$27*12,IF(D20=12,SUM(S9:S20),0),0) -> 0 | U20: =IF(B20<='Input sheet(dashboard)'!$D$27*12,IF(S20<AD20,AD20-S20,0),0) -> 0 | V20: =IF(B20<='Input sheet(dashboard)'!$D$27*12,V19*(1+'Input sheet(dashboard)'!$E$25)+U20,0) -> 0 | W20: =IF(B20<='Input sheet(dashboard)'!$D$27*12,J20-I20+V20-N20,0) -> 1709845.9 | X20: =IF(B20<='Input sheet(dashboard)'!$D$27*12,'Input sheet(dashboard)'!$D$17*(1+'Input sheet(dashboard)'!$E$23)^(B20-1),0) -> 27646.235 | AB20: =IF(B20=1,'Input sheet(dashboard)'!$D$18*Calculations!X20,IF(Calculations!B20=12*'Input sheet(dashboard)'!$D$27,'Input sheet(dashboard)'!$D$18*-Calculations!X20,0)) -> 0 | AC20: =IF(B20<='Input sheet(dashboard)'!$D$27*12,IF(MOD(B19,'Input sheet(dashboard)'!$D$19*12),0,'Input sheet(dashboard)'!$D$20*(1+'Input sheet(dashboard)'!$E$22)^Calculations!B20),0) -> 0 | AD20: =X20+Y20+AB20+AC20 -> 27646.235 | AE20: =IF(B20<='Input sheet(dashboard)'!$D$27*12,IF(D20=12,SUM(AD9:AD20),0),0) -> 0 | AF20: =S20-AD20 -> 26987.035 | AG20: =IF(AF20>0,AF20,0) -> 26987.035 | AH20: =IF(B20<='Input sheet(dashboard)'!$D$27*12,AH19*(1+'Input sheet(dashboard)'!$E$25)+AG20," ") -> 1522351.8
B21: =B20+1 -> 18 | C21: =C9+1 -> 2 | D21: =D9 -> 6 | E21: =IF(C21<='Input sheet(dashboard)'!$D$6, -PMT('Input sheet(dashboard)'!$E$5,'Input sheet(dashboard)'!$D$6*12,'Input sheet(dashboard)'!$D$3*'Input sheet(dashboard)'!$D$4),0) -> 39834.138 | F21: =I20*'Input sheet(dashboard)'!$E$5 -> 28389.537 | G21: =IF(C21<='Input sheet(dashboard)'!$D$6,E21*'Input sheet(dashboard)'!$D$7,0) -> 3186.731 | H21: =E21-F21 -> 11444.601 | I21: =I20-H21 -> 7781908.3 | J21: =IF(B21<='Input sheet(dashboard)'!$D$27*12,'Input sheet(dashboard)'!$D$3*(1+'Input sheet(dashboard)'!$E$24)^B21,0) -> 9541916 | K21: =IF(B21<='Input sheet(dashboard)'!$D$27*12,J21*'Input sheet(dashboard)'!$E$8,0) -> 9883.0014 | L21: =IF(B21<='Input sheet(dashboard)'!$D$27*12,'Input sheet(dashboard)'!$D$9*(1+'Input sheet(dashboard)'!$E$22)^B21,0) -> 3113.2002 | M21: =IF(B21=1,'Input sheet(dashboard)'!$D$3*'Input sheet(dashboard)'!$D$10,0) -> 0 | N21: =IF(B21='Input sheet(dashboard)'!$D$27*12,J21*'Input sheet(dashboard)'!$D$11,0) -> 0 | O21: =IF(SUM(F21:F32)>=150000,150000/12*'Input sheet(dashboard)'!$D$28,SUM(F21:F32)/12*'Input sheet(dashboard)'!$D$28) -> 1875 | P21: =IF(D21=12,IF(SUM(F10:F22)>=150000,150000*0.15,SUM(F10:F22)*0.15),0) -> 0 | Q21: =IF(B21<='Input sheet(dashboard)'!$D$27*12,'Input sheet(dashboard)'!$D$12/12,0) -> 192.5 | R21: =IF(B21<='Input sheet(dashboard)'!$D$27*12,('Input sheet(dashboard)'!$D$15/12)*(1+'Input sheet(dashboard)'!$E$22)^Calculations!B21,0) -> 345.91114 | S21: =IF(B21<='Input sheet(dashboard)'!$D$27*12,(E21+G21+K21+L21-O21+M21+Q21+R21),0) -> 54680.482 | T21: =IF(B21<='Input sheet(dashboard)'!$D$27*12,IF(D21=12,SUM(S10:S21),0),0) -> 0 | U21: =IF(B21<='Input sheet(dashboard)'!$D$27*12,IF(S21<AD21,AD21-S21,0),0) -> 0 | V21: =IF(B21<='Input sheet(dashboard)'!$D$27*12,V20*(1+'Input sheet(dashboard)'!$E$25)+U21,0) -> 0 | W21: =IF(B21<='Input sheet(dashboard)'!$D$27*12,J21-I21+V21-N21,0) -> 1760007.7 | X21: =IF(B21<='Input sheet(dashboard)'!$D$27*12,'Input sheet(dashboard)'!$D$17*(1+'Input sheet(dashboard)'!$E$23)^(B21-1),0) -> 27758.869 | AB21: =IF(B21=1,'Input sheet(dashboard)'!$D$18*Calculations!X21,IF(Calculations!B21=12*'Input sheet(dashboard)'!$D$27,'Input sheet(dashboard)'!$D$18*-Calculations!X21,0)) -> 0 | AC21: =IF(B21<='Input sheet(dashboard)'!$D$27*12,IF(MOD(B20,'Input sheet(dashboard)'!$D$19*12),0,'Input sheet(dashboard)'!$D$20*(1+'Input sheet(dashboard)'!$E$22)^Calculations!B21),0) -> 0 | AD21: =X21+Y21+AB21+AC21 -> 27758.869 | AE21: =IF(B21<='Input sheet(dashboard)'!$D$27*12,IF(D21=12,SUM(AD10:AD21),0),0) -> 0 | AF21: =S21-AD21 -> 26921.613 | AG21: =IF(AF21>0,AF21,0) -> 26921.613 | AH21: =IF(B21<='Input sheet(dashboard)'!$D$27*12,AH20*(1+'Input sheet(dashboard)'!$E$25)+AG21," ") -> 1559068.3
B22: =B21+1 -> 19 | C22: =C10+1 -> 2 | D22: =D10 -> 7 | E22: =IF(C22<='Input sheet(dashboard)'!$D$6, -PMT('Input sheet(dashboard)'!$E$5,'Input sheet(dashboard)'!$D$6*12,'Input sheet(dashboard)'!$D$3*'Input sheet(dashboard)'!$D$4),0) -> 39834.138 | F22: =I21*'Input sheet(dashboard)'!$E$5 -> 28347.847 | G22: =IF(C22<='Input sheet(dashboard)'!$D$6,E22*'Input sheet(dashboard)'!$D$7,0) -> 3186.731 | H22: =E22-F22 -> 11486.291 | I22: =I21-H22 -> 7770422 | J22: =IF(B22<='Input sheet(dashboard)'!$D$27*12,'Input sheet(dashboard)'!$D$3*(1+'Input sheet(dashboard)'!$E$24)^B22,0) -> 9580790.9 | K22: =IF(B22<='Input sheet(dashboard)'!$D$27*12,J22*'Input sheet(dashboard)'!$E$8,0) -> 9923.266 | L22: =IF(B22<='Input sheet(dashboard)'!$D$27*12,'Input sheet(dashboard)'!$D$9*(1+'Input sheet(dashboard)'!$E$22)^B22,0) -> 3119.6129 | M22: =IF(B22=1,'Input sheet(dashboard)'!$D$3*'Input sheet(dashboard)'!$D$10,0) -> 0 | N22: =IF(B22='Input sheet(dashboard)'!$D$27*12,J22*'Input sheet(dashboard)'!$D$11,0) -> 0 | O22: =IF(SUM(F22:F33)>=150000,150000/12*'Input sheet(dashboard)'!$D$28,SUM(F22:F33)/12*'Input sheet(dashboard)'!$D$28) -> 1875 | P22: =IF(D22=12,IF(SUM(F11:F23)>=150000,150000*0.15,SUM(F11:F23)*0.15),0) -> 0 | Q22: =IF(B22<='Input sheet(dashboard)'!$D$27*12,'Input sheet(dashboard)'!$D$12/12,0) -> 192.5 | R22: =IF(B22<='Input sheet(dashboard)'!$D$27*12,('Input sheet(dashboard)'!$D$15/12)*(1+'Input sheet(dashboard)'!$E$22)^Calculations!B22,0) -> 346.62366 | S22: =IF(B22<='Input sheet(dashboard)'!$D$27*12,(E22+G22+K22+L22-O22+M22+Q22+R22),0) -> 54727.872 | T22: =IF(B22<='Input sheet(dashboard)'!$D$27*12,IF(D22=12,SUM(S11:S22),0),0) -> 0 | U22: =IF(B22<='Input sheet(dashboard)'!$D$27*12,IF(S22<AD22,AD22-S22,0),0) -> 0 | V22: =IF(B22<='Input sheet(dashboard)'!$D$27*12,V21*(1+'Input sheet(dashboard)'!$E$25)+U22,0) -> 0 | W22: =IF(B22<='Input sheet(dashboard)'!$D$27*12,J22-I22+V22-N22,0) -> 1810368.9 | X22: =IF(B22<='Input sheet(dashboard)'!$D$27*12,'Input sheet(dashboard)'!$D$17*(1+'Input sheet(dashboard)'!$E$23)^(B22-1),0) -> 27871.962 | AB22: =IF(B22=1,'Input sheet(dashboard)'!$D$18*Calculations!X22,IF(Calculations!B22=12*'Input sheet(dashboard)'!$D$27,'Input sheet(dashboard)'!$D$18*-Calculations!X22,0)) -> 0 | AC22: =IF(B22<='Input sheet(dashboard)'!$D$27*12,IF(MOD(B21,'Input sheet(dashboard)'!$D$19*12),0,'Input sheet(dashboard)'!$D$20*(1+'Input sheet(dashboard)'!$E$22)^Calculations!B22),0) -> 0 | AD22: =X22+Y22+AB22+AC22 -> 27871.962 | AE22: =IF(B22<='Input sheet(dashboard)'!$D$27*12,IF(D22=12,SUM(AD11:AD22),0),0) -> 0 | AF22: =S22-AD22 -> 26855.909 | AG22: =IF(AF22>0,AF22,0) -> 26855.909 | AH22: =IF(B22<='Input sheet(dashboard)'!$D$27*12,AH21*(1+'Input sheet(dashboard)'!$E$25)+AG22," ") -> 1595955.3
B23: =B22+1 -> 20 | C23: =C11+1 -> 2 | D23: =D11 -> 8 | E23: =IF(C23<='Input sheet(dashboard)'!$D$6, -PMT('Input sheet(dashboard)'!$E$5,'Input sheet(dashboard)'!$D$6*12,'Input sheet(dashboard)'!$D$3*'Input sheet(dashboard)'!$D$4),0) -> 39834.138 | F23: =I22*'Input sheet(dashboard)'!$E$5 -> 28306.005 | G23: =IF(C23<='Input sheet(dashboard)'!$D$6,E23*'Input sheet(dashboard)'!$D$7,0) -> 3186.731 | H23: =E23-F23 -> 11528.133 | I23: =I22-H23 -> 7758893.9 | J23: =IF(B23<='Input sheet(dashboard)'!$D$27*12,'Input sheet(dashboard)'!$D$3*(1+'Input sheet(dashboard)'!$E$24)^B23,0) -> 9619824.3 | K23: =IF(B23<='Input sheet(dashboard)'!$D$27*12,J23*'Input sheet(dashboard)'!$E$8,0) -> 9963.6946 | L23: =IF(B23<='Input sheet(dashboard)'!$D$27*12,'Input sheet(dashboard)'!$D$9*(1+'Input sheet(dashboard)'!$E$22)^B23,0) -> 3126.0388 | M23: =IF(B23=1,'Input sheet(dashboard)'!$D$3*'Input sheet(dashboard)'!$D$10,0) -> 0 | N23: =IF(B23='Input sheet(dashboard)'!$D$27*12,J23*'Input sheet(dashboard)'!$D$11,0) -> 0 | O23: =IF(SUM(F23:F34)>=150000,150000/12*'Input sheet(dashboard)'!$D$28,SUM(F23:F34)/12*'Input sheet(dashboard)'!$D$28) -> 1875 | P23: =IF(D23=12,IF(SUM(F12:F24)>=150000,150000*0.15,SUM(F12:F24)*0.15),0) -> 0 | Q23: =IF(B23<='Input sheet(dashboard)'!$D$27*12,'Input sheet(dashboard)'!$D$12/12,0) -> 192.5 | R23: =IF(B23<='Input sheet(dashboard)'!$D$27*12,('Input sheet(dashboard)'!$D$15/12)*(1+'Input sheet(dashboard)'!$E$22)^Calculations!B23,0) -> 347.33764 | S23: =IF(B23<='Input sheet(dashboard)'!$D$27*12,(E23+G23+K23+L23-O23+M23+Q23+R23),0) -> 54775.44 | T23: =IF(B23<='Input sheet(dashboard)'!$D$27*12,IF(D23=12,SUM(S12:S23),0),0) -> 0 | U23: =IF(B23<='Input sheet(dashboard)'!$D$27*12,IF(S23<AD23,AD23-S23,0),0) -> 0 | V23: =IF(B23<='Input sheet(dashboard)'!$D$27*12,V22*(1+'Input sheet(dashboard)'!$E$25)+U23,0) -> 0 | W23: =IF(B23<='Input sheet(dashboard)'!$D$27*12,J23-I23+V23-N23,0) -> 1860930.4 | X23: =IF(B23<='Input sheet(dashboard)'!$D$27*12,'Input sheet(dashboard)'!$D$17*(1+'Input sheet(dashboard)'!$E$23)^(B23-1),0) -> 27985.516 | AB23: =IF(B23=1,'Input sheet(dashboard)'!$D$18*Calculations!X23,IF(Calculations!B23=12*'Input sheet(dashboard)'!$D$27,'Input sheet(dashboard)'!$D$18*-Calculations!X23,0)) -> 0 | AC23: =IF(B23<='Input sheet(dashboard)'!$D$27*12,IF(MOD(B22,'Input sheet(dashboard)'!$D$19*12),0,'Input sheet(dashboard)'!$D$20*(1+'Input sheet(dashboard)'!$E$22)^Calculations!B23),0) -> 0 | AD23: =X23+Y23+AB23+AC23 -> 27985.516 | AE23: =IF(B23<='Input sheet(dashboard)'!$D$27*12,IF(D23=12,SUM(AD12:AD23),0),0) -> 0 | AF23: =S23-AD23 -> 26789.924 | AG23: =IF(AF23>0,AF23,0) -> 26789.924 | AH23: =IF(B23<='Input sheet(dashboard)'!$D$27*12,AH22*(1+'Input sheet(dashboard)'!$E$25)+AG23," ") -> 1633013.7
B24: =B23+1 -> 21 | C24: =C12+1 -> 2 | D24: =D12 -> 9 | E24: =IF(C24<='Input sheet(dashboard)'!$D$6, -PMT('Input sheet(dashboard)'!$E$5,'Input sheet(dashboard)'!$D$6*12,'Input sheet(dashboard)'!$D$3*'Input sheet(dashboard)'!$D$4),0) -> 39834.138 | F24: =I23*'Input sheet(dashboard)'!$E$5 -> 28264.01 | G24: =IF(C24<='Input sheet(dashboard)'!$D$6,E24*'Input sheet(dashboard)'!$D$7,0) -> 3186.731 | H24: =E24-F24 -> 11570.128 | I24: =I23-H24 -> 7747323.7 | J24: =IF(B24<='Input sheet(dashboard)'!$D$27*12,'Input sheet(dashboard)'!$D$3*(1+'Input sheet(dashboard)'!$E$24)^B24,0) -> 9659016.6 | K24: =IF(B24<='Input sheet(dashboard)'!$D$27*12,J24*'Input sheet(dashboard)'!$E$8,0) -> 10004.288 | L24: =IF(B24<='Input sheet(dashboard)'!$D$27*12,'Input sheet(dashboard)'!$D$9*(1+'Input sheet(dashboard)'!$E$22)^B24,0) -> 3132.4779 | M24: =IF(B24=1,'Input sheet(dashboard)'!$D$3*'Input sheet(dashboard)'!$D$10,0) -> 0 | N24: =IF(B24='Input sheet(dashboard)'!$D$27*12,J24*'Input sheet(dashboard)'!$D$11,0) -> 0 | O24: =IF(SUM(F24:F35)>=150000,150000/12*'Input sheet(dashboard)'!$D$28,SUM(F24:F35)/12*'Input sheet(dashboard)'!$D$28) -> 1875 | P24: =IF(D24=12,IF(SUM(F13:F25)>=150000,150000*0.15,SUM(F13:F25)*0.15),0) -> 0 | Q24: =IF(B24<='Input sheet(dashboard)'!$D$27*12,'Input sheet(dashboard)'!$D$12/12,0) -> 192.5 | R24: =IF(B24<='Input sheet(dashboard)'!$D$27*12,('Input sheet(dashboard)'!$D$15/12)*(1+'Input sheet(dashboard)'!$E$22)^Calculations!B24,0) -> 348.0531 | S24: =IF(B24<='Input sheet(dashboard)'!$D$27*12,(E24+G24+K24+L24-O24+M24+Q24+R24),0) -> 54823.188 | T24: =IF(B24<='Input sheet(dashboard)'!$D$27*12,IF(D24=12,SUM(S13:S24),0),0) -> 0 | U24: =IF(B24<='Input sheet(dashboard)'!$D$27*12,IF(S24<AD24,AD24-S24,0),0) -> 0 | V24: =IF(B24<='Input sheet(dashboard)'!$D$27*12,V23*(1+'Input sheet(dashboard)'!$E$25)+U24,0) -> 0 | W24: =IF(B24<='Input sheet(dashboard)'!$D$27*12,J24-I24+V24-N24,0) -> 1911692.9 | X24: =IF(B24<='Input sheet(dashboard)'!$D$27*12,'Input sheet(dashboard)'!$D$17*(1+'Input sheet(dashboard)'!$E$23)^(B24-1),0) -> 28099.533 | AB24: =IF(B24=1,'Input sheet(dashboard)'!$D$18*Calculations!X24,IF(Calculations!B24=12*'Input sheet(dashboard)'!$D$27,'Input sheet(dashboard)'!$D$18*-Calculations!X24,0)) -> 0 | AC24: =IF(B24<='Input sheet(dashboard)'!$D$27*12,IF(MOD(B23,'Input sheet(dashboard)'!$D$19*12),0,'Input sheet(dashboard)'!$D$20*(1+'Input sheet(dashboard)'!$E$22)^Calculations!B24),0) -> 0 | AD24: =X24+Y24+AB24+AC24 -> 28099.533 | AE24: =IF(B24<='Input sheet(dashboard)'!$D$27*12,IF(D24=12,SUM(AD13:AD24),0),0) -> 0 | AF24: =S24-AD24 -> 26723.655 | AG24: =IF(AF24>0,AF24,0) -> 26723.655 | AH24: =IF(B24<='Input sheet(dashboard)'!$D$27*12,AH23*(1+'Input sheet(dashboard)'!$E$25)+AG24," ") -> 1670244.2
B25: =B24+1 -> 22 | C25: =C13+1 -> 2 | D25: =D13 -> 10 | E25: =IF(C25<='Input sheet(dashboard)'!$D$6, -PMT('Input sheet(dashboard)'!$E$5,'Input sheet(dashboard)'!$D$6*12,'Input sheet(dashboard)'!$D$3*'Input sheet(dashboard)'!$D$4),0) -> 39834.138 | F25: =I24*'Input sheet(dashboard)'!$E$5 -> 28221.863 | G25: =IF(C25<='Input sheet(dashboard)'!$D$6,E25*'Input sheet(dashboard)'!$D$7,0) -> 3186.731 | H25: =E25-F25 -> 11612.275 | I25: =I24-H25 -> 7735711.5 | J25: =IF(B25<='Input sheet(dashboard)'!$D$27*12,'Input sheet(dashboard)'!$D$3*(1+'Input sheet(dashboard)'!$E$24)^B25,0) -> 9698368.6 | K25: =IF(B25<='Input sheet(dashboard)'!$D$27*12,J25*'Input sheet(dashboard)'!$E$8,0) -> 10045.047 | L25: =IF(B25<='Input sheet(dashboard)'!$D$27*12,'Input sheet(dashboard)'!$D$9*(1+'Input sheet(dashboard)'!$E$22)^B25,0) -> 3138.9303 | M25: =IF(B25=1,'Input sheet(dashboard)'!$D$3*'Input sheet(dashboard)'!$D$10,0) -> 0 | N25: =IF(B25='Input sheet(dashboard)'!$D$27*12,J25*'Input sheet(dashboard)'!$D$11,0) -> 0 | O25: =IF(SUM(F25:F36)>=150000,150000/12*'Input sheet(dashboard)'!$D$28,SUM(F25:F36)/12*'Input sheet(dashboard)'!$D$28) -> 1875 | P25: =IF(D25=12,IF(SUM(F14:F26)>=150000,150000*0.15,SUM(F14:F26)*0.15),0) -> 0 | Q25: =IF(B25<='Input sheet(dashboard)'!$D$27*12,'Input sheet(dashboard)'!$D$12/12,0) -> 192.5 | R25: =IF(B25<='Input sheet(dashboard)'!$D$27*12,('Input sheet(dashboard)'!$D$15/12)*(1+'Input sheet(dashboard)'!$E$22)^Calculations!B25,0) -> 348.77004 | S25: =IF(B25<='Input sheet(dashboard)'!$D$27*12,(E25+G25+K25+L25-O25+M25+Q25+R25),0) -> 54871.116 | T25: =IF(B25<='Input sheet(dashboard)'!$D$27*12,IF(D25=12,SUM(S14:S25),0),0) -> 0 | U25: =IF(B25<='Input sheet(dashboard)'!$D$27*12,IF(S25<AD25,AD25-S25,0),0) -> 0 | V25: =IF(B25<='Input sheet(dashboard)'!$D$27*12,V24*(1+'Input sheet(dashboard)'!$E$25)+U25,0) -> 0 | W25: =IF(B25<='Input sheet(dashboard)'!$D$27*12,J25-I25+V25-N25,0) -> 1962657.2 | X25: =IF(B25<='Input sheet(dashboard)'!$D$27*12,'Input sheet(dashboard)'!$D$17*(1+'Input sheet(dashboard)'!$E$23)^(B25-1),0) -> 28214.014 | AB25: =IF(B25=1,'Input sheet(dashboard)'!$D$18*Calculations!X25,IF(Calculations!B25=12*'Input sheet(dashboard)'!$D$27,'Input sheet(dashboard)'!$D$18*-Calculations!X25,0)) -> 0 | AC25: =IF(B25<='Input sheet(dashboard)'!$D$27*12,IF(MOD(B24,'Input sheet(dashboard)'!$D$19*12),0,'Input sheet(dashboard)'!$D$20*(1+'Input sheet(dashboard)'!$E$22)^Calculations!B25),0) -> 0 | AD25: =X25+Y25+AB25+AC25 -> 28214.014 | AE25: =IF(B25<='Input sheet(dashboard)'!$D$27*12,IF(D25=12,SUM(AD14:AD25),0),0) -> 0 | AF25: =S25-AD25 -> 26657.102 | AG25: =IF(AF25>0,AF25,0) -> 26657.102 | AH25: =IF(B25<='Input sheet(dashboard)'!$D$27*12,AH24*(1+'Input sheet(dashboard)'!$E$25)+AG25," ") -> 1707647.7
B26: =B25+1 -> 23 | C26: =C14+1 -> 2 | D26: =D14 -> 11 | E26: =IF(C26<='Input sheet(dashboard)'!$D$6, -PMT('Input sheet(dashboard)'!$E$5,'Input sheet(dashboard)'!$D$6*12,'Input sheet(dashboard)'!$D$3*'Input sheet(dashboard)'!$D$4),0) -> 39834.138 | F26: =I25*'Input sheet(dashboard)'!$E$5 -> 28179.562 | G26: =IF(C26<='Input sheet(dashboard)'!$D$6,E26*'Input sheet(dashboard)'!$D$7,0) -> 3186.731 | H26: =E26-F26 -> 11654.576 | I26: =I25-H26 -> 7724056.9 | J26: =IF(B26<='Input sheet(dashboard)'!$D$27*12,'Input sheet(dashboard)'!$D$3*(1+'Input sheet(dashboard)'!$E$24)^B26,0) -> 9737881 | K26: =IF(B26<='Input sheet(dashboard)'!$D$27*12,J26*'Input sheet(dashboard)'!$E$8,0) -> 10085.971 | L26: =IF(B26<='Input sheet(dashboard)'!$D$27*12,'Input sheet(dashboard)'!$D$9*(1+'Input sheet(dashboard)'!$E$22)^B26,0) -> 3145.396 | M26: =IF(B26=1,'Input sheet(dashboard)'!$D$3*'Input sheet(dashboard)'!$D$10,0) -> 0 | N26: =IF(B26='Input sheet(dashboard)'!$D$27*12,J26*'Input sheet(dashboard)'!$D$11,0) -> 0 | O26: =IF(SUM(F26:F37)>=150000,150000/12*'Input sheet(dashboard)'!$D$28,SUM(F26:F37)/12*'Input sheet(dashboard)'!$D$28) -> 1875 | P26: =IF(D26=12,IF(SUM(F15:F27)>=150000,150000*0.15,SUM(F15:F27)*0.15),0) -> 0 | Q26: =IF(B26<='Input sheet(dashboard)'!$D$27*12,'Input sheet(dashboard)'!$D$12/12,0) -> 192.5 | R26: =IF(B26<='Input sheet(dashboard)'!$D$27*12,('Input sheet(dashboard)'!$D$15/12)*(1+'Input sheet(dashboard)'!$E$22)^Calculations!B26,0) -> 349.48844 | S26: =IF(B26<='Input sheet(dashboard)'!$D$27*12,(E26+G26+K26+L26-O26+M26+Q26+R26),0) -> 54919.225 | T26: =IF(B26<='Input sheet(dashboard)'!$D$27*12,IF(D26=12,SUM(S15:S26),0),0) -> 0 | U26: =IF(B26<='Input sheet(dashboard)'!$D$27*12,IF(S26<AD26,AD26-S26,0),0) -> 0 | V26: =IF(B26<='Input sheet(dashboard)'!$D$27*12,V25*(1+'Input sheet(dashboard)'!$E$25)+U26,0) -> 0 | W26: =IF(B26<='Input sheet(dashboard)'!$D$27*12,J26-I26+V26-N26,0) -> 2013824.1 | X26: =IF(B26<='Input sheet(dashboard)'!$D$27*12,'Input sheet(dashboard)'!$D$17*(1+'Input sheet(dashboard)'!$E$23)^(B26-1),0) -> 28328.961 | AB26: =IF(B26=1,'Input sheet(dashboard)'!$D$18*Calculations!X26,IF(Calculations!B26=12*'Input sheet(dashboard)'!$D$27,'Input sheet(dashboard)'!$D$18*-Calculations!X26,0)) -> 0 | AC26: =IF(B26<='Input sheet(dashboard)'!$D$27*12,IF(MOD(B25,'Input sheet(dashboard)'!$D$19*12),0,'Input sheet(dashboard)'!$D$20*(1+'Input sheet(dashboard)'!$E$22)^Calculations!B26),0) -> 0 | AD26: =X26+Y26+AB26+AC26 -> 28328.961 | AE26: =IF(B26<='Input sheet(dashboard)'!$D$27*12,IF(D26=12,SUM(AD15:AD26),0),0) -> 0 | AF26: =S26-AD26 -> 26590.264 | AG26: =IF(AF26>0,AF26,0) -> 26590.264 | AH26: =IF(B26<='Input sheet(dashboard)'!$D$27*12,AH25*(1+'Input sheet(dashboard)'!$E$25)+AG26," ") -> 1745225
B27: =B26+1 -> 24 | C27: =C15+1 -> 2 | D27: =D15 -> 12 | E27: =IF(C27<='Input sheet(dashboard)'!$D$6, -PMT('Input sheet(dashboard)'!$E$5,'Input sheet(dashboard)'!$D$6*12,'Input sheet(dashboard)'!$D$3*'Input sheet(dashboard)'!$D$4),0) -> 39834.138 | F27: =I26*'Input sheet(dashboard)'!$E$5 -> 28137.107 | G27: =IF(C27<='Input sheet(dashboard)'!$D$6,E27*'Input sheet(dashboard)'!$D$7,0) -> 3186.731 | H27: =E27-F27 -> 11697.031 | I27: =I26-H27 -> 7712359.8 | J27: =IF(B27<='Input sheet(dashboard)'!$D$27*12,'Input sheet(dashboard)'!$D$3*(1+'Input sheet(dashboard)'!$E$24)^B27,0) -> 9777554.3 | K27: =IF(B27<='Input sheet(dashboard)'!$D$27*12,J27*'Input sheet(dashboard)'!$E$8,0) -> 10127.063 | L27: =IF(B27<='Input sheet(dashboard)'!$D$27*12,'Input sheet(dashboard)'!$D$9*(1+'Input sheet(dashboard)'!$E$22)^B27,0) -> 3151.875 | M27: =IF(B27=1,'Input sheet(dashboard)'!$D$3*'Input sheet(dashboard)'!$D$10,0) -> 0 | N27: =IF(B27='Input sheet(dashboard)'!$D$27*12,J27*'Input sheet(dashboard)'!$D$11,0) -> 0 | O27: =IF(SUM(F27:F38)>=150000,150000/12*'Input sheet(dashboard)'!$D$28,SUM(F27:F38)/12*'Input sheet(dashboard)'!$D$28) -> 1875 | P27: =IF(D27=12,IF(SUM(F16:F28)>=150000,150000*0.15,SUM(F16:F28)*0.15),0) -> 22500 | Q27: =IF(B27<='Input sheet(dashboard)'!$D$27*12,'Input sheet(dashboard)'!$D$12/12,0) -> 192.5 | R27: =IF(B27<='Input sheet(dashboard)'!$D$27*12,('Input sheet(dashboard)'!$D$15/12)*(1+'Input sheet(dashboard)'!$E$22)^Calculations!B27,0) -> 350.20833 | S27: =IF(B27<='Input sheet(dashboard)'!$D$27*12,(E27+G27+K27+L27-O27+M27+Q27+R27),0) -> 54967.515 | T27: =IF(B27<='Input sheet(dashboard)'!$D$27*12,IF(D27=12,SUM(S16:S27),0),0) -> 656462.61 | U27: =IF(B27<='Input sheet(dashboard)'!$D$27*12,IF(S27<AD27,AD27-S27,0),0) -> 0 | V27: =IF(B27<='Input sheet(dashboard)'!$D$27*12,V26*(1+'Input sheet(dashboard)'!$E$25)+U27,0) -> 0 | W27: =IF(B27<='Input sheet(dashboard)'!$D$27*12,J27-I27+V27-N27,0) -> 2065194.5 | X27: =IF(B27<='Input sheet(dashboard)'!$D$27*12,'Input sheet(dashboard)'!$D$17*(1+'Input sheet(dashboard)'!$E$23)^(B27-1),0) -> 28444.377 | AB27: =IF(B27=1,'Input sheet(dashboard)'!$D$18*Calculations!X27,IF(Calculations!B27=12*'Input sheet(dashboard)'!$D$27,'Input sheet(dashboard)'!$D$18*-Calculations!X27,0)) -> 0 | AC27: =IF(B27<='Input sheet(dashboard)'!$D$27*12,IF(MOD(B26,'Input sheet(dashboard)'!$D$19*12),0,'Input sheet(dashboard)'!$D$20*(1+'Input sheet(dashboard)'!$E$22)^Calculations!B27),0) -> 0 | AD27: =X27+Y27+AB27+AC27 -> 28444.377 | AE27: =IF(B27<='Input sheet(dashboard)'!$D$27*12,IF(D27=12,SUM(AD16:AD27),0),0) -> 333817.18 | AF27: =S27-AD27 -> 26523.139 | AG27: =IF(AF27>0,AF27,0) -> 26523.139 | AH27: =IF(B27<='Input sheet(dashboard)'!$D$27*12,AH26*(1+'Input sheet(dashboard)'!$E$25)+AG27," ") -> 1782977
... B723: =B722+1 -> 720 | C723: =C711+1 -> 60 | D723: =D711 -> 12 | E723: =IF(C723<='Input sheet(dashboard)'!$D$6, -PMT('Input sheet(dashboard)'!$E$5,'Input sheet(dashboard)'!$D$6*12,'Input sheet(dashboard)'!$D$3*'Input sheet(dashboard)'!$D$4),0) -> 0 | F723: =I722*'Input sheet(dashboard)'!$E$5 -> 2.7867016e-11 | G723: =IF(C723<='Input sheet(dashboard)'!$D$6,E723*'Input sheet(dashboard)'!$D$7,0) -> 0 | H723: =E723-F723 -> -2.7867016e-11 | I723: =I722-H723 -> 7.67778e-09 | J723: =IF(B723<='Input sheet(dashboard)'!$D$27*12,'Input sheet(dashboard)'!$D$3*(1+'Input sheet(dashboard)'!$E$24)^B723,0) -> 0 | K723: =IF(B723<='Input sheet(dashboard)'!$D$27*12,J723*'Input sheet(dashboard)'!$E$8,0) -> 0 | L723: =IF(B723<='Input sheet(dashboard)'!$D$27*12,'Input sheet(dashboard)'!$D$9*(1+'Input sheet(dashboard)'!$E$22)^B723,0) -> 0 | M723: =IF(B723=1,'Input sheet(dashboard)'!$D$3*'Input sheet(dashboard)'!$D$10,0) -> 0 | N723: =IF(B723='Input sheet(dashboard)'!$D$27*12,J723*'Input sheet(dashboard)'!$D$11,0) -> 0 | O723: =IF(SUM(F723:F734)>=150000,150000/12*'Input sheet(dashboard)'!$D$28,SUM(F723:F734)/12*'Input sheet(dashboard)'!$D$28) -> 3.483377e-13 | P723: =IF(D723=12,IF(SUM(F712:F724)>=150000,150000*0.15,SUM(F712:F724)*0.15),0) -> 4.9171308e-11 | Q723: =IF(B723<='Input sheet(dashboard)'!$D$27*12,'Input sheet(dashboard)'!$D$12/12,0) -> 0 | R723: =IF(B723<='Input sheet(dashboard)'!$D$27*12,('Input sheet(dashboard)'!$D$15/12)*(1+'Input sheet(dashboard)'!$E$22)^Calculations!B723,0) -> 0 | S723: =IF(B723<='Input sheet(dashboard)'!$D$27*12,(E723+G723+K723+L723-O723+M723+Q723+R723),0) -> 0 | T723: =IF(B723<='Input sheet(dashboard)'!$D$27*12,IF(D723=12,SUM(S712:S723),0),0) -> 0 | U723: =IF(B723<='Input sheet(dashboard)'!$D$27*12,IF(S723<AD723,AD723-S723,0),0) -> 0 | V723: =IF(B723<='Input sheet(dashboard)'!$D$27*12,V722*(1+'Input sheet(dashboard)'!$E$25)+U723,0) -> 0 | W723: =IF(B723<='Input sheet(dashboard)'!$D$27*12,J723-I723+V723-N723,0) -> 0 | X723: =IF(B723<='Input sheet(dashboard)'!$D$27*12,'Input sheet(dashboard)'!$D$17*(1+'Input sheet(dashboard)'!$E$23)^(B723-1),0) -> 0 | AB723: =IF(B723=1,'Input sheet(dashboard)'!$D$18*Calculations!X723,IF(Calculations!B723=12*'Input sheet(dashboard)'!$D$27,'Input sheet(dashboard)'!$D$18*-Calculations!X723,0)) -> 0 | AC723: =IF(B723<='Input sheet(dashboard)'!$D$27*12,IF(MOD(B722,'Input sheet(dashboard)'!$D$19*12),0,'Input sheet(dashboard)'!$D$20*(1+'Input sheet(dashboard)'!$E$22)^Calculations!B723),0) -> 0 | AD723: =X723+Y723+AB723+AC723 -> 0 | AE723: =IF(B723<='Input sheet(dashboard)'!$D$27*12,IF(D723=12,SUM(AD712:AD723),0),0) -> 0 | AF723: =S723-AD723 -> 0 | AG723: =IF(AF723>0,AF723,0) -> 0 | AH723: =IF(B723<='Input sheet(dashboard)'!$D$27*12,AH722*(1+'Input sheet(dashboard)'!$E$25)+AG723," ")

Sheet Results>>>

Sheet Results summary
B4: Sensitivity testing inputs | F4: BASELINE INPUTS
B5: Mortgage interest rate | C5: 0.025 | D5: 3 | E5: 3.5 | F5: 4.46 | G5: 5.5
B6: Repairs | E6: 0.01 | F6: 0.0125 | G6: 0.015
B7: SVJ | E7: 2000 | F7: 3000 | G7: 4000
B8: Rent growth | D8: 3 | E8: 4 | F8: 5 | G8: 6 | H8: 7
B9: Real estate price growth | D9: 3 | E9: 4 | F9: 5 | G9: 6 | H9: 7
B10: Investment return | D10: 6 | E10: 7 | F10: 8 | G10: 9 | H10: 10
T13: Input assumption | U13: Unit
T14: Buying | W14: (monthly reculculation if applicable)
B15: RESULTS | T15: Flatprice | U15: czk | V15: 8868530
B16: Case | C16: variable changed | D16: value | E16: Buy | F16: Rent | G16: Difference | H16: Winner | I16: Buy liquidity | J16: Buy liqudity in % | K16: Net worth Crossover year | L16: Annual costs Crossover year | M16: Monthly mortgage payment | N16: Required net income(based on DSTI) | T16: LTV | U16: % | V16: 0.9
B17: baseline | C17: / | D17: / | E17: 83391236 | F17: 62067437 | G17: 21323798 | H17: BUY | I17: 21581228 | J17: 0.25879492 | L17: 20 | M17: 39834.138 | N17: 99585.345 | T17: Interest(annual) | U17: % | V17: 0.0446 | W17: =((1+V17)^(1/12))-1 -> 0.0036427886
B18: M1 | C18: Mortgage interest rate | D18: 0.025 | E18: 88831713 | F18: 40457899 | G18: 48373814 | H18: BUY | I18: 27021705 | J18: 0.30418985 | L18: 14 | M18: 31420.388 | N18: 78550.97 | T18: Time to maturity | U18: years | V18: 30
B19: M2 | C19: Mortgage interest rate | D19: 0.03 | E19: 87230774 | F19: 45336683 | G19: 41894091 | H19: BUY | I19: 25420766 | J19: 0.2914197 | L19: 16 | M19: 33477.084 | N19: 83692.71 | T19: Mortgage Insurance (% of mortgage payment) | U19: % | V19: 0.08 | W19: =((1+V19)^(1/12))-1 -> 0.0064340301
B20: M3 | C20: Mortgage interest rate | D20: 0.035 | E20: 85786946 | F20: 50702586 | G20: 35084360 | H20: BUY | I20: 23976939 | J20: 0.27949402 | L20: 17 | M20: 35597.045 | N20: 88992.612 | T20: Repairs(annual % of property value) | U20: % | V20: 0.0125 | W20: =((1+V20)^(1/12))-1 -> 0.001035746
B21: M4 | C21: Mortgage interest rate | D21: 0.055 | E21: 81372732 | F21: 75783242 | G21: 5589489.5 | H21: BUY | I21: 19562724 | J21: 0.24040884 | L21: 22 | M21: 44650.515 | N21: 111626.29 | T21: Other fees(house admin, repair fund, monthly) | U21: czk | V21: 3000
B22: Rep1 | C22: Repairs | D22: 0.01 | E22: 88266182 | F22: 55516545 | G22: 32749637 | H22: BUY | I22: 26456174 | J22: 0.29973171 | L22: 17 | M22: 39834.138 | N22: 99585.345 | T22: Purchase costs | U22: % | V22: 0.01
B23: Rep2 | C23: Repairs | D23: 0.015 | E23: 79168914 | F23: 69245123 | G23: 9923791.6 | H23: BUY | I23: 17358907 | J23: 0.21926417 | L23: 22 | M23: 39834.138 | N23: 99585.345 | T23: Selling costs | U23: % | V23: 0.01
B24: SVJ1 | C24: SVJ fees | D24: 2000 | E24: 84713435 | F24: 59027993 | G24: 25685442 | H24: BUY | I24: 22903428 | J24: 0.27036358 | L24: 18 | M24: 39834.138 | N24: 99585.345 | T24: Relestate tax (annual) | U24: czk | V24: 2310
B25: SVJ2 | C25: SVJ fees | D25: 4000 | E25: 82147993 | F25: 65185838 | G25: 16962155 | H25: BUY | I25: 20337985 | J25: 0.24757738 | L25: 20 | M25: 39834.138 | N25: 99585.345 | T25: Interest Tax deduction limit | U25: czk | V25: 150000
B26: RG1 | C26: Rent growth | D26: 0.03 | E26: 65805084 | F26: 85136124 | G26: 19331040 | H26: RENT | I26: 3995076.4 | J26: 0.060710756 | K26: 29 | L26: 31 | M26: 39834.138 | N26: 99585.345 | T26: DSTI | U26: % | V26: 0.4
B27: RG2 | C27: Rent growth | D27: 0.04 | E27: 70972534 | F27: 72120297 | G27: 1147763 | H27: RENT | I27: 9162526.1 | J27: 0.12909961 | K27: 40 | L27: 30 | M27: 39834.138 | N27: 99585.345 | T27: Property insurance (annual) | U27: czk | V27: 4000 | W27: =V27/12 -> 333.33333
B28: RG3 | C28: Rent growth | D28: 0.06 | E28: 1.0486354e+08 | F28: 55569351 | G28: 49294191 | H28: BUY | I28: 43053535 | J28: 0.41056724 | L28: 15 | M28: 39834.138 | N28: 99585.345 | T28: Renting
B29: RG4 | C29: Rent growth | D29: 0.07 | E29: 1.3520699e+08 | F29: 50864090 | G29: 84342899 | H29: BUY | I29: 73396982 | J29: 0.54284902 | L29: 13 | M29: 39834.138 | N29: 99585.345 | T29: Monthly rent | U29: czk | V29: 25905
A30: renting is winning from the 26 to 30th year | B30: PG1 | C30: Real estate price growth | D30: 0.03 | E30: 60328662 | F30: 57631605 | G30: 2697056.8 | H30: BUY | I30: 31688477 | J30: 0.52526404 | K30: 26 | L30: 17 | M30: 39834.138 | N30: 99585.345 | T30: Deposit | U30: months of rent | V30: 2
B31: PG2 | C31: Real estate price growth | D31: 0.04 | E31: 69315574 | F31: 59609639 | G31: 9705935.5 | H31: BUY | I31: 27163359 | J31: 0.39187959 | L31: 18 | M31: 39834.138 | N31: 99585.345 | T31: Moving(how often) | U31: years | V31: =52/12 -> 4.3333333
B32: PG3 | C32: Real estate price growth | D32: 0.06 | E32: 1.0517705e+08 | F32: 65367786 | G32: 39809267 | H32: BUY | I32: 14870047 | J32: 0.14138109 | L32: 22 | M32: 39834.138 | N32: 99585.345 | T32: Moving cost | U32: czk | V32: 8000
B33: PG4 | C33: Real estate price growth | D33: 0.07 | E33: 1.394048e+08 | F33: 70979927 | G33: 68424873 | H33: BUY | I33: 7931385.6 | J33: 0.056894638 | L33: 31 | M33: 39834.138 | N33: 99585.345 | T33: Macro
B34: IR1 | C34: Inv. Ret. | D34: 0.06 | E34: 80649976 | F34: 31578458 | G34: 49071518 | H34: BUY | I34: 18839969 | J34: 0.23360167 | L34: 20 | M34: 39834.138 | N34: 99585.345 | T34: Inflation | U34: % | V34: 0.025 | W34: =((1+V34)^(1/12))-1 -> 0.0020598363
B35: IR2 | C35: Inv. Ret. | D35: 0.07 | E35: 81960037 | F35: 44307282 | G35: 37652756 | H35: BUY | I35: 20150030 | J35: 0.24585188 | L35: 20 | M35: 39834.138 | N35: 99585.345 | T35: Rent growth | U35: % | V35: 0.05 | W35: =((1+V35)^(1/12))-1 -> 0.0040741238
B36: IR3 | C36: Inv. Ret. | D36: 0.09 | E36: 84956672 | F36: 86803205 | G36: 1846532.6 | H36: RENT | I36: 23146665 | J36: 0.27245258 | K36: 39 | L36: 20 | M36: 39834.138 | N36: 99585.345 | T36: Real estate price growth | U36: % | V36: 0.05 | W36: =((1+V36)^(1/12))-1 -> 0.0040741238
B37: IR4 | C37: Inv. Ret. | D37: 0.1 | E37: 86670991 | F37: 1.2119132e+08 | G37: 34520334 | H37: RENT | I37: 24860983 | J37: 0.28684319 | K37: 25 | L37: 20 | M37: 39834.138 | N37: 99585.345 | T37: Investment growth | U37: % | V37: 0.08 | W37: =((1+V37)^(1/12))-1 -> 0.0064340301
B38: LTV 80 | C38: LTV | D38: 0.8 | E38: 86025995 | F38: 69356813 | G38: 16669182 | H38: BUY | I38: 24215988 | J38: 0.28149616 | L38: 17 | M38: 35408.123 | N38: 88520.306 | T38: Further assumptions
T39: Time horizont | U39: years | V39: 40
B41: BRNO BASELINE | C41: base | D41: base | E41: 1.1692554e+08 | F41: 55543170 | G41: 61382368 | H41: BUY | I41: 7229553.6 | J41: 0.061830407 | L41: 27 | M41: 33235.959 | N41: 83089.897
B42: Brno costs | C42: Annual costs in year
C43: 1 | D43: 616448.6 | E43: 352837.34
C44: 10 | D44: 631538.59 | E44: 467560.5
C45: 20 | D45: 815174.86 | E45: 745713.05
C46: 30 | D46: 1186008.4 | E46: 1194342.6
C47: 31 | D47: 805199.18 | E47: 1269147.2
C48: 40 | D48: 1433266.5 | E48: 1896084.3
B51: Prague baseline detail | C51: Annual costs in year
C52: 1 | D52: 734420.97 | E52: 406216.78
C53: 10 | D53: 717220.22 | E53: 538765.6
C54: 20 | D54: 840412.68 | E54: 861698.65
C55: 30 | D55: 1058477.3 | E55: 1383271
C56: 31 | D56: 568040.01 | E56: 1467522
C57: 40 | D57: 856794.91 | E57: 2196348.7

Sheet Sensitivity decomposition
A4: Scenario | B4: Buy terminal NW | C4: Rent terminal NW | D4: Advantage (buy/rent) | E4: Winner | F4: Cros over NW | G4: Cost crossover year | H4: Monthly mortgage payment | I4: Required net income (DSTI) | J4: Buy liquid wealth | K4: Buy liquid % of NW | L4: Total buy cash paid | M4: Total rent cash paid | N4: Terminal property (net) | O4: Cum. mortgage interest | P4: Cum. property insurance | Q4: Cum. repairs | R4: Cum. admin fees | S4: Cum. rent paid | T4: Cum. real estate tax
A5: BASELINE
A6: Prague baseline | B6: 79496192 | C6: 74271374 | D6: 5224817.6 | E6: BUY | G6: 22 | H6: 39834.138 | I6: 88520.306 | J6: 17686184 | K6: 0.22247838 | L6: 32123994 | M6: 38221293 | N6: 61810008 | O6: 6358612.7 | P6: 273247.41 | Q6: 13673276 | R6: 2459226.7 | S6: 38404800 | T6: 92400
A8: HORIZON IN YEARS
A9: 10 | B9: 7935373.4 | C9: 6423545.9 | D9: 1511827.4 | E9: BUY | G9: 0 | H9: 39834.138 | I9: 88520.306 | J9: 0 | K9: 0 | L9: 17046926 | M9: 3985388.3 | N9: 14301442 | O9: 6358612.7 | P9: 45418.088 | Q9: 1423686.4 | R9: 408762.79 | S9: 3998777.7 | T9: 23100
A10: 15 | B10: 13000514 | C10: 10532145 | D10: 2468368.8 | E10: BUY | G10: 0 | H10: 39834.138 | I10: 88520.306 | J10: 0 | K10: 0 | L10: 18389943 | M10: 6834720.9 | N10: 18252667 | O10: 6358612.7 | P10: 72695.355 | Q10: 2442468.7 | R10: 654258.2 | S10: 6860281.1 | T10: 34650
A11: 20 | B11: 19434609 | C11: 15997353 | D11: 3437255.7 | E11: BUY | G11: 0 | H11: 39834.138 | I11: 88520.306 | J11: 5731.8465 | K11: 0.00029492987 | L11: 20061301 | M11: 10469467 | N11: 23295542 | O11: 6358612.7 | P11: 103557.08 | Q11: 3742721.6 | R11: 932013.72 | S11: 10512365 | T11: 46200
A12: 30 | B12: 39293977 | C12: 34485107 | D12: 4808869.7 | E12: BUY | G12: 22 | H12: 39834.138 | I12: 88520.306 | J12: 1347994.2 | K12: 0.034305365 | L12: 24754077 | M12: 21022234 | N12: 37945983 | O12: 6358612.7 | P12: 177979.9 | Q12: 7520185.6 | R12: 1601819.1 | S12: 21122313 | T12: 69300
A13: 50 | B13: 1.6352924e+08 | C13: 1.6020769e+08 | D13: 3321550.2 | E13: BUY | G13: 22 | H13: 39834.138 | I13: 88520.306 | J13: 62847254 | K13: 0.38431814 | L13: 43781981 | M13: 66193571 | N13: 1.0068199e+08 | O13: 6358612.7 | P13: 395197.88 | Q13: 23696013 | R13: 3556780.9 | S13: 66556149 | T13: 115500
A14: 60 | B14: 3.4049344e+08 | C14: 3.4565346e+08 | D14: -5160019.1 | E14: RENT | F14: 58 | G14: 22 | H14: 39834.138 | I14: 88520.306 | J14: 1.7649309e+08 | K14: 0.51834505 | L14: 62331711 | M14: 1.1173819e+08 | N14: 1.6400035e+08 | O14: 6358612.7 | P14: 551304.78 | Q14: 40021994 | R14: 4961743 | S14: 1.1241173e+08 | T14: 138600
A16: MORTGAGE RATE
A17: Mortgage rate 2.5% | B17: 83299911 | C17: 51025078 | D17: 32274833 | E17: BUY | G17: 18 | H17: 31420.388 | I17: 69823.084 | J17: 21489903 | K17: 0.25798231 | L17: 28973404 | M17: 38221293 | N17: 61810008 | O17: 3329662.6 | P17: 273247.41 | Q17: 13673276 | R17: 2459226.7 | S17: 38404800 | T17: 92400
A18: 3 | B18: 82163230 | C18: 56368120 | D18: 25795110 | E18: BUY | G18: 18 | H18: 33477.084 | I18: 74393.52 | J18: 20353222 | K18: 0.24771692 | L18: 29725493 | M18: 38221293 | N18: 61810008 | O18: 4070073.3 | P18: 273247.41 | Q18: 13673276 | R18: 2459226.7 | S18: 38404800 | T18: 92400
A19: 3.5 | B19: 81135259 | C19: 62149880 | D19: 18985379 | E19: BUY | G19: 20 | H19: 35597.045 | I19: 79104.544 | J19: 19325252 | K19: 0.23818562 | L19: 30516917 | M19: 38221293 | N19: 61810008 | O19: 4833259.1 | P19: 273247.41 | Q19: 13673276 | R19: 2459226.7 | S19: 38404800 | T19: 92400
A20: 5.5 | B20: 78150239 | C20: 88659730 | D20: -10509491 | E20: RENT | F20: 25 | G20: 25 | H20: 44650.515 | I20: 99223.367 | J20: 16340231 | K20: 0.20908741 | L20: 33970789 | M20: 38221293 | N20: 61810008 | O20: 8092508.4 | P20: 273247.41 | Q20: 13673276 | R20: 2459226.7 | S20: 38404800 | T20: 92400
A21: payment insurance 6 | B21: 79764229 | C21: 72116735 | D21: 7647494.1 | E21: BUY | G21: 22 | H21: 39834.138 | I21: 88520.306 | J21: 17954222 | K21: 0.22509115 | L21: 31837188 | M21: 38221293 | N21: 61810008 | O21: 6358612.7 | P21: 273247.41 | Q21: 13673276 | R21: 2459226.7 | S21: 38404800 | T21: 92400
A22: payment insurance 10 | B22: 79244471 | C22: 76442330 | D22: 2802141.2 | E22: BUY | G22: 22 | H22: 39834.138 | I22: 88520.306 | J22: 17434464 | K22: 0.22000858 | L22: 32410800 | M22: 38221293 | N22: 61810008 | O22: 6358612.7 | P22: 273247.41 | Q22: 13673276 | R22: 2459226.7 | S22: 38404800 | T22: 92400
A24: RENT GROWTH
A25: Rent growth 3% | B25: 64406366 | C25: 99641715 | D25: -35235350 | E25: RENT | F25: 22 | G25: 31 | H25: 39834.138 | I25: 88520.306 | J25: 2596358.2 | K25: 0.040312136 | L25: 32123994 | M25: 23770970 | N25: 61810008 | O25: 6358612.7 | P25: 273247.41 | Q25: 13673276 | R25: 2459226.7 | S25: 23759805 | T25: 92400
A26: Rent growth 4% | B26: 69513075 | C26: 86644486 | D26: -17131411 | E26: RENT | F26: 28 | G26: 31 | H26: 39834.138 | I26: 88520.306 | J26: 7703067.7 | K26: 0.11081466 | L26: 32123994 | M26: 30009183 | N26: 61810008 | O26: 6358612.7 | P26: 273247.41 | Q26: 13673276 | R26: 2459226.7 | S26: 30077357 | T26: 92400
A27: Rent growth 6% | B27: 99302258 | C27: 66274107 | D27: 33028151 | E27: BUY | G27: 17 | H27: 39834.138 | I27: 88520.306 | J27: 37492250 | K27: 0.37755688 | L27: 32123994 | M27: 49067826 | N27: 61810008 | O27: 6358612.7 | P27: 273247.41 | Q27: 13673276 | R27: 2459226.7 | S27: 49418392 | T27: 92400
A28: Rent growth 7% | B28: 1.283955e+08 | C28: 60559780 | D28: 67835716 | E28: BUY | G28: 14 | H28: 39834.138 | I28: 88520.306 | J28: 66585488 | K28: 0.51859676 | L28: 32123994 | M28: 63433586 | N28: 61810008 | O28: 6358612.7 | P28: 273247.41 | Q28: 13673276 | R28: 2459226.7 | S28: 64025296 | T28: 92400
A30: PRICE GROWTH
A31: 3 | B31: 55390785 | C31: 68792709 | D31: -13401924 | E31: RENT | G31: 19 | H31: 39834.138 | I31: 88520.306 | J31: 26750600 | K31: 0.48294314 | L31: 26561336 | M31: 38221293 | N31: 28640185 | O31: 6358612.7 | P31: 273247.41 | Q31: 8445667 | R31: 2459226.7 | S31: 38404800 | T31: 92400
A32: 4 | B32: 64814650 | C32: 71207695 | D32: -6393045.2 | E32: RENT | F32: 24 | G32: 20 | H32: 39834.138 | I32: 88520.306 | J32: 22662435 | K32: 0.34964988 | L32: 28952071 | M32: 38221293 | N32: 42152216 | O32: 6358612.7 | P32: 273247.41 | Q32: 10699917 | R32: 2459226.7 | S32: 38404800 | T32: 92400
A33: 6 | B33: 1.022301e+08 | C33: 78519815 | D33: 23710287 | E33: BUY | G33: 26 | H33: 39834.138 | I33: 88520.306 | J33: 11923096 | K33: 0.11662999 | L33: 36346920 | M33: 38221293 | N33: 90307006 | O33: 6358612.7 | P33: 273247.41 | Q33: 17608353 | R33: 2459226.7 | S33: 38404800 | T33: 92400
A34: 7 | B34: 1.37956e+08 | C34: 85630110 | D34: 52325892 | E34: BUY | G34: 31 | H34: 39834.138 | I34: 88520.306 | J34: 6482587.4 | K34: 0.046990253 | L34: 41985211 | M34: 38221293 | N34: 1.3147341e+08 | O34: 6358612.7 | P34: 273247.41 | Q34: 22830822 | R34: 2459226.7 | S34: 38404800 | T34: 92400
A36: INVESTMENT RETURN
A37: 6 | B37: 77499772 | C37: 38358919 | D37: 39140853 | E37: BUY | G37: 22 | H37: 39834.138 | I37: 88520.306 | J37: 15689764 | K37: 0.20244917 | L37: 32123994 | M37: 38221293 | N37: 61810008 | O37: 6358612.7 | P37: 273247.41 | Q37: 13673276 | R37: 2459226.7 | S37: 38404800 | T37: 92400
A38: 7 | B38: 78460815 | C38: 53390565 | D38: 25070250 | E38: BUY | G38: 22 | H38: 39834.138 | I38: 88520.306 | J38: 16650807 | K38: 0.21221813 | L38: 32123994 | M38: 38221293 | N38: 61810008 | O38: 6358612.7 | P38: 273247.41 | Q38: 13673276 | R38: 2459226.7 | S38: 38404800 | T38: 92400
A39: 9 | B39: 80612438 | C39: 1.0323628e+08 | D39: -22623841 | E39: RENT | F39: 25 | G39: 22 | H39: 39834.138 | I39: 88520.306 | J39: 18802431 | K39: 0.23324478 | L39: 32123994 | M39: 38221293 | N39: 61810008 | O39: 6358612.7 | P39: 273247.41 | Q39: 13673276 | R39: 2459226.7 | S39: 38404800 | T39: 92400
A40: 10 | B40: 81816712 | C40: 1.4335538e+08 | D40: -61538671 | E40: RENT | F40: 17 | G40: 22 | H40: 39834.138 | I40: 88520.306 | J40: 20006705 | K40: 0.24453078 | L40: 32123994 | M40: 38221293 | N40: 61810008 | O40: 6358612.7 | P40: 273247.41 | Q40: 13673276 | R40: 2459226.7 | S40: 38404800 | T40: 92400
A42: OWNERSHIP COSTS
A43: Repairs 1.0% | B43: 83625580 | C43: 66974923 | D43: 16650656 | E43: BUY | G43: 20 | H43: 39834.138 | I43: 88520.306 | J43: 21815572 | K43: 0.260872 | L43: 29401765 | M43: 38221293 | N43: 61810008 | O43: 6358612.7 | P43: 273247.41 | Q43: 10951048 | R43: 2459226.7 | S43: 38404800 | T43: 92400
A44: Repairs 1.5% | B44: 76021195 | C44: 82196385 | D44: -6175189.2 | E44: RENT | F44: 33 | G44: 25 | H44: 39834.138 | I44: 88520.306 | J44: 14211188 | K44: 0.18693718 | L44: 34840068 | M44: 38221293 | N44: 61810008 | O44: 6358612.7 | P44: 273247.41 | Q44: 16389351 | R44: 2459226.7 | S44: 38404800 | T44: 92400
A45: Admin fees CZK 2,000 | B45: 80558737 | C45: 70972275 | D45: 9586461.5 | E45: BUY | G45: 21 | H45: 39834.138 | I45: 88520.306 | J45: 18748729 | K45: 0.23273365 | L45: 31304252 | M45: 38221293 | N45: 61810008 | O45: 6358612.7 | P45: 273247.41 | Q45: 13673276 | R45: 1639484.5 | S45: 38404800 | T45: 92400
A46: Admin fees CZK 4,000 | B46: 78502365 | C46: 77639191 | D46: 863173.75 | E46: BUY | G46: 23 | H46: 39834.138 | I46: 88520.306 | J46: 16692357 | K46: 0.21263509 | L46: 32943736 | M46: 38221293 | N46: 61810008 | O46: 6358612.7 | P46: 273247.41 | Q46: 13673276 | R46: 3278969 | S46: 38404800 | T46: 92400
A47: property insurance 3000 | B47: 79582019 | C47: 73993731 | D47: 5588288 | E47: BUY | G47: 22 | H47: 39834.138 | I47: 88520.306 | J47: 17772012 | K47: 0.22331692 | L47: 32055682 | M47: 38221293 | N47: 61810008 | O47: 6358612.7 | P47: 204935.56 | Q47: 13673276 | R47: 2459226.7 | S47: 38404800 | T47: 92400
A48: property insurance 5000 | B48: 79410953 | C48: 74549606 | D48: 4861347.3 | E48: BUY | G48: 22 | H48: 39834.138 | I48: 88520.306 | J48: 17600945 | K48: 0.2216438 | L48: 32192306 | M48: 38221293 | N48: 61810008 | O48: 6358612.7 | P48: 341559.27 | Q48: 13673276 | R48: 2459226.7 | S48: 38404800 | T48: 92400
A49: LTV
A50: LTV 80% | B50: 81321019 | C50: 80873986 | D50: 447032.91 | E50: BUY | G50: 20 | H50: 35408.123 | I50: 78684.717 | J50: 19511012 | K50: 0.23992581 | L50: 30416308 | M50: 38221293 | N50: 61810008 | O50: 5652100.1 | P50: 273247.41 | Q50: 13673276 | R50: 2459226.7 | S50: 38404800 | T50: 92400
A51: LTV 70% | B51: 83873931 | C51: 88226513 | D51: -4352582.8 | E51: RENT | F51: 34 | G51: 17 | H51: 30982.107 | I51: 68849.127 | J51: 22063923 | K51: 0.26306056 | L51: 28713117 | M51: 38221293 | N51: 61810008 | O51: 4945587.6 | P51: 273247.41 | Q51: 13673276 | R51: 2459226.7 | S51: 38404800 | T51: 92400
A53: TAX 23 | B53: 79689026 | C53: 71569399 | D53: 8119627.1 | E53: BUY | G53: 22 | H53: 39834.138 | I53: 88520.306 | J53: 17879019 | K53: 0.22435986 | L53: 31817488 | M53: 38221293 | N53: 61810008 | O53: 6358612.7 | P53: 273247.41 | Q53: 13673276 | R53: 2459226.7 | S53: 38404800 | T53: 92400
A54: BRNO
A55: Brno baseline | B55: 66938899 | C55: 60726836 | D55: 6212063.3 | E55: BUY | G55: 22 | H55: 33235.959 | I55: 73857.686 | J55: 15367183 | K55: 0.2295703 | L55: 27196767 | M55: 32721616 | N55: 51571716 | O55: 5305363.7 | P55: 273247.41 | Q55: 11408417 | R55: 2459226.7 | S55: 32860158 | T55: 92400

Sheet Decomposition
A4: CUMULATIVE BUY-SIDE COSTS (over full horizon)
A6: Component | B6: Total (CZK) | C6: % of cash
A7: Mortgage interest | B7: =SUM(Calculations!F4:F723) -> 6358612.7 | C7: =B7/$B$17 -> 0.19793967
A8: Mortgage principal | B8: =SUM(Calculations!H4:H723) -> 7981677 | C8: =B8/$B$17 -> 0.24846465
A9: Payment protection insurance | B9: =SUM(Calculations!G4:G723) -> 1147223.2 | C9: =B9/$B$17 -> 0.035712345
A10: Property insurance | B10: =SUM(Calculations!R4:R723) -> 273247.41 | C10: =B10/$B$17 -> 0.0085060224
A11: Repairs | B11: =SUM(Calculations!K4:K723) -> 13673276 | C11: =B11/$B$17 -> 0.42564061
A12: Admin / SVJ fees | B12: =SUM(Calculations!L4:L723) -> 2459226.7 | C12: =B12/$B$17 -> 0.076554202
A13: Real estate tax | B13: =SUM(Calculations!Q4:Q723) -> 92400 | C13: =B13/$B$17 -> 0.0028763547
A14: Purchase cost (one-time) | B14: =SUM(Calculations!M4:M723) -> 88685.3 | C14: =B14/$B$17 -> 0.0027607184
A15: Selling cost (one-time) | B15: =SUM(Calculations!N4:N723) -> 624343.51 | C15: =B15/$B$17 -> 0.019435426
A16: Tax benefit from interest deduction | B16: =-SUM(Calculations!O4:O723) -> -574698.15 | C16: =B16/$B$17 -> -0.017889997
A17: TOTAL BUY CASH PAID | B17: =SUM(B7:B16) -> 32123994 | C17: =SUM(C7:C16) -> 1
A19: CUMULATIVE RENT-SIDE COSTS (over full horizon)
A21: Component | B21: Total (CZK) | C21: % of cash
A22: Rent | B22: =SUM(Calculations!X4:X723) -> 38404800 | C22: =B22/$B$25 -> 1.0048012
A23: Moving cost | B23: =SUM(Calculations!AC4:AC723) -> 127945 | C23: =B23/$B$25 -> 0.0033474796
A24: Deposit cash flows (net) | B24: =SUM(Calculations!AB4:AB723) -> -311451.84 | C24: =B24/$B$25 -> -0.0081486475
A25: TOTAL RENT CASH PAID | B25: =SUM(B22:B24) -> 38221293 | C25: =SUM(C22:C24) -> 1
A27: TERMINAL DECOMPOSITION (year 40)
A29: Component | B29: Buy | C29: Rent
A30: Total cash paid over horizon | B30: =-B17 -> -32123994 | C30: =-B25 -> -38221293
A31: + Terminal property value (net of selling) | B31: =B53 -> 61810008 | C31: 0
A32: + Terminal investment portfolio | B32: =INDEX(Calculations!V:V,MATCH('Input sheet(dashboard)'!D27*12,Calculations!B:B,0),1) -> 17686184 | C32: =INDEX(Calculations!AH:AH,MATCH('Input sheet(dashboard)'!D27*12,Calculations!B:B,0),1) -> 74271374
A34: Terminal net worth | B34: =B42 -> 79496192 | C34: =B43 -> 74271374
A38: CURRENT SCENARIO SNAPSHOT (for copying into sensitivity table)
A42: Buy terminal NW | B42: ='Input sheet(dashboard)'!$H$36 -> 79496192 | E42: Buy terminal NW | F42: Rent terminal NW | G42: Advantage (buy - rent) | H42: Winner | I42: Cros over NW | J42: Cost crossover year | K42: Monthly mortgage payment | L42: Required net income (DSTI) | M42: Buy liquid wealth | N42: Buy liquid % of NW | O42: Total buy cash paid | P42: Total rent cash paid | Q42: Terminal property (net) | R42: Cum. mortgage interest | S42: Cum. property insurance | T42: Cum. repairs | U42: Cum. admin fees | V42: Cum. rent paid | W42: Cum. real estate tax
A43: Rent terminal NW | B43: ='Input sheet(dashboard)'!$I$36 -> 74271374 | E43: ='Input sheet(dashboard)'!$H$36 -> 79496192 | F43: ='Input sheet(dashboard)'!$I$36 -> 74271374 | G43: =E43-F43 -> 5224817.6 | H43: =IF(E43>F43,"BUY","RENT") -> BUY | I43: ='Input sheet(dashboard)'!N36 | J43: ='Input sheet(dashboard)'!O36 -> 22 | K43: ='Input sheet(dashboard)'!$P$36 -> 39834.138 | L43: ='Input sheet(dashboard)'!$Q$36 -> 88520.306 | M43: ='Input sheet(dashboard)'!$L$36 -> 17686184 | N43: =M43/E43 -> 0.22247838 | O43: =$B$17 -> 32123994 | P43: =$B$25 -> 38221293 | Q43: =INDEX(Calculations!J:J,MATCH('Input sheet(dashboard)'!D27*12,Calculations!B:B,0),1)-INDEX(Calculations!N:N,MATCH('Input sheet(dashboard)'!D27*12,Calculations!B:B,0),1) -> 61810008 | R43: =B7 -> 6358612.7 | S43: =B10 -> 273247.41 | T43: =B11 -> 13673276 | U43: =B12 -> 2459226.7 | V43: =B22 -> 38404800 | W43: =B13 -> 92400
A44: Advantage (buy - rent) | B44: =B42-B43 -> 5224817.6
A45: Winner | B45: =IF(B42>B43,"BUY","RENT") -> BUY
A46: Cost crossover year | B46: xxxx
A47: Monthly mortgage payment | B47: ='Input sheet(dashboard)'!$P$36 -> 39834.138
A48: Required net income (DSTI) | B48: ='Input sheet(dashboard)'!$Q$36 -> 88520.306
A49: Buy liquid wealth | B49: ='Input sheet(dashboard)'!$L$36 -> 17686184
A50: Buy liquid % of NW | B50: =B49/B42 -> 0.22247838
A51: Total buy cash paid | B51: =$B$17 -> 32123994
A52: Total rent cash paid | B52: =$B$25 -> 38221293
A53: Terminal property (net) | B53: =INDEX(Calculations!J:J,MATCH('Input sheet(dashboard)'!D27*12,Calculations!B:B,0),1)-INDEX(Calculations!N:N,MATCH('Input sheet(dashboard)'!D27*12,Calculations!B:B,0),1) -> 61810008
A54: Cum. mortgage interest | B54: =B7 -> 6358612.7
A55: Cum. property insurance | B55: =B10 -> 273247.41
A56: Cum. repairs | B56: =B11 -> 13673276
A57: Cum. admin fees | B57: =B12 -> 2459226.7
A58: Cum. rent paid | B58: =B22 -> 38404800
A59: Cum. real estate tax | B59: =B13 -> 92400

Sheet Results
C4: period | D4: Year | E4: Buy Net worth CZK | F4: Rent Net worth CZK | G4: Buy annaul cost | H4: Rent annual cost | I4: BUy avg. monthly cost given year | J4: Rent avg. monthly cost given year | K4: NetWCrossover | L4: ACost corover
C5: =D5*12 -> 12 | D5: 1 | E5: =INDEX(Calculations!W:W,MATCH(C5,Calculations!B:B,0),1) -> 1462000.7 | F5: =INDEX(Calculations!AH:AH,MATCH(C5,Calculations!B:B,0),1) -> 1341299.2 | G5: =INDEX(Calculations!T:T,MATCH(C5,Calculations!B:B,0),1)+INDEX(Calculations!N:N,MATCH(C5,Calculations!B:B,0),1) -> 738474.94 | H5: =INDEX(Calculations!AE:AE,MATCH(C5,Calculations!B:B,0),1) -> 369731.12 | I5: =IF(G5>0,G5/12,"") -> 61539.578 | J5: =IF(H5>0,H5/12,"") -> 30810.927 | K5: =IF(AND(F5>E5,F5<>""),D5,"") | L5: =IF(AND(H5>G5,H5<>""),D5,"")
C6: =D6*12 -> 24 | D6: 2 | E6: =INDEX(Calculations!W:W,MATCH(C6,Calculations!B:B,0),1) -> 2065194.5 | F6: =INDEX(Calculations!AH:AH,MATCH(C6,Calculations!B:B,0),1) -> 1782977 | G6: =INDEX(Calculations!T:T,MATCH(C6,Calculations!B:B,0),1)+INDEX(Calculations!N:N,MATCH(C6,Calculations!B:B,0),1) -> 656462.61 | H6: =INDEX(Calculations!AE:AE,MATCH(C6,Calculations!B:B,0),1) -> 333817.18 | I6: =IF(G6>0,G6/12,"") -> 54705.217 | J6: =IF(H6>0,H6/12,"") -> 27818.098 | K6: =IF(AND(F6>E6,F6<>""),D6,"") | L6: =IF(AND(H6>G6,H6<>""),D6,"")
C7: =D7*12 -> 36 | D7: 3 | E7: =INDEX(Calculations!W:W,MATCH(C7,Calculations!B:B,0),1) -> 2697804.9 | F7: =INDEX(Calculations!AH:AH,MATCH(C7,Calculations!B:B,0),1) -> 2249931.6 | G7: =INDEX(Calculations!T:T,MATCH(C7,Calculations!B:B,0),1)+INDEX(Calculations!N:N,MATCH(C7,Calculations!B:B,0),1) -> 663443.89 | H7: =INDEX(Calculations!AE:AE,MATCH(C7,Calculations!B:B,0),1) -> 350508.04 | I7: =IF(G7>0,G7/12,"") -> 55286.991 | J7: =IF(H7>0,H7/12,"") -> 29209.003 | K7: =IF(AND(F7>E7,F7<>""),D7,"") | L7: =IF(AND(H7>G7,H7<>""),D7,"")
C8: =D8*12 -> 48 | D8: 4 | E8: =INDEX(Calculations!W:W,MATCH(C8,Calculations!B:B,0),1) -> 3361269.8 | F8: =INDEX(Calculations!AH:AH,MATCH(C8,Calculations!B:B,0),1) -> 2743655.4 | G8: =INDEX(Calculations!T:T,MATCH(C8,Calculations!B:B,0),1)+INDEX(Calculations!N:N,MATCH(C8,Calculations!B:B,0),1) -> 670748.26 | H8: =INDEX(Calculations!AE:AE,MATCH(C8,Calculations!B:B,0),1) -> 368033.44 | I8: =IF(G8>0,G8/12,"") -> 55895.688 | J8: =IF(H8>0,H8/12,"") -> 30669.453 | K8: =IF(AND(F8>E8,F8<>""),D8,"") | L8: =IF(AND(H8>G8,H8<>""),D8,"")
C9: =D9*12 -> 60 | D9: 5 | E9: =INDEX(Calculations!W:W,MATCH(C9,Calculations!B:B,0),1) -> 4057097.1 | F9: =INDEX(Calculations!AH:AH,MATCH(C9,Calculations!B:B,0),1) -> 3256401.7 | G9: =INDEX(Calculations!T:T,MATCH(C9,Calculations!B:B,0),1)+INDEX(Calculations!N:N,MATCH(C9,Calculations!B:B,0),1) -> 678391.23 | H9: =INDEX(Calculations!AE:AE,MATCH(C9,Calculations!B:B,0),1) -> 395356.93 | I9: =IF(G9>0,G9/12,"") -> 56532.603 | J9: =IF(H9>0,H9/12,"") -> 32946.411 | K9: =IF(AND(F9>E9,F9<>""),D9,"") | L9: =IF(AND(H9>G9,H9<>""),D9,"")
C10: =D10*12 -> 72 | D10: 6 | E10: =INDEX(Calculations!W:W,MATCH(C10,Calculations!B:B,0),1) -> 4786868.8 | F10: =INDEX(Calculations!AH:AH,MATCH(C10,Calculations!B:B,0),1) -> 3807769.5 | G10: =INDEX(Calculations!T:T,MATCH(C10,Calculations!B:B,0),1)+INDEX(Calculations!N:N,MATCH(C10,Calculations!B:B,0),1) -> 686389.07 | H10: =INDEX(Calculations!AE:AE,MATCH(C10,Calculations!B:B,0),1) -> 405756.86 | I10: =IF(G10>0,G10/12,"") -> 57199.089 | J10: =IF(H10>0,H10/12,"") -> 33813.072 | K10: =IF(AND(F10>E10,F10<>""),D10,"") | L10: =IF(AND(H10>G10,H10<>""),D10,"")
C11: =D11*12 -> 84 | D11: 7 | E11: =INDEX(Calculations!W:W,MATCH(C11,Calculations!B:B,0),1) -> 5552244.4 | F11: =INDEX(Calculations!AH:AH,MATCH(C11,Calculations!B:B,0),1) -> 4390901.8 | G11: =INDEX(Calculations!T:T,MATCH(C11,Calculations!B:B,0),1)+INDEX(Calculations!N:N,MATCH(C11,Calculations!B:B,0),1) -> 694758.83 | H11: =INDEX(Calculations!AE:AE,MATCH(C11,Calculations!B:B,0),1) -> 426044.71 | I11: =IF(G11>0,G11/12,"") -> 57896.569 | J11: =IF(H11>0,H11/12,"") -> 35503.726 | K11: =IF(AND(F11>E11,F11<>""),D11,"") | L11: =IF(AND(H11>G11,H11<>""),D11,"")
C12: =D12*12 -> 96 | D12: 8 | E12: =INDEX(Calculations!W:W,MATCH(C12,Calculations!B:B,0),1) -> 6354964.6 | F12: =INDEX(Calculations!AH:AH,MATCH(C12,Calculations!B:B,0),1) -> 5007692.7 | G12: =INDEX(Calculations!T:T,MATCH(C12,Calculations!B:B,0),1)+INDEX(Calculations!N:N,MATCH(C12,Calculations!B:B,0),1) -> 703518.41 | H12: =INDEX(Calculations!AE:AE,MATCH(C12,Calculations!B:B,0),1) -> 447346.94 | I12: =IF(G12>0,G12/12,"") -> 58626.534 | J12: =IF(H12>0,H12/12,"") -> 37278.912 | K12: =IF(AND(F12>E12,F12<>""),D12,"") | L12: =IF(AND(H12>G12,H12<>""),D12,"")
C13: =D13*12 -> 108 | D13: 9 | E13: =INDEX(Calculations!W:W,MATCH(C13,Calculations!B:B,0),1) -> 7196855.4 | F13: =INDEX(Calculations!AH:AH,MATCH(C13,Calculations!B:B,0),1) -> 5650032.7 | G13: =INDEX(Calculations!T:T,MATCH(C13,Calculations!B:B,0),1)+INDEX(Calculations!N:N,MATCH(C13,Calculations!B:B,0),1) -> 712686.59 | H13: =INDEX(Calculations!AE:AE,MATCH(C13,Calculations!B:B,0),1) -> 479643.71 | I13: =IF(G13>0,G13/12,"") -> 59390.549 | J13: =IF(H13>0,H13/12,"") -> 39970.309 | K13: =IF(AND(F13>E13,F13<>""),D13,"") | L13: =IF(AND(H13>G13,H13<>""),D13,"")
C14: =D14*12 -> 120 | D14: 10 | E14: =INDEX(Calculations!W:W,MATCH(C14,Calculations!B:B,0),1) -> 8079832.4 | F14: =INDEX(Calculations!AH:AH,MATCH(C14,Calculations!B:B,0),1) -> 6339495.3 | G14: =INDEX(Calculations!T:T,MATCH(C14,Calculations!B:B,0),1)+INDEX(Calculations!N:N,MATCH(C14,Calculations!B:B,0),1) -> 722283.06 | H14: =INDEX(Calculations!AE:AE,MATCH(C14,Calculations!B:B,0),1) -> 493200.01 | I14: =IF(G14>0,G14/12,"") -> 60190.255 | J14: =IF(H14>0,H14/12,"") -> 41100 | K14: =IF(AND(F14>E14,F14<>""),D14,"") | L14: =IF(AND(H14>G14,H14<>""),D14,"")
C15: =D15*12 -> 132 | D15: 11 | E15: =INDEX(Calculations!W:W,MATCH(C15,Calculations!B:B,0),1) -> 9005904.8 | F15: =INDEX(Calculations!AH:AH,MATCH(C15,Calculations!B:B,0),1) -> 7068976.9 | G15: =INDEX(Calculations!T:T,MATCH(C15,Calculations!B:B,0),1)+INDEX(Calculations!N:N,MATCH(C15,Calculations!B:B,0),1) -> 732328.48 | H15: =INDEX(Calculations!AE:AE,MATCH(C15,Calculations!B:B,0),1) -> 517860.01 | I15: =IF(G15>0,G15/12,"") -> 61027.373 | J15: =IF(H15>0,H15/12,"") -> 43155 | K15: =IF(AND(F15>E15,F15<>""),D15,"") | L15: =IF(AND(H15>G15,H15<>""),D15,"")
C16: =D16*12 -> 144 | D16: 12 | E16: =INDEX(Calculations!W:W,MATCH(C16,Calculations!B:B,0),1) -> 9977180.4 | F16: =INDEX(Calculations!AH:AH,MATCH(C16,Calculations!B:B,0),1) -> 7840889.2 | G16: =INDEX(Calculations!T:T,MATCH(C16,Calculations!B:B,0),1)+INDEX(Calculations!N:N,MATCH(C16,Calculations!B:B,0),1) -> 742844.53 | H16: =INDEX(Calculations!AE:AE,MATCH(C16,Calculations!B:B,0),1) -> 543753.01 | I16: =IF(G16>0,G16/12,"") -> 61903.711 | J16: =IF(H16>0,H16/12,"") -> 45312.75 | K16: =IF(AND(F16>E16,F16<>""),D16,"") | L16: =IF(AND(H16>G16,H16<>""),D16,"")
... C64: =D64*12 -> 720 | D64: 60 | E64: =INDEX(Calculations!W:W,MATCH(C64,Calculations!B:B,0),1) -> 0 | F64: =INDEX(Calculations!AH:AH,MATCH(C64,Calculations!B:B,0),1) | G64: =INDEX(Calculations!T:T,MATCH(C64,Calculations!B:B,0),1)+INDEX(Calculations!N:N,MATCH(C64,Calculations!B:B,0),1) -> 0 | H64: =INDEX(Calculations!AE:AE,MATCH(C64,Calculations!B:B,0),1) -> 0 | I64: =IF(G64>0,G64/12,"") | J64: =IF(H64>0,H64/12,"") | K64: =IF(AND(F64>E64,F64<>""),D64,"") -> 60 | L64: =IF(AND(H64>G64,H64<>""),D64,"")

Sheet Annual cost matrix
A4: BUY-SIDE ANNUAL COSTS
A6: Year | B6: Mortgage interest | C6: Mortgage principal | D6: Payment protection ins | E6: Property insurance | F6: Repairs | G6: Admin/SVJ fees | H6: Real estate tax | I6: Tax benefit (negative) | J6: purchase cost | K6: selling cost
A7: 1 | B7: =SUMIFS(Calculations!F:F,Calculations!C:C,$A7) -> 346288.46 | C7: =SUMIFS(Calculations!H:H,Calculations!C:C,$A7) -> 131721.2 | D7: =SUMIFS(Calculations!G:G,Calculations!C:C,$A7) -> 38240.772 | E7: =SUMIFS(Calculations!R:R,Calculations!C:C,$A7) -> 4053.9623 | F7: =SUMIFS(Calculations!K:K,Calculations!C:C,$A7) -> 113189.59 | G7: =SUMIFS(Calculations!L:L,Calculations!C:C,$A7) -> 36485.661 | H7: =SUMIFS(Calculations!Q:Q,Calculations!C:C,$A7) -> 2310 | I7: =-SUMIFS(Calculations!O:O,Calculations!C:C,$A7) -> -22500 | J7: =SUMIFS(Calculations!M:M,Calculations!C:C,$A7) -> 88685.3 | K7: =SUMIFS(Calculations!N:N,Calculations!C:C,$A7) -> 0 | N7: =SUM(B7:K7) -> 738474.94
A8: 2 | B8: =SUMIFS(Calculations!F:F,Calculations!C:C,$A8) -> 340413.69 | C8: =SUMIFS(Calculations!H:H,Calculations!C:C,$A8) -> 137595.96 | D8: =SUMIFS(Calculations!G:G,Calculations!C:C,$A8) -> 38240.772 | E8: =SUMIFS(Calculations!R:R,Calculations!C:C,$A8) -> 4155.3114 | F8: =SUMIFS(Calculations!K:K,Calculations!C:C,$A8) -> 118849.06 | G8: =SUMIFS(Calculations!L:L,Calculations!C:C,$A8) -> 37397.802 | H8: =SUMIFS(Calculations!Q:Q,Calculations!C:C,$A8) -> 2310 | I8: =-SUMIFS(Calculations!O:O,Calculations!C:C,$A8) -> -22500 | J8: =SUMIFS(Calculations!M:M,Calculations!C:C,$A8) -> 0 | K8: =SUMIFS(Calculations!N:N,Calculations!C:C,$A8) -> 0
A9: 3 | B9: =SUMIFS(Calculations!F:F,Calculations!C:C,$A9) -> 334276.91 | C9: =SUMIFS(Calculations!H:H,Calculations!C:C,$A9) -> 143732.74 | D9: =SUMIFS(Calculations!G:G,Calculations!C:C,$A9) -> 38240.772 | E9: =SUMIFS(Calculations!R:R,Calculations!C:C,$A9) -> 4259.1942 | F9: =SUMIFS(Calculations!K:K,Calculations!C:C,$A9) -> 124791.52 | G9: =SUMIFS(Calculations!L:L,Calculations!C:C,$A9) -> 38332.748 | H9: =SUMIFS(Calculations!Q:Q,Calculations!C:C,$A9) -> 2310 | I9: =-SUMIFS(Calculations!O:O,Calculations!C:C,$A9) -> -22500 | J9: =SUMIFS(Calculations!M:M,Calculations!C:C,$A9) -> 0 | K9: =SUMIFS(Calculations!N:N,Calculations!C:C,$A9) -> 0
A10: 4 | B10: =SUMIFS(Calculations!F:F,Calculations!C:C,$A10) -> 327866.43 | C10: =SUMIFS(Calculations!H:H,Calculations!C:C,$A10) -> 150143.22 | D10: =SUMIFS(Calculations!G:G,Calculations!C:C,$A10) -> 38240.772 | E10: =SUMIFS(Calculations!R:R,Calculations!C:C,$A10) -> 4365.674 | F10: =SUMIFS(Calculations!K:K,Calculations!C:C,$A10) -> 131031.09 | G10: =SUMIFS(Calculations!L:L,Calculations!C:C,$A10) -> 39291.066 | H10: =SUMIFS(Calculations!Q:Q,Calculations!C:C,$A10) -> 2310 | I10: =-SUMIFS(Calculations!O:O,Calculations!C:C,$A10) -> -22500 | J10: =SUMIFS(Calculations!M:M,Calculations!C:C,$A10) -> 0 | K10: =SUMIFS(Calculations!N:N,Calculations!C:C,$A10) -> 0
A11: 5 | B11: =SUMIFS(Calculations!F:F,Calculations!C:C,$A11) -> 321170.05 | C11: =SUMIFS(Calculations!H:H,Calculations!C:C,$A11) -> 156839.61 | D11: =SUMIFS(Calculations!G:G,Calculations!C:C,$A11) -> 38240.772 | E11: =SUMIFS(Calculations!R:R,Calculations!C:C,$A11) -> 4474.8159 | F11: =SUMIFS(Calculations!K:K,Calculations!C:C,$A11) -> 137582.65 | G11: =SUMIFS(Calculations!L:L,Calculations!C:C,$A11) -> 40273.343 | H11: =SUMIFS(Calculations!Q:Q,Calculations!C:C,$A11) -> 2310 | I11: =-SUMIFS(Calculations!O:O,Calculations!C:C,$A11) -> -22500 | J11: =SUMIFS(Calculations!M:M,Calculations!C:C,$A11) -> 0 | K11: =SUMIFS(Calculations!N:N,Calculations!C:C,$A11) -> 0
A12: 6 | B12: =SUMIFS(Calculations!F:F,Calculations!C:C,$A12) -> 314175 | C12: =SUMIFS(Calculations!H:H,Calculations!C:C,$A12) -> 163834.65 | D12: =SUMIFS(Calculations!G:G,Calculations!C:C,$A12) -> 38240.772 | E12: =SUMIFS(Calculations!R:R,Calculations!C:C,$A12) -> 4586.6863 | F12: =SUMIFS(Calculations!K:K,Calculations!C:C,$A12) -> 144461.78 | G12: =SUMIFS(Calculations!L:L,Calculations!C:C,$A12) -> 41280.176 | H12: =SUMIFS(Calculations!Q:Q,Calculations!C:C,$A12) -> 2310 | I12: =-SUMIFS(Calculations!O:O,Calculations!C:C,$A12) -> -22500 | J12: =SUMIFS(Calculations!M:M,Calculations!C:C,$A12) -> 0 | K12: =SUMIFS(Calculations!N:N,Calculations!C:C,$A12) -> 0
A13: 7 | B13: =SUMIFS(Calculations!F:F,Calculations!C:C,$A13) -> 306867.97 | C13: =SUMIFS(Calculations!H:H,Calculations!C:C,$A13) -> 171141.68 | D13: =SUMIFS(Calculations!G:G,Calculations!C:C,$A13) -> 38240.772 | E13: =SUMIFS(Calculations!R:R,Calculations!C:C,$A13) -> 4701.3534 | F13: =SUMIFS(Calculations!K:K,Calculations!C:C,$A13) -> 151684.87 | G13: =SUMIFS(Calculations!L:L,Calculations!C:C,$A13) -> 42312.181 | H13: =SUMIFS(Calculations!Q:Q,Calculations!C:C,$A13) -> 2310 | I13: =-SUMIFS(Calculations!O:O,Calculations!C:C,$A13) -> -22500 | J13: =SUMIFS(Calculations!M:M,Calculations!C:C,$A13) -> 0 | K13: =SUMIFS(Calculations!N:N,Calculations!C:C,$A13) -> 0
A14: 8 | B14: =SUMIFS(Calculations!F:F,Calculations!C:C,$A14) -> 299235.06 | C14: =SUMIFS(Calculations!H:H,Calculations!C:C,$A14) -> 178774.6 | D14: =SUMIFS(Calculations!G:G,Calculations!C:C,$A14) -> 38240.772 | E14: =SUMIFS(Calculations!R:R,Calculations!C:C,$A14) -> 4818.8873 | F14: =SUMIFS(Calculations!K:K,Calculations!C:C,$A14) -> 159269.11 | G14: =SUMIFS(Calculations!L:L,Calculations!C:C,$A14) -> 43369.985 | H14: =SUMIFS(Calculations!Q:Q,Calculations!C:C,$A14) -> 2310 | I14: =-SUMIFS(Calculations!O:O,Calculations!C:C,$A14) -> -22500 | J14: =SUMIFS(Calculations!M:M,Calculations!C:C,$A14) -> 0 | K14: =SUMIFS(Calculations!N:N,Calculations!C:C,$A14) -> 0
A15: 9 | B15: =SUMIFS(Calculations!F:F,Calculations!C:C,$A15) -> 291261.71 | C15: =SUMIFS(Calculations!H:H,Calculations!C:C,$A15) -> 186747.95 | D15: =SUMIFS(Calculations!G:G,Calculations!C:C,$A15) -> 38240.772 | E15: =SUMIFS(Calculations!R:R,Calculations!C:C,$A15) -> 4939.3594 | F15: =SUMIFS(Calculations!K:K,Calculations!C:C,$A15) -> 167232.57 | G15: =SUMIFS(Calculations!L:L,Calculations!C:C,$A15) -> 44454.235 | H15: =SUMIFS(Calculations!Q:Q,Calculations!C:C,$A15) -> 2310 | I15: =-SUMIFS(Calculations!O:O,Calculations!C:C,$A15) -> -22500 | J15: =SUMIFS(Calculations!M:M,Calculations!C:C,$A15) -> 0 | K15: =SUMIFS(Calculations!N:N,Calculations!C:C,$A15) -> 0
A16: 10 | B16: =SUMIFS(Calculations!F:F,Calculations!C:C,$A16) -> 282932.75 | C16: =SUMIFS(Calculations!H:H,Calculations!C:C,$A16) -> 195076.91 | D16: =SUMIFS(Calculations!G:G,Calculations!C:C,$A16) -> 38240.772 | E16: =SUMIFS(Calculations!R:R,Calculations!C:C,$A16) -> 5062.8434 | F16: =SUMIFS(Calculations!K:K,Calculations!C:C,$A16) -> 175594.2 | G16: =SUMIFS(Calculations!L:L,Calculations!C:C,$A16) -> 45565.591 | H16: =SUMIFS(Calculations!Q:Q,Calculations!C:C,$A16) -> 2310 | I16: =-SUMIFS(Calculations!O:O,Calculations!C:C,$A16) -> -22500 | J16: =SUMIFS(Calculations!M:M,Calculations!C:C,$A16) -> 0 | K16: =SUMIFS(Calculations!N:N,Calculations!C:C,$A16) -> 0
A17: 11 | B17: =SUMIFS(Calculations!F:F,Calculations!C:C,$A17) -> 274232.32 | C17: =SUMIFS(Calculations!H:H,Calculations!C:C,$A17) -> 203777.33 | D17: =SUMIFS(Calculations!G:G,Calculations!C:C,$A17) -> 38240.772 | E17: =SUMIFS(Calculations!R:R,Calculations!C:C,$A17) -> 5189.4145 | F17: =SUMIFS(Calculations!K:K,Calculations!C:C,$A17) -> 184373.91 | G17: =SUMIFS(Calculations!L:L,Calculations!C:C,$A17) -> 46704.731 | H17: =SUMIFS(Calculations!Q:Q,Calculations!C:C,$A17) -> 2310 | I17: =-SUMIFS(Calculations!O:O,Calculations!C:C,$A17) -> -22500 | J17: =SUMIFS(Calculations!M:M,Calculations!C:C,$A17) -> 0 | K17: =SUMIFS(Calculations!N:N,Calculations!C:C,$A17) -> 0
A18: 12 | B18: =SUMIFS(Calculations!F:F,Calculations!C:C,$A18) -> 265143.85 | C18: =SUMIFS(Calculations!H:H,Calculations!C:C,$A18) -> 212865.8 | D18: =SUMIFS(Calculations!G:G,Calculations!C:C,$A18) -> 38240.772 | E18: =SUMIFS(Calculations!R:R,Calculations!C:C,$A18) -> 5319.1499 | F18: =SUMIFS(Calculations!K:K,Calculations!C:C,$A18) -> 193592.6 | G18: =SUMIFS(Calculations!L:L,Calculations!C:C,$A18) -> 47872.349 | H18: =SUMIFS(Calculations!Q:Q,Calculations!C:C,$A18) -> 2310 | I18: =-SUMIFS(Calculations!O:O,Calculations!C:C,$A18) -> -22500 | J18: =SUMIFS(Calculations!M:M,Calculations!C:C,$A18) -> 0 | K18: =SUMIFS(Calculations!N:N,Calculations!C:C,$A18) -> 0
A19: 13 | B19: =SUMIFS(Calculations!F:F,Calculations!C:C,$A19) -> 255650.04 | C19: =SUMIFS(Calculations!H:H,Calculations!C:C,$A19) -> 222359.62 | D19: =SUMIFS(Calculations!G:G,Calculations!C:C,$A19) -> 38240.772 | E19: =SUMIFS(Calculations!R:R,Calculations!C:C,$A19) -> 5452.1286 | F19: =SUMIFS(Calculations!K:K,Calculations!C:C,$A19) -> 203272.23 | G19: =SUMIFS(Calculations!L:L,Calculations!C:C,$A19) -> 49069.158 | H19: =SUMIFS(Calculations!Q:Q,Calculations!C:C,$A19) -> 2310 | I19: =-SUMIFS(Calculations!O:O,Calculations!C:C,$A19) -> -22500 | J19: =SUMIFS(Calculations!M:M,Calculations!C:C,$A19) -> 0 | K19: =SUMIFS(Calculations!N:N,Calculations!C:C,$A19) -> 0
... A66: 60 | B66: =SUMIFS(Calculations!F:F,Calculations!C:C,$A66) -> 3.2780872e-10 | C66: =SUMIFS(Calculations!H:H,Calculations!C:C,$A66) -> -3.2780872e-10 | D66: =SUMIFS(Calculations!G:G,Calculations!C:C,$A66) -> 0 | E66: =SUMIFS(Calculations!R:R,Calculations!C:C,$A66) -> 0 | F66: =SUMIFS(Calculations!K:K,Calculations!C:C,$A66) -> 0 | G66: =SUMIFS(Calculations!L:L,Calculations!C:C,$A66) -> 0 | H66: =SUMIFS(Calculations!Q:Q,Calculations!C:C,$A66) -> 0 | I66: =-SUMIFS(Calculations!O:O,Calculations!C:C,$A66) -> -2.6812006e-11 | J66: =SUMIFS(Calculations!M:M,Calculations!C:C,$A66) -> 0 | K66: =SUMIFS(Calculations!N:N,Calculations!C:C,$A66) -> 0
A72: RENT-SIDE ANNUAL COSTS
A74: Year | B74: Rent | C74: Moving cost | D74: Deposit flows (net)
A75: 1 | B75: =SUMIFS(Calculations!X:X,Calculations!C:C,$A75) -> 317921.12 | C75: =SUMIFS(Calculations!AC:AC,Calculations!C:C,$A75) -> 0 | D75: =SUMIFS(Calculations!AB:AB,Calculations!C:C,$A75) -> 51810
A76: 2 | B76: =SUMIFS(Calculations!X:X,Calculations!C:C,$A76) -> 333817.18 | C76: =SUMIFS(Calculations!AC:AC,Calculations!C:C,$A76) -> 0 | D76: =SUMIFS(Calculations!AB:AB,Calculations!C:C,$A76) -> 0
A77: 3 | B77: =SUMIFS(Calculations!X:X,Calculations!C:C,$A77) -> 350508.04 | C77: =SUMIFS(Calculations!AC:AC,Calculations!C:C,$A77) -> 0 | D77: =SUMIFS(Calculations!AB:AB,Calculations!C:C,$A77) -> 0
A78: 4 | B78: =SUMIFS(Calculations!X:X,Calculations!C:C,$A78) -> 368033.44 | C78: =SUMIFS(Calculations!AC:AC,Calculations!C:C,$A78) -> 0 | D78: =SUMIFS(Calculations!AB:AB,Calculations!C:C,$A78) -> 0
A79: 5 | B79: =SUMIFS(Calculations!X:X,Calculations!C:C,$A79) -> 386435.11 | C79: =SUMIFS(Calculations!AC:AC,Calculations!C:C,$A79) -> 8921.8255 | D79: =SUMIFS(Calculations!AB:AB,Calculations!C:C,$A79) -> 0
A80: 6 | B80: =SUMIFS(Calculations!X:X,Calculations!C:C,$A80) -> 405756.86 | C80: =SUMIFS(Calculations!AC:AC,Calculations!C:C,$A80) -> 0 | D80: =SUMIFS(Calculations!AB:AB,Calculations!C:C,$A80) -> 0
A81: 7 | B81: =SUMIFS(Calculations!X:X,Calculations!C:C,$A81) -> 426044.71 | C81: =SUMIFS(Calculations!AC:AC,Calculations!C:C,$A81) -> 0 | D81: =SUMIFS(Calculations!AB:AB,Calculations!C:C,$A81) -> 0
A82: 8 | B82: =SUMIFS(Calculations!X:X,Calculations!C:C,$A82) -> 447346.94 | C82: =SUMIFS(Calculations!AC:AC,Calculations!C:C,$A82) -> 0 | D82: =SUMIFS(Calculations!AB:AB,Calculations!C:C,$A82) -> 0
A83: 9 | B83: =SUMIFS(Calculations!X:X,Calculations!C:C,$A83) -> 469714.29 | C83: =SUMIFS(Calculations!AC:AC,Calculations!C:C,$A83) -> 9929.4184 | D83: =SUMIFS(Calculations!AB:AB,Calculations!C:C,$A83) -> 0
A84: 10 | B84: =SUMIFS(Calculations!X:X,Calculations!C:C,$A84) -> 493200.01 | C84: =SUMIFS(Calculations!AC:AC,Calculations!C:C,$A84) -> 0 | D84: =SUMIFS(Calculations!AB:AB,Calculations!C:C,$A84) -> 0
A85: 11 | B85: =SUMIFS(Calculations!X:X,Calculations!C:C,$A85) -> 517860.01 | C85: =SUMIFS(Calculations!AC:AC,Calculations!C:C,$A85) -> 0 | D85: =SUMIFS(Calculations!AB:AB,Calculations!C:C,$A85) -> 0
A86: 12 | B86: =SUMIFS(Calculations!X:X,Calculations!C:C,$A86) -> 543753.01 | C86: =SUMIFS(Calculations!AC:AC,Calculations!C:C,$A86) -> 0 | D86: =SUMIFS(Calculations!AB:AB,Calculations!C:C,$A86) -> 0
... A134: 60 | B134: =SUMIFS(Calculations!X:X,Calculations!C:C,$A134) -> 0 | C134: =SUMIFS(Calculations!AC:AC,Calculations!C:C,$A134) -> 0 | D134: =SUMIFS(Calculations!AB:AB,Calculations!C:C,$A134) -> 0

Sheet Data>>>

Sheet Price data
F2: Difference vs prague
B3: Prague | C3: price | D3: =8868530/55 -> 161246 | E3: 161246 | G3: =E3/(E4*12) -> 28.529016 | I3: =E3*55 -> 8868530
C4: rent | D4: =25905/55 -> 471 | E4: 471 | I4: =E4*55 -> 25905
B6: Brno | C6: price | E6: 134537 | F6: =($E$3/E6)-1 -> 0.19852531 | G6: =E6/(E7*12) -> 27.819892 | I6: =E6*55 -> 7399535
C7: rent | E7: 403 | F7: =($E$4/E7)-1 -> 0.16873449 | I7: =E7*55 -> 22165
B9: Ostrava | C9: price | E9: 73986 | F9: =($E$3/E9)-1 -> 1.1794123
C10: rent | E10: 253 | F10: =($E$4/E10)-1 -> 0.86166008
B12: Plzen | C12: price | E12: 92279 | F12: =($E$3/E12)-1 -> 0.74737481
C13: rent | E13: 304 | F13: =($E$4/E13)-1 -> 0.54934211
B15: HRadec | C15: price | E15: 101595 | F15: =($E$3/E15)-1 -> 0.58714504
C16: rent | E16: 323 | F16: =($E$4/E16)-1 -> 0.45820433
B18: Liberec | C18: price | E18: 90366 | F18: =($E$3/E18)-1 -> 0.7843658
C19: rent | E19: 303 | F19: =($E$4/E19)-1 -> 0.55445545
B21: pbc | C21: price | E21: 95814 | F21: =($E$3/E21)-1 -> 0.68290646
C22: rent | E22: 307 | F22: =($E$4/E22)-1 -> 0.53420195
B24: olom | C24: price | E24: 99263 | F24: =($E$3/E24)-1 -> 0.62443206
C25: rent | E25: 294 | F25: =($E$4/E25)-1 -> 0.60204082
B27: ČB | C27: price | E27: 97728 | F27: =($E$3/E27)-1 -> 0.64994679
C28: rent | E28: 287 | F28: =($E$4/E28)-1 -> 0.64111498
B30: KV | C30: price | E30: 76638 | F30: =($E$3/E30)-1 -> 1.1039954
C31: rent | E31: 250 | F31: =($E$4/E31)-1 -> 0.884
B33: jihlava | C33: price | E33: 77887 | F33: =($E$3/E33)-1 -> 1.0702556
C34: rent | E34: 258 | F34: =($E$4/E34)-1 -> 0.8255814
B36: zlin | C36: price | E36: 93514 | F36: =($E$3/E36)-1 -> 0.72429797
C37: rent | E37: 294 | F37: =($E$4/E37)-1 -> 0.60204082
B39: usti nad labem | C39: price | E39: 50157 | F39: =($E$3/E39)-1 -> 2.2148254
C40: rent | E40: 226 | F40: =($E$4/E40)-1 -> 1.0840708

Sheet Price evolution
C6: Realizovane ceny pronajmu Byty | D6: 2012 | E6: 2013 | F6: 2014 | G6: 2015 | H6: 2016 | I6: 2017 | J6: 2018 | K6: 2019 | L6: 2020 | M6: 2021 | N6: 2022 | O6: 2023 | P6: 2024 | Q6: 2025 | S6: cagr 12-23
A7: Toplak | B7: https://www.toplak.cz/dlouhodoby-pohled-na-vyvoj-cen-najmu/ | C7: Praha | D7: 191 | E7: 187 | F7: 194 | G7: 206 | H7: 224 | I7: 252 | J7: 276 | K7: 293 | L7: 273 | M7: 266 | N7: 329 | O7: 351 | S7: =(O7/D7)^(1/10)-1 -> 0.062740851
C8: Brno | D8: 161 | E8: 166 | F8: 165 | G8: 171 | H8: 188 | I8: 204 | J8: 227 | K8: 236 | L8: 242 | M8: 249 | N8: 282 | O8: 306
S9: cagr 12y
B10: sreality | C10: Praha | I10: 301 | J10: 325 | K10: 333 | L10: 314 | M10: 301 | N10: 360 | O10: 403 | P10: 429 | Q10: 455 | S10: =(Q10/D12)^(1/13)-1 -> 0.057850826
C11: Brno
B12: Toplak adjusted | C12: Praha | D12: =D7/$H$18 -> 219.02506 | E12: =E7/$H$18 -> 214.43815 | F12: =F7/$H$18 -> 222.46525 | G12: =G7/$H$18 -> 236.22598 | H12: =H7/$H$18 -> 256.86709 | I12: =I7/$H$18 -> 288.97547 | J12: =J7/$H$18 -> 316.49695 | K12: =K7/$H$18 -> 335.99133 | ... O12: =O7/$H$18 -> 402.50155
S13: cagr 4y
B14: deloitte | C14: Praha | M14: 302 | N14: 368 | O14: 395 | P14: 425 | Q14: 459 | S14: =(Q14/M14)^(1/4)-1 -> 0.11032837
S15: =(Q10/M10)^(1/4)-1 -> 0.10882045
H17: Toplak data x ratio | I17: =I7/I10 -> 0.8372093 | J17: =J7/J10 -> 0.84923077 | K17: =K7/K10 -> 0.87987988 | L17: =L7/L10 -> 0.86942675 | M17: =M7/M10 -> 0.88372093 | N17: =N7/N10 -> 0.91388889 | O17: =O7/O10 -> 0.87096774
G18: avg ratio of toplak x sreality | H18: =AVERAGE(I17:O17) -> 0.87204632

Sheet Listing flat price

Sheet flat price index
A1: Indexy nabídkových cen bytů (průměr roku 2010=100)
B2: ČR | C2: ČR bez Prahy | D2: Praha
A3: 1Q/05 | B3: 66.3 | C3: 59.7 | D3: 73 | E3: 2005 | R3: Praha
A4: 2Q | B4: 65.8 | C4: 59.5 | D4: 72.1 | P4: 2005 | Q4: 2025 | R4: Cagr
A5: 3Q | B5: 66.5 | C5: 60.4 | D5: 72.5 | R5: =(D86/D6)^(1/20)-1 -> 0.071608276
A6: 4Q | B6: 67.5 | C6: 62 | D6: 73.1
A7: 1Q/06 | B7: 69 | C7: 63.1 | D7: 74.8 | E7: 2006 | P7: 2015 | Q7: 2025 | R7: =(D86/D46)^(1/10)-1 -> 0.092721669
A8: 2Q | B8: 70.7 | C8: 64.8 | D8: 76.6
A9: 3Q | B9: 73.3 | C9: 67.8 | D9: 78.8
A10: 4Q | B10: 76.5 | C10: 71.5 | D10: 81.4 | P10: 2012 | Q10: 2025 | R10: =(D86/D34)^(1/13)-1 -> 0.084536168
A11: 1Q/07 | B11: 80.3 | C11: 75.8 | D11: 84.8 | E11: 2007
A12: 2Q | B12: 84.9 | C12: 80.2 | D12: 89.7
A13: 3Q | B13: 89.7 | C13: 85.7 | D13: 93.7
A14: 4Q | B14: 93.9 | C14: 90.3 | D14: 97.6
A15: 1Q/08 | B15: 99.1 | C15: 96.8 | D15: 101.5 | E15: 2008
A16: 2Q | B16: 106.1 | C16: 105.2 | D16: 107
A17: 3Q | B17: 111.8 | C17: 110.2 | D17: 113.5
A18: 4Q | B18: 111.9 | C18: 112.3 | D18: 111.5
A19: 1Q/09 | B19: 108.8 | C19: 107.2 | D19: 110.5 | E19: 2009
A20: 2Q | B20: 103 | C20: 100.4 | D20: 105.5
A21: 3Q | B21: 103.3 | C21: 102.6 | D21: 104
A22: 4Q | B22: 102.1 | C22: 101.7 | D22: 102.5
A23: 1Q/10 | B23: 100.8 | C23: 99.9 | D23: 101.8 | E23: 2010
A24: 2Q | B24: 100.4 | C24: 100.2 | D24: 100.7
A25: 3Q | B25: 99.9 | C25: 99.9 | D25: 99.8
A26: 4Q | B26: 98.9 | C26: 100 | D26: 97.7
A27: 1Q/11 | B27: 97.1 | C27: 98 | D27: 96.2 | E27: 2011
A28: 2Q | B28: 95.1 | C28: 97.1 | D28: 93.1
A29: 3Q | B29: 94.5 | C29: 96.4 | D29: 92.7
A30: 4Q | B30: 93.7 | C30: 94.9 | D30: 92.5
A31: 1Q/12 | B31: 94.9 | C31: 93.9 | D31: 95.9 | E31: 2012
A32: 2Q | B32: 96.8 | C32: 93.1 | D32: 100.4
A33: 3Q | B33: 96 | C33: 91.3 | D33: 100.7
A34: 4Q | B34: 96.6 | C34: 91.7 | D34: 101.5
A35: 1Q/13 | B35: 96.4 | C35: 90.9 | D35: 101.8 | E35: 2013
A36: 2Q | B36: 96.6 | C36: 91 | D36: 102.3
A37: 3Q | B37: 97.4 | C37: 91.3 | D37: 103.4
A38: 4Q | B38: 98.5 | C38: 91.9 | D38: 105
A39: 1Q/14 | B39: 99.3 | C39: 92.9 | D39: 105.7 | E39: 2014
A40: 2Q | B40: 100.6 | C40: 93.4 | D40: 107.7
A41: 3Q | B41: 101.9 | C41: 93.5 | D41: 110.3
A42: 4Q | B42: 101.2 | C42: 92.1 | D42: 110.4
A43: 1Q/15 | B43: 102.9 | C43: 94 | D43: 111.8 | E43: 2015
A44: 2Q | B44: 105.6 | C44: 96.5 | D44: 114.7
A45: 3Q | B45: 108.1 | C45: 98.5 | D45: 117.7
A46: 4Q | B46: 110.9 | C46: 101.6 | D46: 120.1
A47: 1Q/16 | B47: 113.4 | C47: 103.5 | D47: 123.2 | E47: 2016
A48: 2Q | B48: 116.5 | C48: 106.1 | D48: 126.8
A49: 3Q | B49: 118.8 | C49: 108.4 | D49: 129.2
A50: 4Q | B50: 121.9 | C50: 110.2 | D50: 133.7
A51: 1Q/17 | B51: 124.2 | C51: 108.3 | D51: 140 | E51: 2017
A52: 2Q | B52: 127.6 | C52: 109.9 | D52: 145.3
A53: 3Q | B53: 133.7 | C53: 114.6 | D53: 152.8
A54: 4Q | B54: 137.1 | C54: 115.4 | D54: 158.8
A55: 1Q/18 | B55: 140.1 | C55: 119.1 | D55: 161.1 | E55: 2018
A56: 2Q | B56: 143.2 | C56: 120.3 | D56: 166
A57: 3Q | B57: 146.4 | C57: 123.5 | D57: 169.2
A58: 4Q | B58: 148.7 | C58: 124.8 | D58: 172.7
A59: 1Q/19 | B59: 150.5 | C59: 126.5 | D59: 174.5 | E59: 2019
A60: 2Q | B60: 151.4 | C60: 128.6 | D60: 174.2
A61: 3Q | B61: 154 | C61: 133.1 | D61: 174.8
A62: 4Q | B62: 156.9 | C62: 135.9 | D62: 177.8
A63: 1Q/20 | B63: 159.6 | C63: 138.5 | D63: 180.7 | E63: 2020
A64: 2Q | B64: 162.2 | C64: 141.1 | D64: 183.4
A65: 3Q | B65: 166.3 | C65: 146.9 | D65: 185.7
A66: 4Q | B66: 168.9 | C66: 150.8 | D66: 187
A67: 1Q/21 | B67: 171.8 | C67: 154.3 | D67: 189.3 | E67: 2021
A68: 2Q | B68: 175.1 | C68: 158.6 | D68: 191.7
A69: 3Q | B69: 181.8 | C69: 166.4 | D69: 197.3
A70: 4Q | B70: 189.9 | C70: 175.7 | D70: 204.1
A71: 1Q/22 | B71: 200.8 | C71: 189.1 | D71: 212.5 | E71: 2022
A72: 2Q | B72: 218.3 | C72: 207.1 | D72: 229.5
A73: 3Q | B73: 223.5 | C73: 213.2 | D73: 233.8
A74: 4Q | B74: 224.7 | C74: 210.7 | D74: 238.6
A75: 1Q/23 | B75: 220.5 | C75: 206.6 | D75: 234.4 | E75: 2023
A76: 2Q | B76: 216.7 | C76: 203.3 | D76: 230.2
A77: 3Q | B77: 216.1 | C77: 202.1 | D77: 230.1
A78: 4Q | B78: 215.3 | C78: 200.4 | D78: 230.1
A79: 1Q/24 | B79: 219 | C79: 202.8 | D79: 235.2 | E79: 2024
A80: 2Q | B80: 224 | C80: 208.7 | D80: 239.4
A81: 3Q | B81: 231.1 | C81: 216.5 | D81: 245.7
A82: 4Q | B82: 238.3 | C82: 222.7 | D82: 254
A83: 1Q/25 | B83: 253.3 | C83: 232.5 | D83: 274 | E83: 2025
A84: 2Q | B84: 262.1 | C84: 246 | D84: 278.2
A85: 3Q | B85: 271.9 | C85: 258.7 | D85: 285.2
A86: 4Q | B86: 278.5 | C86: 265.5 | D86: 291.5
A87: 1Q/26 | B87: 286.1 | C87: 273.7 | D87: 298.4 | E87: 2026
A88: 2Q
A89: 3Q
A90: 4Q

Sheet SP500 retuns

Sheet DamodaranUS
A1: Date updated: | B1: 45658
A2: Created by: | B2: Aswath Damodaran, adamodar@stern.nyu.edu
A3: What is this data? | B3: Historical returns: Stocks, Bonds & T.Bills with premiums | I3: In US Dollars
A4: Home Page: | B4: http://www.damodaran.com
A5: Data website: | B5: https://pages.stern.nyu.edu/~adamodar/New_Home_Page/data.html
A6: Companies in each industry: | B6: https://pages.stern.nyu.edu/~adamodar/pc/datasets/indname.xls | O6: 1985-2025
A7: Variable definitions: | B7: https://pages.stern.nyu.edu/~adamodar/New_Home_Page/datafile/variable.htm | N7: CAGR | O7: =(I118/I78)^(1/40)-1 -> 0.11381613
A8: Customized Geometric risk premium estimator
A9: What is your riskfree rate? | D9: LT | G9: Estimates of risk premiums from 1928, over the last 50 years and over the last 10 years
A10: Enter your starting year | D10: 1928
A12: Value of stocks in starting year: | E12: =IF(D10=1928,100,VLOOKUP(D10-1,A21:O118,9)) -> 100
A13: Value of T.Bills in starting year: | E13: =IF(D10=1928,100,VLOOKUP(D10-1,A21:L118,11)) -> 100
A14: Value of T.bonds in starting year: | E14: =IF(D10=1928,100,VLOOKUP(D10-1,A20:L118,12)) -> 100
A15: Value of Real estate in starting year | E15: =IF(D10=1928,100,VLOOKUP(D10-1,A20:N118,14)) -> 100
A16: Value of Gold in starting year | E16: =IF(D10=1928,100,VLOOKUP(D10-1,A20:O118,15)) -> 100
A17: Estimate of risk premium based on your inputs: | E17: =IF(D9="ST",(I118/E12)^(1/(A118-D10+1))-(K118/E13)^(1/(A118-D10+1)),(I118/E12)^(1/(A118-D10+1))-(L118/E14)^(1/(A118-D10+1))) -> 0.054831293
B19: Annual Returns on Investments in | I19: Value of $100 invested at start of 1928 in | P19: Annual Risk Premium | U19: Annual Real Returns | AC19: Value of $100 invested at start of 1928 in real terms | AJ19: Real Risk Premium
A20: Year | B20: S&P 500 (includes dividends) | C20: US Small cap (bottom decile) | D20: 3-month T.Bill | E20: US T. Bond (10-year) | F20: Baa Corporate Bond | G20: Real Estate | H20: Gold* | I20: S&P 500 (includes dividends)3 | J20: US Small cap (bottom decile) Cum Value | K20: 3-month T.Bill4 | L20: US T. Bond5 | M20: Baa Corporate Bond2 | N20: Real Estate2 | O20: Gold2 | P20: Stocks - Bills | Q20: Stocks - Bonds | R20: Small Cap Premium (S&P 500 minus Bottom Decile) | S20: Stocks - Baa Corp Bond | T20: Historical ERP | U20: Inflation Rate | V20: S&P 500 (includes dividends)2 | W20: US Small cap (bottom decile)22 | X20: 3-month T. Bill (Real) | Y20: !0-year T.Bonds | Z20: Baa Corp Bonds | AA20: Real Estate3 | AB20: Gold | AC20: S&P 500 (includes dividends)3 | AD20: US Small cap (bottom decile)22 | AE20: 3-month T.Bill4 | AF20: US T. Bond5 | AG20: Baa Corporate Bond2 | AH20: Real Estate2 | AI20: Gold2 | AJ20: Stocks minus T. Bills | AK20: Stocks minus T.Bonds
A21: 1928 | B21: =('[1]S&P 500 & Raw Data'!B4-'[1]S&P 500 & Raw Data'!B3+'[1]S&P 500 & Raw Data'!C4)/'[1]S&P 500 & Raw Data'!B3 -> 0.43811155 | C21: ='[1]Small Cap'!B2 -> 0.6215 | D21: 0.0308 | E21: ='[1]S&P 500 & Raw Data'!F4 -> 0.0083547086 | F21: ='[1]S&P 500 & Raw Data'!J4 -> 0.032195515 | G21: ='[1]Home Prices'!B4/'[1]Home Prices'!B3-1 -> 0.014910537 | H21: ='[1]Gold Prices'!B3/'[1]Gold Prices'!B2-1 -> 0.00096899225 | I21: =100*(1+B21) -> 143.81116 | J21: 159.91 | K21: =100*(1+D21) -> 103.08 | L21: =100*(1+E21) -> 100.83547 | M21: =100*(1+F21) -> 103.21955 | N21: =100*(1+G21) -> 101.49105 | O21: =100*(1+H21) -> 100.0969 | P21: =B21-D21 -> 0.40731155 | Q21: =B21-E21 -> 0.42975684 | R21: =DamodaranUS!$C21-DamodaranUS!$B21 -> 0.18338845 | S21: =B21-F21 -> 0.40591604 | U21: ='[1]Inflation Rate'!C26 -> -0.0115607 | V21: =(1+B21)/(1+$U21)-1 -> 0.45493158 | W21: =(1+C21)/(1+$U21)-1 -> 0.64046492 | X21: =(1+D21)/(1+$U21)-1 -> 0.042856147 | Y21: =(1+E21)/(1+$U21)-1 -> 0.020148337 | Z21: =(1+F21)/(1+$U21)-1 -> 0.044267984 | AA21: =(1+G21)/(1+$U21)-1 -> 0.026780842 | AB21: =(1+H21)/(1+$U21)-1 -> 0.012676238 | AC21: =100*(1+V21) -> 145.49316 | AD21: =100*(1+W21) -> 164.04649 | AE21: =100*(1+X21) -> 104.28561 | AF21: =100*(1+Y21) -> 102.01483 | AG21: =100*(1+Z21) -> 104.4268 | AH21: =100*(1+AA21) -> 102.67808 | AI21: =100*(1+AB21) -> 101.26762 | AJ21: =DamodaranUS!$V21-DamodaranUS!$X21 -> 0.41207543 | AK21: =DamodaranUS!$V21-DamodaranUS!$Y21 -> 0.43478324
A22: 1929 | B22: =('[1]S&P 500 & Raw Data'!B5-'[1]S&P 500 & Raw Data'!B4+'[1]S&P 500 & Raw Data'!C5)/'[1]S&P 500 & Raw Data'!B4 -> -0.082979466 | C22: ='[1]Small Cap'!B3 -> -0.4608 | D22: 0.0316 | E22: ='[1]S&P 500 & Raw Data'!F5 -> 0.042038042 | F22: ='[1]S&P 500 & Raw Data'!J5 -> 0.030178562 | G22: ='[1]Home Prices'!B5/'[1]Home Prices'!B4-1 -> -0.020568071 | H22: ='[1]Gold Prices'!B4/'[1]Gold Prices'!B3-1 -> -0.0014520813 | I22: =I21*(1+B22) -> 131.87778 | J22: =J21*(1+C22) -> 86.223472 | K22: =K21*(1+D22) -> 106.33733 | L22: =L21*(1+E22) -> 105.0744 | M22: =M21*(1+F22) -> 106.33457 | N22: =N21*(1+G22) -> 99.403579 | O22: =O21*(1+H22) -> 99.95155 | P22: =B22-D22 -> -0.11457947 | Q22: =B22-E22 -> -0.12501751 | R22: =DamodaranUS!$C22-DamodaranUS!$B22 -> -0.37782053 | S22: =B22-F22 -> -0.11315803 | U22: ='[1]Inflation Rate'!C27 -> 0.005848 | V22: =(1+B22)/(1+$U22)-1 -> -0.088311023 | W22: =(1+C22)/(1+$U22)-1 -> -0.46393491 | X22: =(1+D22)/(1+$U22)-1 -> 0.025602278 | Y22: =(1+E22)/(1+$U22)-1 -> 0.035979633 | Z22: =(1+F22)/(1+$U22)-1 -> 0.024189105 | AA22: =(1+G22)/(1+$U22)-1 -> -0.026262487 | AB22: =(1+H22)/(1+$U22)-1 -> -0.0072576386 | AC22: =AC21*(1+V22) -> 132.64451 | AD22: =AD21*(1+W22) -> 87.939598 | AE22: =AE21*(1+X22) -> 106.95556 | AF22: =AF21*(1+Y22) -> 105.68529 | AG22: =AG21*(1+Z22) -> 106.95279 | AH22: =AH21*(1+AA22) -> 99.981502 | AI22: =AI21*(1+AB22) -> 100.53266 | AJ22: =DamodaranUS!$V22-DamodaranUS!$X22 -> -0.1139133 | AK22: =DamodaranUS!$V22-DamodaranUS!$Y22 -> -0.12429066
A23: 1930 | B23: =('[1]S&P 500 & Raw Data'!B6-'[1]S&P 500 & Raw Data'!B5+'[1]S&P 500 & Raw Data'!C6)/'[1]S&P 500 & Raw Data'!B5 -> -0.25123636 | C23: ='[1]Small Cap'!B4 -> -0.4835 | D23: 0.0455 | E23: ='[1]S&P 500 & Raw Data'!F6 -> 0.045409314 | F23: ='[1]S&P 500 & Raw Data'!J6 -> 0.0053978095 | G23: ='[1]Home Prices'!B6/'[1]Home Prices'!B5-1 -> -0.043 | H23: ='[1]Gold Prices'!B5/'[1]Gold Prices'!B4-1 -> 0.00096946195 | I23: =I22*(1+B23) -> 98.745288 | J23: =J22*(1+C23) -> 44.534423 | K23: =K22*(1+D23) -> 111.17568 | L23: =L22*(1+E23) -> 109.84575 | M23: =M22*(1+F23) -> 106.90854 | N23: =N22*(1+G23) -> 95.129225 | O23: =O22*(1+H23) -> 100.04845 | P23: =B23-D23 -> -0.29673636 | Q23: =B23-E23 -> -0.29664568 | R23: =DamodaranUS!$C23-DamodaranUS!$B23 -> -0.23226364 | S23: =B23-F23 -> -0.25663417 | U23: ='[1]Inflation Rate'!C28 -> -0.0639535 | V23: =(1+B23)/(1+$U23)-1 -> -0.20007859 | W23: =(1+C23)/(1+$U23)-1 -> -0.44821117 | X23: =(1+D23)/(1+$U23)-1 -> 0.11693169 | Y23: =(1+E23)/(1+$U23)-1 -> 0.11683481 | Z23: =(1+F23)/(1+$U23)-1 -> 0.074089599 | AA23: =(1+G23)/(1+$U23)-1 -> 0.022385106 | AB23: =(1+H23)/(1+$U23)-1 -> 0.069358693 | AC23: =AC22*(1+V23) -> 106.10518 | AD23: =AD22*(1+W23) -> 48.524088 | AE23: =AE22*(1+X23) -> 119.46206 | AF23: =AF22*(1+Y23) -> 118.03301 | AG23: =AG22*(1+Z23) -> 114.87688 | AH23: =AH22*(1+AA23) -> 102.2196 | AI23: =AI22*(1+AB23) -> 107.50547 | AJ23: =DamodaranUS!$V23-DamodaranUS!$X23 -> -0.31701028 | AK23: =DamodaranUS!$V23-DamodaranUS!$Y23 -> -0.3169134
A24: 1931 | B24: =('[1]S&P 500 & Raw Data'!B7-'[1]S&P 500 & Raw Data'!B6+'[1]S&P 500 & Raw Data'!C7)/'[1]S&P 500 & Raw Data'!B6 -> -0.43837549 | C24: ='[1]Small Cap'!B5 -> -0.4362 | D24: 0.0231 | E24: ='[1]S&P 500 & Raw Data'!F7 -> -0.02558856 | F24: ='[1]S&P 500 & Raw Data'!J7 -> -0.15680775 | G24: ='[1]Home Prices'!B7/'[1]Home Prices'!B6-1 -> -0.081504702 | H24: ='[1]Gold Prices'!B6/'[1]Gold Prices'!B5-1 -> -0.17384988 | I24: =I23*(1+B24) -> 55.457774 | J24: =J23*(1+C24) -> 25.108508 | K24: =K23*(1+D24) -> 113.74383 | L24: =L23*(1+E24) -> 107.03496 | M24: =M23*(1+F24) -> 90.144455 | N24: =N23*(1+G24) -> 87.375746 | O24: =O23*(1+H24) -> 82.655039 | P24: =B24-D24 -> -0.46147549 | Q24: =B24-E24 -> -0.41278693 | R24: =DamodaranUS!$C24-DamodaranUS!$B24 -> 0.0021754889 | S24: =B24-F24 -> -0.28156774 | U24: ='[1]Inflation Rate'!C29 -> -0.0931677 | V24: =(1+B24)/(1+$U24)-1 -> -0.38067434 | W24: =(1+C24)/(1+$U24)-1 -> -0.37827534 | X24: =(1+D24)/(1+$U24)-1 -> 0.12821301 | Y24: =(1+E24)/(1+$U24)-1 -> 0.074522203 | Z24: =(1+F24)/(1+$U24)-1 -> -0.070178412 | AA24: =(1+G24)/(1+$U24)-1 -> 0.012861251 | AB24: =(1+H24)/(1+$U24)-1 -> -0.088971444 | AC24: =AC23*(1+V24) -> 65.713662 | AD24: =AD23*(1+W24) -> 30.168622 | AE24: =AE23*(1+X24) -> 134.77865 | AF24: =AF23*(1+Y24) -> 126.82909 | AG24: =AG23*(1+Z24) -> 106.815 | AH24: =AH23*(1+AA24) -> 103.53427 | AI24: =AI23*(1+AB24) -> 97.940557 | AJ24: =DamodaranUS!$V24-DamodaranUS!$X24 -> -0.50888735 | AK24: =DamodaranUS!$V24-DamodaranUS!$Y24 -> -0.45519654
A25: 1932 | B25: =('[1]S&P 500 & Raw Data'!B8-'[1]S&P 500 & Raw Data'!B7+'[1]S&P 500 & Raw Data'!C8)/'[1]S&P 500 & Raw Data'!B7 -> -0.086423645 | C25: ='[1]Small Cap'!B6 -> 0.2865 | D25: 0.0107 | E25: ='[1]S&P 500 & Raw Data'!F8 -> 0.08790307 | F25: ='[1]S&P 500 & Raw Data'!J8 -> 0.23589602 | G25: ='[1]Home Prices'!B8/'[1]Home Prices'!B7-1 -> -0.10466439 | H25: ='[1]Gold Prices'!B7/'[1]Gold Prices'!B6-1 -> 0.21277843 | I25: =I24*(1+B25) -> 50.664911 | J25: =J24*(1+C25) -> 32.302095 | K25: =K24*(1+D25) -> 114.96089 | L25: =L24*(1+E25) -> 116.44366 | M25: =M24*(1+F25) -> 111.40917 | N25: =N24*(1+G25) -> 78.230616 | O25: =O24*(1+H25) -> 100.24225 | P25: =B25-D25 -> -0.097123645 | Q25: =B25-E25 -> -0.17432672 | R25: =DamodaranUS!$C25-DamodaranUS!$B25 -> 0.37292365 | S25: =B25-F25 -> -0.32231966 | U25: ='[1]Inflation Rate'!C30 -> -0.1027397 | V25: =(1+B25)/(1+$U25)-1 -> 0.018184305 | W25: =(1+C25)/(1+$U25)-1 -> 0.43380912 | X25: =(1+D25)/(1+$U25)-1 -> 0.12642897 | Y25: =(1+E25)/(1+$U25)-1 -> 0.21247209 | Z25: =(1+F25)/(1+$U25)-1 -> 0.37741079 | AA25: =(1+G25)/(1+$U25)-1 -> -0.0021450758 | AB25: =(1+H25)/(1+$U25)-1 -> 0.35164615 | AC25: =AC24*(1+V25) -> 66.908619 | AD25: =AD24*(1+W25) -> 43.256045 | AE25: =AE24*(1+X25) -> 151.81858 | AF25: =AF24*(1+Y25) -> 153.77673 | AG25: =AG24*(1+Z25) -> 147.12814 | AH25: =AH24*(1+AA25) -> 103.31218 | AI25: =AI24*(1+AB25) -> 132.38098 | AJ25: =DamodaranUS!$V25-DamodaranUS!$X25 -> -0.10824467 | AK25: =DamodaranUS!$V25-DamodaranUS!$Y25 -> -0.19428778
A26: 1933 | B26: =('[1]S&P 500 & Raw Data'!B9-'[1]S&P 500 & Raw Data'!B8+'[1]S&P 500 & Raw Data'!C9)/'[1]S&P 500 & Raw Data'!B8 -> 0.49982225 | C26: ='[1]Small Cap'!B7 -> 1.466 | D26: 0.0096 | E26: ='[1]S&P 500 & Raw Data'!F9 -> 0.018552721 | F26: ='[1]S&P 500 & Raw Data'!J9 -> 0.12966894 | G26: ='[1]Home Prices'!B9/'[1]Home Prices'!B8-1 -> -0.038119441 | H26: ='[1]Gold Prices'!B8/'[1]Gold Prices'!B7-1 -> 0.27259546 | I26: =I25*(1+B26) -> 75.988361 | J26: =J25*(1+C26) -> 79.656967 | K26: =K25*(1+D26) -> 116.06452 | L26: =L25*(1+E26) -> 118.60401 | M26: =M25*(1+F26) -> 125.85548 | N26: =N25*(1+G26) -> 75.248509 | O26: =O25*(1+H26) -> 127.56783 | P26: =B26-D26 -> 0.49022225 | Q26: =B26-E26 -> 0.48126953 | R26: =DamodaranUS!$C26-DamodaranUS!$B26 -> 0.96617775 | S26: =B26-F26 -> 0.37015332 | U26: ='[1]Inflation Rate'!C31 -> 0.0076336 | V26: =(1+B26)/(1+$U26)-1 -> 0.48845995 | W26: =(1+C26)/(1+$U26)-1 -> 1.4473182 | X26: =(1+D26)/(1+$U26)-1 -> 0.001951503 | Y26: =(1+E26)/(1+$U26)-1 -> 0.0108364 | Z26: =(1+F26)/(1+$U26)-1 -> 0.12111083 | AA26: =(1+G26)/(1+$U26)-1 -> -0.045406426 | AB26: =(1+H26)/(1+$U26)-1 -> 0.26295457 | AC26: =AC25*(1+V26) -> 99.590799 | AD26: =AD25*(1+W26) -> 105.8613 | AE26: =AE25*(1+X26) -> 152.11485 | AF26: =AF25*(1+Y26) -> 155.44312 | AG26: =AG25*(1+Z26) -> 164.94695 | AH26: =AH25*(1+AA26) -> 98.621145 | AI26: =AI25*(1+AB26) -> 167.19116 | AJ26: =DamodaranUS!$V26-DamodaranUS!$X26 -> 0.48650844 | AK26: =DamodaranUS!$V26-DamodaranUS!$Y26 -> 0.47762355
A27: 1934 | B27: =('[1]S&P 500 & Raw Data'!B10-'[1]S&P 500 & Raw Data'!B9+'[1]S&P 500 & Raw Data'!C10)/'[1]S&P 500 & Raw Data'!B9 -> -0.011885657 | C27: ='[1]Small Cap'!B8 -> 0.2307 | D27: ='[1]T. Bill rates'!C12 -> 0.0027833333 | E27: ='[1]S&P 500 & Raw Data'!F10 -> 0.079634426 | F27: ='[1]S&P 500 & Raw Data'!J10 -> 0.18816429 | G27: ='[1]Home Prices'!B10/'[1]Home Prices'!B9-1 -> 0.029062087 | H27: ='[1]Gold Prices'!B9/'[1]Gold Prices'!B8-1 -> 0.31750855 | I27: =I26*(1+B27) -> 75.085189 | J27: =J26*(1+C27) -> 98.033829 | K27: =K26*(1+D27) -> 116.38756 | L27: =L26*(1+E27) -> 128.04897 | M27: =M26*(1+F27) -> 149.53699 | N27: =N26*(1+G27) -> 77.435388 | O27: =O26*(1+H27) -> 168.07171 | P27: =B27-D27 -> -0.01466899 | Q27: =B27-E27 -> -0.091520083 | R27: =DamodaranUS!$C27-DamodaranUS!$B27 -> 0.24258566 | S27: =B27-F27 -> -0.20004995 | U27: ='[1]Inflation Rate'!C32 -> 0.0151515 | V27: =(1+B27)/(1+$U27)-1 -> -0.026633618 | W27: =(1+C27)/(1+$U27)-1 -> 0.21233136 | X27: =(1+D27)/(1+$U27)-1 -> -0.012183567 | Y27: =(1+E27)/(1+$U27)-1 -> 0.063520495 | Z27: =(1+F27)/(1+$U27)-1 -> 0.17043051 | AA27: =(1+G27)/(1+$U27)-1 -> 0.013702967 | AB27: =(1+H27)/(1+$U27)-1 -> 0.29784426 | AC27: =AC26*(1+V27) -> 96.938336 | AD27: =AD26*(1+W27) -> 128.33898 | AE27: =AE26*(1+X27) -> 150.26155 | AF27: =AF26*(1+Y27) -> 165.31694 | AG27: =AG26*(1+Z27) -> 193.05894 | AH27: =AH26*(1+AA27) -> 99.972547 | AI27: =AI26*(1+AB27) -> 216.98809 | AJ27: =DamodaranUS!$V27-DamodaranUS!$X27 -> -0.01445005 | AK27: =DamodaranUS!$V27-DamodaranUS!$Y27 -> -0.090154113
A28: 1935 | B28: =('[1]S&P 500 & Raw Data'!B11-'[1]S&P 500 & Raw Data'!B10+'[1]S&P 500 & Raw Data'!C11)/'[1]S&P 500 & Raw Data'!B10 -> 0.46740421 | C28: ='[1]Small Cap'!B9 -> 0.549 | D28: ='[1]T. Bill rates'!C13 -> 0.001675 | E28: ='[1]S&P 500 & Raw Data'!F11 -> 0.044720477 | F28: ='[1]S&P 500 & Raw Data'!J11 -> 0.13307732 | G28: ='[1]Home Prices'!B11/'[1]Home Prices'!B10-1 -> 0.097658337 | H28: ='[1]Gold Prices'!B10/'[1]Gold Prices'!B9-1 -> 0.0043240127 | I28: =I27*(1+B28) -> 110.18032 | J28: =J27*(1+C28) -> 151.8544 | K28: =K27*(1+D28) -> 116.58251 | L28: =L27*(1+E28) -> 133.77538 | M28: =M27*(1+F28) -> 169.43697 | N28: =N27*(1+G28) -> 84.997599 | O28: =O27*(1+H28) -> 168.79845 | P28: =B28-D28 -> 0.46572921 | Q28: =B28-E28 -> 0.42268373 | R28: =DamodaranUS!$C28-DamodaranUS!$B28 -> 0.081595789 | S28: =B28-F28 -> 0.33432689 | U28: ='[1]Inflation Rate'!C33 -> 0.0298507 | V28: =(1+B28)/(1+$U28)-1 -> 0.42487082 | W28: =(1+C28)/(1+$U28)-1 -> 0.50410152 | X28: =(1+D28)/(1+$U28)-1 -> -0.027359014 | Y28: =(1+E28)/(1+$U28)-1 -> 0.01443877 | Z28: =(1+F28)/(1+$U28)-1 -> 0.10023455 | AA28: =(1+G28)/(1+$U28)-1 -> 0.065842201 | AB28: =(1+H28)/(1+$U28)-1 -> -0.024786784 | AC28: =AC27*(1+V28) -> 138.12461 | AD28: =AD27*(1+W28) -> 193.03485 | AE28: =AE27*(1+X28) -> 146.15054 | AF28: =AF27*(1+Y28) -> 167.70392 | AG28: =AG27*(1+Z28) -> 212.41011 | AH28: =AH27*(1+AA28) -> 106.55496 | AI28: =AI27*(1+AB28) -> 211.60965 | AJ28: =DamodaranUS!$V28-DamodaranUS!$X28 -> 0.45222983 | AK28: =DamodaranUS!$V28-DamodaranUS!$Y28 -> 0.41043205
A29: 1936 | B29: =('[1]S&P 500 & Raw Data'!B12-'[1]S&P 500 & Raw Data'!B11+'[1]S&P 500 & Raw Data'!C12)/'[1]S&P 500 & Raw Data'!B11 -> 0.3194341 | C29: ='[1]Small Cap'!B10 -> 0.9641 | D29: ='[1]T. Bill rates'!C14 -> 0.001725 | E29: ='[1]S&P 500 & Raw Data'!F12 -> 0.050178754 | F29: ='[1]S&P 500 & Raw Data'!J12 -> 0.11383816 | G29: ='[1]Home Prices'!B12/'[1]Home Prices'!B11-1 -> 0.032186015 | H29: ='[1]Gold Prices'!B11/'[1]Gold Prices'!B10-1 -> 0.00086107922 | I29: =I28*(1+B29) -> 145.37568 | J29: =J28*(1+C29) -> 298.25723 | K29: =K28*(1+D29) -> 116.78362 | L29: =L28*(1+E29) -> 140.48806 | M29: =M28*(1+F29) -> 188.72536 | N29: =N28*(1+G29) -> 87.733333 | O29: =O28*(1+H29) -> 168.9438 | P29: =B29-D29 -> 0.3177091 | Q29: =B29-E29 -> 0.26925535 | R29: =DamodaranUS!$C29-DamodaranUS!$B29 -> 0.6446659 | S29: =B29-F29 -> 0.20559594 | U29: ='[1]Inflation Rate'!C34 -> 0.0144928 | V29: =(1+B29)/(1+$U29)-1 -> 0.30058498 | W29: =(1+C29)/(1+$U29)-1 -> 0.93604134 | X29: =(1+D29)/(1+$U29)-1 -> -0.012585402 | Y29: =(1+E29)/(1+$U29)-1 -> 0.035176153 | Z29: =(1+F29)/(1+$U29)-1 -> 0.097926135 | AA29: =(1+G29)/(1+$U29)-1 -> 0.017440454 | AB29: =(1+H29)/(1+$U29)-1 -> -0.013436981 | AC29: =AC28*(1+V29) -> 179.64279 | AD29: =AD28*(1+W29) -> 373.72345 | AE29: =AE28*(1+X29) -> 144.31118 | AF29: =AF28*(1+Y29) -> 173.60309 | AG29: =AG28*(1+Z29) -> 233.21061 | AH29: =AH28*(1+AA29) -> 108.41333 | AI29: =AI28*(1+AB29) -> 208.76625 | AJ29: =DamodaranUS!$V29-DamodaranUS!$X29 -> 0.31317039 | AK29: =DamodaranUS!$V29-DamodaranUS!$Y29 -> 0.26540883
A30: 1937 | B30: =('[1]S&P 500 & Raw Data'!B13-'[1]S&P 500 & Raw Data'!B12+'[1]S&P 500 & Raw Data'!C13)/'[1]S&P 500 & Raw Data'!B12 -> -0.35336729 | C30: ='[1]Small Cap'!B11 -> -0.5394 | D30: ='[1]T. Bill rates'!C15 -> 0.0027583333 | E30: ='[1]S&P 500 & Raw Data'!F13 -> 0.013791461 | F30: ='[1]S&P 500 & Raw Data'!J13 -> -0.044161917 | G30: ='[1]Home Prices'!B13/'[1]Home Prices'!B12-1 -> 0.025633912 | H30: ='[1]Gold Prices'!B12/'[1]Gold Prices'!B11-1 -> -0.0022942357 | I30: =I29*(1+B30) -> 94.004668 | J30: =J29*(1+C30) -> 137.37728 | K30: =K29*(1+D30) -> 117.10575 | L30: =L29*(1+E30) -> 142.4256 | M30: =M29*(1+F30) -> 180.39089 | N30: =N29*(1+G30) -> 89.982281 | O30: =O29*(1+H30) -> 168.5562 | P30: =B30-D30 -> -0.35612562 | Q30: =B30-E30 -> -0.36715875 | R30: =DamodaranUS!$C30-DamodaranUS!$B30 -> -0.18603271 | S30: =B30-F30 -> -0.30920537 | U30: ='[1]Inflation Rate'!C35 -> 0.0285714 | V30: =(1+B30)/(1+$U30)-1 -> -0.37132929 | W30: =(1+C30)/(1+$U30)-1 -> -0.55219443 | X30: =(1+D30)/(1+$U30)-1 -> -0.025096038 | Y30: =(1+E30)/(1+$U30)-1 -> -0.014369386 | Z30: =(1+F30)/(1+$U30)-1 -> -0.070712949 | AA30: =(1+G30)/(1+$U30)-1 -> -0.002855891 | AB30: =(1+H30)/(1+$U30)-1 -> -0.030008258 | AC30: =AC29*(1+V30) -> 112.93616 | AD30: =AD29*(1+W30) -> 167.35544 | AE30: =AE29*(1+X30) -> 140.68954 | AF30: =AF29*(1+Y30) -> 171.10852 | AG30: =AG29*(1+Z30) -> 216.7196 | AH30: =AH29*(1+AA30) -> 108.10371 | AI30: =AI29*(1+AB30) -> 202.50154 | AJ30: =DamodaranUS!$V30-DamodaranUS!$X30 -> -0.34623325 | AK30: =DamodaranUS!$V30-DamodaranUS!$Y30 -> -0.3569599
A31: 1938 | B31: =('[1]S&P 500 & Raw Data'!B14-'[1]S&P 500 & Raw Data'!B13+'[1]S&P 500 & Raw Data'!C14)/'[1]S&P 500 & Raw Data'!B13 -> 0.29282654 | C31: ='[1]Small Cap'!B12 -> 0.0516 | D31: ='[1]T. Bill rates'!C16 -> 0.00065 | E31: ='[1]S&P 500 & Raw Data'!F14 -> 0.042132485 | F31: ='[1]S&P 500 & Raw Data'!J14 -> 0.092358817 | G31: ='[1]Home Prices'!B14/'[1]Home Prices'!B13-1 -> -0.0087368136 | H31: ='[1]Gold Prices'!B13/'[1]Gold Prices'!B12-1 -> 0.0017246335 | I31: =I30*(1+B31) -> 121.53173 | J31: =J30*(1+C31) -> 144.46595 | K31: =K30*(1+D31) -> 117.18187 | L31: =L30*(1+E31) -> 148.42634 | M31: =M30*(1+F31) -> 197.05158 | N31: =N30*(1+G31) -> 89.196123 | O31: =O30*(1+H31) -> 168.8469 | P31: =B31-D31 -> 0.29217654 | Q31: =B31-E31 -> 0.25069405 | R31: =DamodaranUS!$C31-DamodaranUS!$B31 -> -0.24122654 | S31: =B31-F31 -> 0.20046772 | U31: ='[1]Inflation Rate'!C36 -> -0.0277778 | V31: =(1+B31)/(1+$U31)-1 -> 0.32976447 | W31: =(1+C31)/(1+$U31)-1 -> 0.081645739 | X31: =(1+D31)/(1+$U31)-1 -> 0.029240024 | Y31: =(1+E31)/(1+$U31)-1 -> 0.071907724 | Z31: =(1+F31)/(1+$U31)-1 -> 0.12356909 | AA31: =(1+G31)/(1+$U31)-1 -> 0.019585015 | AB31: =(1+H31)/(1+$U31)-1 -> 0.030345361 | AC31: =AC30*(1+V31) -> 150.17849 | AD31: =AD30*(1+W31) -> 181.0193 | AE31: =AE30*(1+X31) -> 144.8033 | AF31: =AF30*(1+Y31) -> 183.41255 | AG31: =AG30*(1+Z31) -> 243.49945 | AH31: =AH30*(1+AA31) -> 110.22092 | AI31: =AI30*(1+AB31) -> 208.64652 | AJ31: =DamodaranUS!$V31-DamodaranUS!$X31 -> 0.30052445 | AK31: =DamodaranUS!$V31-DamodaranUS!$Y31 -> 0.25785675
A32: 1939 | B32: =('[1]S&P 500 & Raw Data'!B15-'[1]S&P 500 & Raw Data'!B14+'[1]S&P 500 & Raw Data'!C15)/'[1]S&P 500 & Raw Data'!B14 -> -0.010975647 | C32: ='[1]Small Cap'!B13 -> -0.0486 | D32: ='[1]T. Bill rates'!C17 -> 0.00045833333 | E32: ='[1]S&P 500 & Raw Data'!F15 -> 0.044122614 | F32: ='[1]S&P 500 & Raw Data'!J15 -> 0.079831378 | G32: ='[1]Home Prices'!B15/'[1]Home Prices'!B14-1 -> -0.013016072 | H32: ='[1]Gold Prices'!B14/'[1]Gold Prices'!B13-1 -> -0.012338594 | I32: =I31*(1+B32) -> 120.19784 | J32: =J31*(1+C32) -> 137.4449 | K32: =K31*(1+D32) -> 117.23557 | L32: =L31*(1+E32) -> 154.9753 | M32: =M31*(1+F32) -> 212.78248 | N32: =N31*(1+G32) -> 88.03514 | O32: =O31*(1+H32) -> 166.76357 | P32: =B32-D32 -> -0.01143398 | Q32: =B32-E32 -> -0.055098261 | R32: =DamodaranUS!$C32-DamodaranUS!$B32 -> -0.037624353 | S32: =B32-F32 -> -0.090807025 | U32: ='[1]Inflation Rate'!C37 -> 0 | V32: =(1+B32)/(1+$U32)-1 -> -0.010975647 | W32: =(1+C32)/(1+$U32)-1 -> -0.0486 | X32: =(1+D32)/(1+$U32)-1 -> 0.00045833333 | Y32: =(1+E32)/(1+$U32)-1 -> 0.044122614 | Z32: =(1+F32)/(1+$U32)-1 -> 0.079831378 | AA32: =(1+G32)/(1+$U32)-1 -> -0.013016072 | AB32: =(1+H32)/(1+$U32)-1 -> -0.012338594 | AC32: =AC31*(1+V32) -> 148.53019 | AD32: =AD31*(1+W32) -> 172.22176 | AE32: =AE31*(1+X32) -> 144.86967 | AF32: =AF31*(1+Y32) -> 191.50519 | AG32: =AG31*(1+Z32) -> 262.93835 | AH32: =AH31*(1+AA32) -> 108.78628 | AI32: =AI31*(1+AB32) -> 206.07212 | AJ32: =DamodaranUS!$V32-DamodaranUS!$X32 -> -0.01143398 | AK32: =DamodaranUS!$V32-DamodaranUS!$Y32 -> -0.055098261
A33: 1940 | B33: =('[1]S&P 500 & Raw Data'!B16-'[1]S&P 500 & Raw Data'!B15+'[1]S&P 500 & Raw Data'!C16)/'[1]S&P 500 & Raw Data'!B15 -> -0.10672873 | C33: ='[1]Small Cap'!B14 -> -0.3288 | D33: ='[1]T. Bill rates'!C18 -> 0.00035833333 | E33: ='[1]S&P 500 & Raw Data'!F16 -> 0.054024816 | F33: ='[1]S&P 500 & Raw Data'!J16 -> 0.086481372 | G33: ='[1]Home Prices'!B16/'[1]Home Prices'!B15-1 -> 0.033066077 | H33: ='[1]Gold Prices'!B15/'[1]Gold Prices'!B14-1 -> -0.016560139 | I33: =I32*(1+B33) -> 107.36928 | J33: =J32*(1+C33) -> 92.253019 | K33: =K32*(1+D33) -> 117.27758 | L33: =L32*(1+E33) -> 163.34781 | M33: =M32*(1+F33) -> 231.1842 | N33: =N32*(1+G33) -> 90.946116 | O33: =O32*(1+H33) -> 164.00194 | P33: =B33-D33 -> -0.10708707 | Q33: =B33-E33 -> -0.16075355 | R33: =DamodaranUS!$C33-DamodaranUS!$B33 -> -0.22207127 | S33: =B33-F33 -> -0.1932101 | U33: ='[1]Inflation Rate'!C38 -> 0.0071429 | V33: =(1+B33)/(1+$U33)-1 -> -0.11306403 | W33: =(1+C33)/(1+$U33)-1 -> -0.33356031 | X33: =(1+D33)/(1+$U33)-1 -> -0.0067364489 | Y33: =(1+E33)/(1+$U33)-1 -> 0.046549418 | Z33: =(1+F33)/(1+$U33)-1 -> 0.078775784 | AA33: =(1+G33)/(1+$U33)-1 -> 0.025739323 | AB33: =(1+H33)/(1+$U33)-1 -> -0.023534932 | AC33: =AC32*(1+V33) -> 131.73677 | AD33: =AD32*(1+W33) -> 114.77542 | AE33: =AE32*(1+X33) -> 143.89377 | AF33: =AF32*(1+Y33) -> 200.41965 | AG33: =AG32*(1+Z33) -> 283.65152 | AH33: =AH32*(1+AA33) -> 111.58636 | AI33: =AI32*(1+AB33) -> 201.22223 | AJ33: =DamodaranUS!$V33-DamodaranUS!$X33 -> -0.10632758 | AK33: =DamodaranUS!$V33-DamodaranUS!$Y33 -> -0.15961345
A34: 1941 | B34: =('[1]S&P 500 & Raw Data'!B17-'[1]S&P 500 & Raw Data'!B16+'[1]S&P 500 & Raw Data'!C17)/'[1]S&P 500 & Raw Data'!B16 -> -0.12771456 | C34: ='[1]Small Cap'!B15 -> -0.0675 | D34: ='[1]T. Bill rates'!C19 -> 0.0012916667 | E34: ='[1]S&P 500 & Raw Data'!F17 -> -0.020221976 | F34: ='[1]S&P 500 & Raw Data'!J17 -> 0.050071729 | G34: ='[1]Home Prices'!B17/'[1]Home Prices'!B16-1 -> -0.083846277 | H34: ='[1]Gold Prices'!B16/'[1]Gold Prices'!B15-1 -> 0 | I34: =I33*(1+B34) -> 93.656657 | J34: =J33*(1+C34) -> 86.02594 | K34: =K33*(1+D34) -> 117.42907 | L34: =L33*(1+E34) -> 160.0446 | M34: =M33*(1+F34) -> 242.75999 | N34: =N33*(1+G34) -> 83.320623 | O34: =O33*(1+H34) -> 164.00194 | P34: =B34-D34 -> -0.12900622 | Q34: =B34-E34 -> -0.10749258 | R34: =DamodaranUS!$C34-DamodaranUS!$B34 -> 0.060214556 | S34: =B34-F34 -> -0.17778628 | U34: ='[1]Inflation Rate'!C39 -> 0.0992908 | V34: =(1+B34)/(1+$U34)-1 -> -0.20650164 | W34: =(1+C34)/(1+$U34)-1 -> -0.15172582 | X34: =(1+D34)/(1+$U34)-1 -> -0.089147597 | Y34: =(1+E34)/(1+$U34)-1 -> -0.10871807 | Z34: =(1+F34)/(1+$U34)-1 -> -0.044773477 | AA34: =(1+G34)/(1+$U34)-1 -> -0.16659566 | AB34: =(1+H34)/(1+$U34)-1 -> -0.090322597 | AC34: =AC33*(1+V34) -> 104.53291 | AD34: =AD33*(1+W34) -> 97.361024 | AE34: =AE33*(1+X34) -> 131.06598 | AF34: =AF33*(1+Y34) -> 178.63041 | AG34: =AG33*(1+Z34) -> 270.95146 | AH34: =AH33*(1+AA34) -> 92.99656 | AI34: =AI33*(1+AB34) -> 183.04731 | AJ34: =DamodaranUS!$V34-DamodaranUS!$X34 -> -0.11735405 | AK34: =DamodaranUS!$V34-DamodaranUS!$Y34 -> -0.097783571
A35: 1942 | B35: =('[1]S&P 500 & Raw Data'!B18-'[1]S&P 500 & Raw Data'!B17+'[1]S&P 500 & Raw Data'!C18)/'[1]S&P 500 & Raw Data'!B17 -> 0.19173763 | C35: ='[1]Small Cap'!B16 -> 0.6301 | D35: ='[1]T. Bill rates'!C20 -> 0.003425 | E35: ='[1]S&P 500 & Raw Data'!F18 -> 0.022948682 | F35: ='[1]S&P 500 & Raw Data'!J18 -> 0.05179901 | G35: ='[1]Home Prices'!B18/'[1]Home Prices'!B17-1 -> 0.033330412 | H35: ='[1]Gold Prices'!B17/'[1]Gold Prices'!B16-1 -> 0 | I35: =I34*(1+B35) -> 111.61416 | J35: =J34*(1+C35) -> 140.23088 | K35: =K34*(1+D35) -> 117.83126 | L35: =L34*(1+E35) -> 163.71741 | M35: =M34*(1+F35) -> 255.33472 | N35: =N34*(1+G35) -> 86.097734 | O35: =O34*(1+H35) -> 164.00194 | P35: =B35-D35 -> 0.18831263 | Q35: =B35-E35 -> 0.16878895 | R35: =DamodaranUS!$C35-DamodaranUS!$B35 -> 0.43836237 | S35: =B35-F35 -> 0.13993862 | U35: ='[1]Inflation Rate'!C40 -> 0.0903226 | V35: =(1+B35)/(1+$U35)-1 -> 0.093013783 | W35: =(1+C35)/(1+$U35)-1 -> 0.4950621 | X35: =(1+D35)/(1+$U35)-1 -> -0.079698981 | Y35: =(1+E35)/(1+$U35)-1 -> -0.061792645 | Z35: =(1+F35)/(1+$U35)-1 -> -0.035332286 | AA35: =(1+G35)/(1+$U35)-1 -> -0.052270941 | AB35: =(1+H35)/(1+$U35)-1 -> -0.082840253 | AC35: =AC34*(1+V35) -> 114.25591 | AD35: =AD34*(1+W35) -> 145.56078 | AE35: =AE34*(1+X35) -> 120.62016 | AF35: =AF34*(1+Y35) -> 167.59236 | AG35: =AG34*(1+Z35) -> 261.37812 | AH35: =AH34*(1+AA35) -> 88.135543 | AI35: =AI34*(1+AB35) -> 167.88363 | AJ35: =DamodaranUS!$V35-DamodaranUS!$X35 -> 0.17271276 | AK35: =DamodaranUS!$V35-DamodaranUS!$Y35 -> 0.15480643
A36: 1943 | B36: =('[1]S&P 500 & Raw Data'!B19-'[1]S&P 500 & Raw Data'!B18+'[1]S&P 500 & Raw Data'!C19)/'[1]S&P 500 & Raw Data'!B18 -> 0.2506131 | C36: ='[1]Small Cap'!B17 -> 1.4302 | D36: ='[1]T. Bill rates'!C21 -> 0.0038 | E36: ='[1]S&P 500 & Raw Data'!F19 -> 0.0249 | F36: ='[1]S&P 500 & Raw Data'!J19 -> 0.080446701 | G36: ='[1]Home Prices'!B19/'[1]Home Prices'!B18-1 -> 0.1144626 | H36: ='[1]Gold Prices'!B18/'[1]Gold Prices'!B17-1 -> 0 | I36: =I35*(1+B36) -> 139.58613 | J36: =J35*(1+C36) -> 340.7891 | K36: =K35*(1+D36) -> 118.27902 | L36: =L35*(1+E36) -> 167.79397 | M36: =M35*(1+F36) -> 275.87555 | N36: =N35*(1+G36) -> 95.952704 | O36: =O35*(1+H36) -> 164.00194 | P36: =B36-D36 -> 0.2468131 | Q36: =B36-E36 -> 0.2257131 | R36: =DamodaranUS!$C36-DamodaranUS!$B36 -> 1.1795869 | S36: =B36-F36 -> 0.1701664 | U36: ='[1]Inflation Rate'!C41 -> 0.0295858 | V36: =(1+B36)/(1+$U36)-1 -> 0.21467594 | W36: =(1+C36)/(1+$U36)-1 -> 1.3603667 | X36: =(1+D36)/(1+$U36)-1 -> -0.025044829 | Y36: =(1+E36)/(1+$U36)-1 -> -0.0045511506 | Z36: =(1+F36)/(1+$U36)-1 -> 0.04939938 | AA36: =(1+G36)/(1+$U36)-1 -> 0.082437811 | AB36: =(1+H36)/(1+$U36)-1 -> -0.028735633 | AC36: =AC35*(1+V36) -> 138.7839 | AD36: =AD35*(1+W36) -> 343.57681 | AE36: =AE35*(1+X36) -> 117.59925 | AF36: =AF35*(1+Y36) -> 166.82962 | AG36: =AG35*(1+Z36) -> 274.29004 | AH36: =AH35*(1+AA36) -> 95.401244 | AI36: =AI35*(1+AB36) -> 163.05938 | AJ36: =DamodaranUS!$V36-DamodaranUS!$X36 -> 0.23972077 | AK36: =DamodaranUS!$V36-DamodaranUS!$Y36 -> 0.21922709
A37: 1944 | B37: =('[1]S&P 500 & Raw Data'!B20-'[1]S&P 500 & Raw Data'!B19+'[1]S&P 500 & Raw Data'!C20)/'[1]S&P 500 & Raw Data'!B19 -> 0.19030677 | C37: ='[1]Small Cap'!B18 -> 0.7115 | D37: ='[1]T. Bill rates'!C22 -> 0.0038 | E37: ='[1]S&P 500 & Raw Data'!F20 -> 0.025776112 | F37: ='[1]S&P 500 & Raw Data'!J20 -> 0.065658636 | G37: ='[1]Home Prices'!B20/'[1]Home Prices'!B19-1 -> 0.16584227 | H37: ='[1]Gold Prices'!B19/'[1]Gold Prices'!B18-1 -> 0 | I37: =I36*(1+B37) -> 166.15032 | J37: =J36*(1+C37) -> 583.26054 | K37: =K36*(1+D37) -> 118.72848 | L37: =L36*(1+E37) -> 172.11905 | M37: =M36*(1+F37) -> 293.98917 | N37: =N36*(1+G37) -> 111.86572 | O37: =O36*(1+H37) -> 164.00194 | P37: =B37-D37 -> 0.18650677 | Q37: =B37-E37 -> 0.16453066 | R37: =DamodaranUS!$C37-DamodaranUS!$B37 -> 0.52119323 | S37: =B37-F37 -> 0.12464813 | U37: ='[1]Inflation Rate'!C42 -> 0.0229885 | V37: =(1+B37)/(1+$U37)-1 -> 0.16355831 | W37: =(1+C37)/(1+$U37)-1 -> 0.67303934 | X37: =(1+D37)/(1+$U37)-1 -> -0.018757298 | Y37: =(1+E37)/(1+$U37)-1 -> 0.0027249686 | Z37: =(1+F37)/(1+$U37)-1 -> 0.041711257 | AA37: =(1+G37)/(1+$U37)-1 -> 0.13964358 | AB37: =(1+H37)/(1+$U37)-1 -> -0.022471905 | AC37: =AC36*(1+V37) -> 161.48316 | AD37: =AD36*(1+W37) -> 574.81751 | AE37: =AE36*(1+X37) -> 115.3934 | AF37: =AF36*(1+Y37) -> 167.28423 | AG37: =AG36*(1+Z37) -> 285.73102 | AH37: =AH36*(1+AA37) -> 108.72341 | AI37: =AI36*(1+AB37) -> 159.39513 | AJ37: =DamodaranUS!$V37-DamodaranUS!$X37 -> 0.18231561 | AK37: =DamodaranUS!$V37-DamodaranUS!$Y37 -> 0.16083334
A38: 1945 | B38: =('[1]S&P 500 & Raw Data'!B21-'[1]S&P 500 & Raw Data'!B20+'[1]S&P 500 & Raw Data'!C21)/'[1]S&P 500 & Raw Data'!B20 -> 0.35821084 | C38: ='[1]Small Cap'!B19 -> 0.9441 | D38: ='[1]T. Bill rates'!C23 -> 0.0038 | E38: ='[1]S&P 500 & Raw Data'!F21 -> 0.038044173 | F38: ='[1]S&P 500 & Raw Data'!J21 -> 0.067998655 | G38: ='[1]Home Prices'!B21/'[1]Home Prices'!B20-1 -> 0.11777376 | H38: ='[1]Gold Prices'!B20/'[1]Gold Prices'!B19-1 -> 0.025406204 | I38: =I37*(1+B38) -> 225.66717 | J38: =J37*(1+C38) -> 1133.9168 | K38: =K37*(1+D38) -> 119.17965 | L38: =L37*(1+E38) -> 178.66717 | M38: =M37*(1+F38) -> 313.98003 | N38: =N37*(1+G38) -> 125.04057 | O38: =O37*(1+H38) -> 168.1686 | P38: =B38-D38 -> 0.35441084 | Q38: =B38-E38 -> 0.32016667 | R38: =DamodaranUS!$C38-DamodaranUS!$B38 -> 0.58588916 | S38: =B38-F38 -> 0.29021219 | U38: ='[1]Inflation Rate'!C43 -> 0.0224719 | V38: =(1+B38)/(1+$U38)-1 -> 0.32836007 | W38: =(1+C38)/(1+$U38)-1 -> 0.90137255 | X38: =(1+D38)/(1+$U38)-1 -> -0.018261529 | Y38: =(1+E38)/(1+$U38)-1 -> 0.015230026 | Z38: =(1+F38)/(1+$U38)-1 -> 0.044526167 | AA38: =(1+G38)/(1+$U38)-1 -> 0.093207319 | AB38: =(1+H38)/(1+$U38)-1 -> 0.0028698137 | AC38: =AC37*(1+V38) -> 214.50779 | AD38: =AD37*(1+W38) -> 1092.9422 | AE38: =AE37*(1+X38) -> 113.28614 | AF38: =AF37*(1+Y38) -> 169.83197 | AG38: =AG37*(1+Z38) -> 298.45353 | AH38: =AH37*(1+AA38) -> 118.85723 | AI38: =AI37*(1+AB38) -> 159.85256 | AJ38: =DamodaranUS!$V38-DamodaranUS!$X38 -> 0.3466216 | AK38: =DamodaranUS!$V38-DamodaranUS!$Y38 -> 0.31313004
... A52: 1959 | B52: =('[1]S&P 500 & Raw Data'!B35-'[1]S&P 500 & Raw Data'!B34+'[1]S&P 500 & Raw Data'!C35)/'[1]S&P 500 & Raw Data'!B34 -> 0.12056457 | C52: ='[1]Small Cap'!B33 -> 0.127 | D52: ='[1]T. Bill rates'!C37 -> 0.033860159 | E52: ='[1]S&P 500 & Raw Data'!F35 -> -0.026466313 | F52: ='[1]S&P 500 & Raw Data'!J35 -> 0.015743431 | G52: ='[1]Home Prices'!B35/'[1]Home Prices'!B34-1 -> 0.0010952903 | H52: ='[1]Gold Prices'!B34/'[1]Gold Prices'!B33-1 -> 0 | I52: =I51*(1+B52) -> 1608.9516 | J52: =J51*(1+C52) -> 6180.9003 | K52: =K51*(1+D52) -> 149.84231 | L52: =L51*(1+E52) -> 214.55509 | M52: =M51*(1+F52) -> 440.94935 | N52: =N51*(1+G52) -> 259.31167 | O52: =O51*(1+H52) -> 170.05814 | P52: =B52-D52 -> 0.086704412 | Q52: =B52-E52 -> 0.14703088 | R52: =DamodaranUS!$C52-DamodaranUS!$B52 -> 0.0064354284 | S52: =B52-F52 -> 0.10482114 | U52: ='[1]Inflation Rate'!C57 -> 0.017301 | V52: =(1+B52)/(1+$U52)-1 -> 0.10150739 | W52: =(1+C52)/(1+$U52)-1 -> 0.10783337 | X52: =(1+D52)/(1+$U52)-1 -> 0.016277542 | Y52: =(1+E52)/(1+$U52)-1 -> -0.043022972 | Z52: =(1+F52)/(1+$U52)-1 -> -0.0015310799 | AA52: =(1+G52)/(1+$U52)-1 -> -0.015930103 | AB52: =(1+H52)/(1+$U52)-1 -> -0.017006766 | AC52: =AC51*(1+V52) -> 946.76414 | AD52: =AD51*(1+W52) -> 3688.0082 | AE52: =AE51*(1+X52) -> 88.172525 | AF52: =AF51*(1+Y52) -> 126.25182 | AG52: =AG51*(1+Z52) -> 259.47022 | AH52: =AH51*(1+AA52) -> 152.58817 | AI52: =AI51*(1+AB52) -> 100.06823 | AJ52: =DamodaranUS!$V52-DamodaranUS!$X52 -> 0.085229851 | AK52: =DamodaranUS!$V52-DamodaranUS!$Y52 -> 0.14453036
A53: 1960 | B53: =('[1]S&P 500 & Raw Data'!B36-'[1]S&P 500 & Raw Data'!B35+'[1]S&P 500 & Raw Data'!C36)/'[1]S&P 500 & Raw Data'!B35 -> 0.0033653531 | C53: ='[1]Small Cap'!B34 -> -0.0357 | D53: ='[1]T. Bill rates'!C38 -> 0.028729719 | E53: ='[1]S&P 500 & Raw Data'!F36 -> 0.11639504 | F53: ='[1]S&P 500 & Raw Data'!J36 -> 0.066631872 | G53: ='[1]Home Prices'!B36/'[1]Home Prices'!B35-1 -> 0.0076586433 | H53: ='[1]Gold Prices'!B35/'[1]Gold Prices'!B34-1 -> 0.0048433048 | I53: =I52*(1+B53) -> 1614.3663 | J53: =J52*(1+C53) -> 5960.2422 | K53: =K52*(1+D53) -> 154.14724 | L53: =L52*(1+E53) -> 239.52824 | M53: =M52*(1+F53) -> 470.33063 | N53: =N52*(1+G53) -> 261.29765 | O53: =O52*(1+H53) -> 170.88178 | P53: =B53-D53 -> -0.025364366 | Q53: =B53-E53 -> -0.11302968 | R53: =DamodaranUS!$C53-DamodaranUS!$B53 -> -0.039065353 | S53: =B53-F53 -> -0.063266518 | T53: =((I53/100)^(1/(A53-$A$21+1)))-((L53/100)^(1/(A53-$A$21+1))) -> 0.061119788 | U53: ='[1]Inflation Rate'!C58 -> 0.0136054 | V53: =(1+B53)/(1+$U53)-1 -> -0.010102597 | W53: =(1+C53)/(1+$U53)-1 -> -0.048643585 | X53: =(1+D53)/(1+$U53)-1 -> 0.014921309 | Y53: =(1+E53)/(1+$U53)-1 -> 0.10140991 | Z53: =(1+F53)/(1+$U53)-1 -> 0.052314709 | AA53: =(1+G53)/(1+$U53)-1 -> -0.0058669347 | AB53: =(1+H53)/(1+$U53)-1 -> -0.0086444835 | AC53: =AC52*(1+V53) -> 937.19936 | AD53: =AD52*(1+W53) -> 3508.6103 | AE53: =AE52*(1+X53) -> 89.488175 | AF53: =AF52*(1+Y53) -> 139.055 | AG53: =AG52*(1+Z53) -> 273.04433 | AH53: =AH52*(1+AA53) -> 151.69295 | AI53: =AI52*(1+AB53) -> 99.203195 | AJ53: =DamodaranUS!$V53-DamodaranUS!$X53 -> -0.025023905 | AK53: =DamodaranUS!$V53-DamodaranUS!$Y53 -> -0.11151251
A54: 1961 | B54: =('[1]S&P 500 & Raw Data'!B37-'[1]S&P 500 & Raw Data'!B36+'[1]S&P 500 & Raw Data'!C37)/'[1]S&P 500 & Raw Data'!B36 -> 0.26637713 | C54: ='[1]Small Cap'!B35 -> 0.2945 | D54: ='[1]T. Bill rates'!C39 -> 0.0235249 | E54: ='[1]S&P 500 & Raw Data'!F37 -> 0.020609208 | F54: ='[1]S&P 500 & Raw Data'!J37 -> 0.051 | G54: ='[1]Home Prices'!B37/'[1]Home Prices'!B36-1 -> 0.009771987 | H54: ='[1]Gold Prices'!B36/'[1]Gold Prices'!B35-1 -> -0.00056705415 | I54: =I53*(1+B54) -> 2044.3966 | J54: =J53*(1+C54) -> 7715.5335 | K54: =K53*(1+D54) -> 157.77354 | L54: =L53*(1+E54) -> 244.46473 | M54: =M53*(1+F54) -> 494.31749 | N54: =N53*(1+G54) -> 263.85104 | O54: =O53*(1+H54) -> 170.78488 | P54: =B54-D54 -> 0.24285223 | Q54: =B54-E54 -> 0.24576792 | R54: =DamodaranUS!$C54-DamodaranUS!$B54 -> 0.02812287 | S54: =B54-F54 -> 0.21537713 | T54: =((I54/100)^(1/(A54-$A$21+1)))-((L54/100)^(1/(A54-$A$21+1))) -> 0.066173592 | U54: ='[1]Inflation Rate'!C59 -> 0.0067114 | V54: =(1+B54)/(1+$U54)-1 -> 0.25793463 | W54: =(1+C54)/(1+$U54)-1 -> 0.28587001 | X54: =(1+D54)/(1+$U54)-1 -> 0.01670141 | Y54: =(1+E54)/(1+$U54)-1 -> 0.013805156 | Z54: =(1+F54)/(1+$U54)-1 -> 0.043993343 | AA54: =(1+G54)/(1+$U54)-1 -> 0.0030401831 | AB54: =(1+H54)/(1+$U54)-1 -> -0.0072299312 | AC54: =AC53*(1+V54) -> 1178.9355 | AD54: =AD53*(1+W54) -> 4511.6167 | AE54: =AE53*(1+X54) -> 90.982753 | AF54: =AF53*(1+Y54) -> 140.97468 | AG54: =AG53*(1+Z54) -> 285.05646 | AH54: =AH53*(1+AA54) -> 152.15412 | AI54: =AI53*(1+AB54) -> 98.485963 | AJ54: =DamodaranUS!$V54-DamodaranUS!$X54 -> 0.24123322 | AK54: =DamodaranUS!$V54-DamodaranUS!$Y54 -> 0.24412947
A55: 1962 | B55: =('[1]S&P 500 & Raw Data'!B38-'[1]S&P 500 & Raw Data'!B37+'[1]S&P 500 & Raw Data'!C38)/'[1]S&P 500 & Raw Data'!B37 -> -0.088114605 | C55: ='[1]Small Cap'!B36 -> -0.0978 | D55: ='[1]T. Bill rates'!C40 -> 0.027723695 | E55: ='[1]S&P 500 & Raw Data'!F38 -> 0.056935441 | F55: ='[1]S&P 500 & Raw Data'!J38 -> 0.06495328 | G55: ='[1]Home Prices'!B38/'[1]Home Prices'!B37-1 -> 0.0032258065 | H55: ='[1]Gold Prices'!B37/'[1]Gold Prices'!B36-1 -> -0.00056737589 | I55: =I54*(1+B55) -> 1864.2554 | J55: =J54*(1+C55) -> 6960.9543 | K55: =K54*(1+D55) -> 162.1476 | L55: =L54*(1+E55) -> 258.38343 | M55: =M54*(1+F55) -> 526.42504 | N55: =N54*(1+G55) -> 264.70218 | O55: =O54*(1+H55) -> 170.68798 | P55: =B55-D55 -> -0.1158383 | Q55: =B55-E55 -> -0.14505005 | R55: =DamodaranUS!$C55-DamodaranUS!$B55 -> -0.0096853948 | S55: =B55-F55 -> -0.15306789 | T55: =((I55/100)^(1/(A55-$A$21+1)))-((L55/100)^(1/(A55-$A$21+1))) -> 0.059683465 | U55: ='[1]Inflation Rate'!C60 -> 0.0133333 | V55: =(1+B55)/(1+$U55)-1 -> -0.10011307 | W55: =(1+C55)/(1+$U55)-1 -> -0.10967102 | X55: =(1+D55)/(1+$U55)-1 -> 0.014201048 | Y55: =(1+E55)/(1+$U55)-1 -> 0.04302843 | Z55: =(1+F55)/(1+$U55)-1 -> 0.050940771 | AA55: =(1+G55)/(1+$U55)-1 -> -0.0099745005 | AB55: =(1+H55)/(1+$U55)-1 -> -0.013717773 | AC55: =AC54*(1+V55) -> 1060.9087 | AD55: =AD54*(1+W55) -> 4016.8231 | AE55: =AE54*(1+X55) -> 92.274804 | AF55: =AF54*(1+Y55) -> 147.0406 | AG55: =AG54*(1+Z55) -> 299.57746 | AH55: =AH54*(1+AA55) -> 150.63646 | AI55: =AI54*(1+AB55) -> 97.134955 | AJ55: =DamodaranUS!$V55-DamodaranUS!$X55 -> -0.11431412 | AK55: =DamodaranUS!$V55-DamodaranUS!$Y55 -> -0.1431415
A56: 1963 | B56: =('[1]S&P 500 & Raw Data'!B39-'[1]S&P 500 & Raw Data'!B38+'[1]S&P 500 & Raw Data'!C39)/'[1]S&P 500 & Raw Data'!B38 -> 0.22611927 | C56: ='[1]Small Cap'!B37 -> 0.1965 | D56: ='[1]T. Bill rates'!C41 -> 0.031560241 | E56: ='[1]S&P 500 & Raw Data'!F39 -> 0.016841621 | F56: ='[1]S&P 500 & Raw Data'!J39 -> 0.054644806 | G56: ='[1]Home Prices'!B39/'[1]Home Prices'!B38-1 -> 0.021436227 | H56: ='[1]Gold Prices'!B38/'[1]Gold Prices'!B37-1 -> -0.0039738859 | I56: =I55*(1+B56) -> 2285.7995 | J56: =J55*(1+C56) -> 8328.7818 | K56: =K55*(1+D56) -> 167.26502 | L56: =L55*(1+E56) -> 262.73503 | M56: =M55*(1+F56) -> 555.19143 | N56: =N55*(1+G56) -> 270.37639 | O56: =O55*(1+H56) -> 170.00969 | P56: =B56-D56 -> 0.19455903 | Q56: =B56-E56 -> 0.20927765 | R56: =DamodaranUS!$C56-DamodaranUS!$B56 -> -0.029619271 | S56: =B56-F56 -> 0.17147447 | T56: =((I56/100)^(1/(A56-$A$21+1)))-((L56/100)^(1/(A56-$A$21+1))) -> 0.063618994 | U56: ='[1]Inflation Rate'!C61 -> 0.0164474 | V56: =(1+B56)/(1+$U56)-1 -> 0.20627912 | W56: =(1+C56)/(1+$U56)-1 -> 0.17713912 | X56: =(1+D56)/(1+$U56)-1 -> 0.014868296 | Y56: =(1+E56)/(1+$U56)-1 -> 0.00038784175 | Z56: =(1+F56)/(1+$U56)-1 -> 0.037579324 | AA56: =(1+G56)/(1+$U56)-1 -> 0.0049081017 | AB56: =(1+H56)/(1+$U56)-1 -> -0.020090844 | AC56: =AC55*(1+V56) -> 1279.752 | AD56: =AD55*(1+W56) -> 4728.3596 | AE56: =AE55*(1+X56) -> 93.646773 | AF56: =AF55*(1+Y56) -> 147.09763 | AG56: =AG55*(1+Z56) -> 310.83537 | AH56: =AH55*(1+AA56) -> 151.3758 | AI56: =AI55*(1+AB56) -> 95.183432 | AJ56: =DamodaranUS!$V56-DamodaranUS!$X56 -> 0.19141082 | AK56: =DamodaranUS!$V56-DamodaranUS!$Y56 -> 0.20589127
A57: 1964 | B57: =('[1]S&P 500 & Raw Data'!B40-'[1]S&P 500 & Raw Data'!B39+'[1]S&P 500 & Raw Data'!C40)/'[1]S&P 500 & Raw Data'!B39 -> 0.16415456 | C57: ='[1]Small Cap'!B38 -> 0.2325 | D57: ='[1]T. Bill rates'!C42 -> 0.035457371 | E57: ='[1]S&P 500 & Raw Data'!F40 -> 0.037280649 | F57: ='[1]S&P 500 & Raw Data'!J40 -> 0.051617393 | G57: ='[1]Home Prices'!B40/'[1]Home Prices'!B39-1 -> 0.012591815 | H57: ='[1]Gold Prices'!B39/'[1]Gold Prices'!B38-1 -> 0.00028498148 | I57: =I56*(1+B57) -> 2661.0239 | J57: =J56*(1+C57) -> 10265.224 | K57: =K56*(1+D57) -> 173.1958 | L57: =L56*(1+E57) -> 272.52996 | M57: =M56*(1+F57) -> 583.84896 | N57: =N56*(1+G57) -> 273.78092 | O57: =O56*(1+H57) -> 170.05814 | P57: =B57-D57 -> 0.12869719 | Q57: =B57-E57 -> 0.12687391 | R57: =DamodaranUS!$C57-DamodaranUS!$B57 -> 0.068345441 | S57: =B57-F57 -> 0.11253717 | T57: =((I57/100)^(1/(A57-$A$21+1)))-((L57/100)^(1/(A57-$A$21+1))) -> 0.065267777 | U57: ='[1]Inflation Rate'!C62 -> 0.0097087 | V57: =(1+B57)/(1+$U57)-1 -> 0.15296081 | W57: =(1+C57)/(1+$U57)-1 -> 0.22064908 | X57: =(1+D57)/(1+$U57)-1 -> 0.025501088 | Y57: =(1+E57)/(1+$U57)-1 -> 0.027306835 | Z57: =(1+F57)/(1+$U57)-1 -> 0.041505726 | AA57: =(1+G57)/(1+$U57)-1 -> 0.0028553932 | AB57: =(1+H57)/(1+$U57)-1 -> -0.0093331062 | AC57: =AC56*(1+V57) -> 1475.5039 | AD57: =AD56*(1+W57) -> 5771.6678 | AE57: =AE56*(1+X57) -> 96.034867 | AF57: =AF56*(1+Y57) -> 151.1144 | AG57: =AG56*(1+Z57) -> 323.73682 | AH57: =AH56*(1+AA57) -> 151.80804 | AI57: =AI56*(1+AB57) -> 94.295075 | AJ57: =DamodaranUS!$V57-DamodaranUS!$X57 -> 0.12745972 | AK57: =DamodaranUS!$V57-DamodaranUS!$Y57 -> 0.12565397
A58: 1965 | B58: =('[1]S&P 500 & Raw Data'!B41-'[1]S&P 500 & Raw Data'!B40+'[1]S&P 500 & Raw Data'!C41)/'[1]S&P 500 & Raw Data'!B40 -> 0.12399242 | C58: ='[1]Small Cap'!B39 -> 0.4524 | D58: ='[1]T. Bill rates'!C43 -> 0.039490763 | E58: ='[1]S&P 500 & Raw Data'!F41 -> 0.0071885509 | F58: ='[1]S&P 500 & Raw Data'!J41 -> 0.031900095 | G58: ='[1]Home Prices'!B41/'[1]Home Prices'!B40-1 -> 0.016580311 | H58: ='[1]Gold Prices'!B40/'[1]Gold Prices'!B39-1 -> 0.00056980057 | I58: =I57*(1+B58) -> 2990.9707 | J58: =J57*(1+C58) -> 14909.211 | K58: =K57*(1+D58) -> 180.03543 | L58: =L57*(1+E58) -> 274.48906 | M58: =M57*(1+F58) -> 602.4738 | N58: =N57*(1+G58) -> 278.3203 | O58: =O57*(1+H58) -> 170.15504 | P58: =B58-D58 -> 0.084501662 | Q58: =B58-E58 -> 0.11680387 | R58: =DamodaranUS!$C58-DamodaranUS!$B58 -> 0.32840758 | S58: =B58-F58 -> 0.09209233 | T58: =((I58/100)^(1/(A58-$A$21+1)))-((L58/100)^(1/(A58-$A$21+1))) -> 0.066617942 | U58: ='[1]Inflation Rate'!C63 -> 0.0192308 | V58: =(1+B58)/(1+$U58)-1 -> 0.10278499 | W58: =(1+C58)/(1+$U58)-1 -> 0.42499618 | X58: =(1+D58)/(1+$U58)-1 -> 0.019877699 | Y58: =(1+E58)/(1+$U58)-1 -> -0.011815036 | Z58: =(1+F58)/(1+$U58)-1 -> 0.012430251 | AA58: =(1+G58)/(1+$U58)-1 -> -0.0026004798 | AB58: =(1+H58)/(1+$U58)-1 -> -0.018308905 | AC58: =AC57*(1+V58) -> 1627.1635 | AD58: =AD57*(1+W58) -> 8224.6046 | AE58: =AE57*(1+X58) -> 97.94382 | AF58: =AF57*(1+Y58) -> 149.32897 | AG58: =AG57*(1+Z58) -> 327.76095 | AH58: =AH57*(1+AA58) -> 151.41326 | AI58: =AI57*(1+AB58) -> 92.568635 | AJ58: =DamodaranUS!$V58-DamodaranUS!$X58 -> 0.082907288 | AK58: =DamodaranUS!$V58-DamodaranUS!$Y58 -> 0.11460002
A59: 1966 | B59: =('[1]S&P 500 & Raw Data'!B42-'[1]S&P 500 & Raw Data'!B41+'[1]S&P 500 & Raw Data'!C42)/'[1]S&P 500 & Raw Data'!B41 -> -0.099709542 | C59: ='[1]Small Cap'!B40 -> -0.0947 | D59: ='[1]T. Bill rates'!C44 -> 0.0485572 | E59: ='[1]S&P 500 & Raw Data'!F42 -> 0.029079409 | F59: ='[1]S&P 500 & Raw Data'!J42 -> -0.034453616 | G59: ='[1]Home Prices'!B42/'[1]Home Prices'!B41-1 -> 0.012232416 | H59: ='[1]Gold Prices'!B41/'[1]Gold Prices'!B40-1 -> 0.00028473804 | I59: =I58*(1+B59) -> 2692.7424 | J59: =J58*(1+C59) -> 13497.309 | K59: =K58*(1+D59) -> 188.77745 | L59: =L58*(1+E59) -> 282.47104 | M59: =M58*(1+F59) -> 581.7164 | N59: =N58*(1+G59) -> 281.72482 | O59: =O58*(1+H59) -> 170.20349 | P59: =B59-D59 -> -0.14826674 | Q59: =B59-E59 -> -0.12878895 | R59: =DamodaranUS!$C59-DamodaranUS!$B59 -> 0.0050095424 | S59: =B59-F59 -> -0.065255926 | T59: =((I59/100)^(1/(A59-$A$21+1)))-((L59/100)^(1/(A59-$A$21+1))) -> 0.06112372 | U59: ='[1]Inflation Rate'!C64 -> 0.0345912 | V59: =(1+B59)/(1+$U59)-1 -> -0.12981044 | W59: =(1+C59)/(1+$U59)-1 -> -0.12496839 | X59: =(1+D59)/(1+$U59)-1 -> 0.013499052 | Y59: =(1+E59)/(1+$U59)-1 -> -0.0053275059 | Z59: =(1+F59)/(1+$U59)-1 -> -0.066736326 | AA59: =(1+G59)/(1+$U59)-1 -> -0.021611226 | AB59: =(1+H59)/(1+$U59)-1 -> -0.033159437 | AC59: =AC58*(1+V59) -> 1415.9407 | AD59: =AD58*(1+W59) -> 7196.789 | AE59: =AE58*(1+X59) -> 99.265968 | AF59: =AF58*(1+Y59) -> 148.53342 | AG59: =AG58*(1+Z59) -> 305.88739 | AH59: =AH58*(1+AA59) -> 148.14104 | AI59: =AI58*(1+AB59) -> 89.499111 | AJ59: =DamodaranUS!$V59-DamodaranUS!$X59 -> -0.14330949 | AK59: =DamodaranUS!$V59-DamodaranUS!$Y59 -> -0.12448294
A60: 1967 | B60: =('[1]S&P 500 & Raw Data'!B43-'[1]S&P 500 & Raw Data'!B42+'[1]S&P 500 & Raw Data'!C43)/'[1]S&P 500 & Raw Data'!B42 -> 0.23802967 | C60: ='[1]Small Cap'!B41 -> 1.1587 | D60: ='[1]T. Bill rates'!C45 -> 0.042934538 | E60: ='[1]S&P 500 & Raw Data'!F43 -> -0.01580621 | F60: ='[1]S&P 500 & Raw Data'!J43 -> 0.0089522661 | G60: ='[1]Home Prices'!B43/'[1]Home Prices'!B42-1 -> 0.023162135 | H60: ='[1]Gold Prices'!B42/'[1]Gold Prices'!B41-1 -> -0.0051238258 | I60: =I59*(1+B60) -> 3333.6949 | J60: =J59*(1+C60) -> 29136.64 | K60: =K59*(1+D60) -> 196.88252 | L60: =L59*(1+E60) -> 278.00624 | M60: =M59*(1+F60) -> 586.92408 | N60: =N59*(1+G60) -> 288.25017 | O60: =O59*(1+H60) -> 169.3314 | P60: =B60-D60 -> 0.19509513 | Q60: =B60-E60 -> 0.25383588 | R60: =DamodaranUS!$C60-DamodaranUS!$B60 -> 0.92067033 | S60: =B60-F60 -> 0.2290774 | T60: =((I60/100)^(1/(A60-$A$21+1)))-((L60/100)^(1/(A60-$A$21+1))) -> 0.065732839 | U60: ='[1]Inflation Rate'!C65 -> 0.0303951 | V60: =(1+B60)/(1+$U60)-1 -> 0.20150966 | W60: =(1+C60)/(1+$U60)-1 -> 1.0950216 | X60: =(1+D60)/(1+$U60)-1 -> 0.012169544 | Y60: =(1+E60)/(1+$U60)-1 -> -0.044838441 | Z60: =(1+F60)/(1+$U60)-1 -> -0.020810303 | AA60: =(1+G60)/(1+$U60)-1 -> -0.0070196035 | AB60: =(1+H60)/(1+$U60)-1 -> -0.034471171 | AC60: =AC59*(1+V60) -> 1701.2664 | AD60: =AD59*(1+W60) -> 15077.428 | AE60: =AE59*(1+X60) -> 100.47399 | AF60: =AF59*(1+Y60) -> 141.87342 | AG60: =AG59*(1+Z60) -> 299.52178 | AH60: =AH59*(1+AA60) -> 147.10115 | AI60: =AI59*(1+AB60) -> 86.413972 | AJ60: =DamodaranUS!$V60-DamodaranUS!$X60 -> 0.18934012 | AK60: =DamodaranUS!$V60-DamodaranUS!$Y60 -> 0.2463481
A61: 1968 | B61: =('[1]S&P 500 & Raw Data'!B44-'[1]S&P 500 & Raw Data'!B43+'[1]S&P 500 & Raw Data'!C44)/'[1]S&P 500 & Raw Data'!B43 -> 0.10814863 | C61: ='[1]Small Cap'!B42 -> 0.6069 | D61: ='[1]T. Bill rates'!C46 -> 0.053376 | E61: ='[1]S&P 500 & Raw Data'!F44 -> 0.032746197 | F61: ='[1]S&P 500 & Raw Data'!J44 -> 0.048451462 | G61: ='[1]Home Prices'!B44/'[1]Home Prices'!B43-1 -> 0.041338583 | H61: ='[1]Gold Prices'!B43/'[1]Gold Prices'!B42-1 -> 0.12474964 | I61: =I60*(1+B61) -> 3694.2294 | J61: =J60*(1+C61) -> 46819.667 | K61: =K60*(1+D61) -> 207.39133 | L61: =L60*(1+E61) -> 287.10989 | M61: =M60*(1+F61) -> 615.36141 | N61: =N60*(1+G61) -> 300.16603 | O61: =O60*(1+H61) -> 190.45543 | P61: =B61-D61 -> 0.054772627 | Q61: =B61-E61 -> 0.07540243 | R61: =DamodaranUS!$C61-DamodaranUS!$B61 -> 0.49875137 | S61: =B61-F61 -> 0.059697164 | T61: =((I61/100)^(1/(A61-$A$21+1)))-((L61/100)^(1/(A61-$A$21+1))) -> 0.065966278 | U61: ='[1]Inflation Rate'!C66 -> 0.0471976 | V61: =(1+B61)/(1+$U61)-1 -> 0.05820394 | W61: =(1+C61)/(1+$U61)-1 -> 0.5344764 | X61: =(1+D61)/(1+$U61)-1 -> 0.0058999371 | Y61: =(1+E61)/(1+$U61)-1 -> -0.013800073 | Z61: =(1+F61)/(1+$U61)-1 -> 0.0011973502 | AA61: =(1+G61)/(1+$U61)-1 -> -0.0055949492 | AB61: =(1+H61)/(1+$U61)-1 -> 0.074056742 | AC61: =AC60*(1+V61) -> 1800.2868 | AD61: =AD60*(1+W61) -> 23135.958 | AE61: =AE60*(1+X61) -> 101.06678 | AF61: =AF60*(1+Y61) -> 139.91555 | AG61: =AG60*(1+Z61) -> 299.88041 | AH61: =AH60*(1+AA61) -> 146.27812 | AI61: =AI60*(1+AB61) -> 92.813509 | AJ61: =DamodaranUS!$V61-DamodaranUS!$X61 -> 0.052304003 | AK61: =DamodaranUS!$V61-DamodaranUS!$Y61 -> 0.072004013
A62: 1969 | B62: =('[1]S&P 500 & Raw Data'!B45-'[1]S&P 500 & Raw Data'!B44+'[1]S&P 500 & Raw Data'!C45)/'[1]S&P 500 & Raw Data'!B44 -> -0.082413711 | C62: ='[1]Small Cap'!B43 -> -0.3295 | D62: ='[1]T. Bill rates'!C47 -> 0.066684677 | E62: ='[1]S&P 500 & Raw Data'!F45 -> -0.050140493 | F62: ='[1]S&P 500 & Raw Data'!J45 -> -0.020251643 | G62: ='[1]Home Prices'!B45/'[1]Home Prices'!B44-1 -> 0.069943289 | H62: ='[1]Gold Prices'!B44/'[1]Gold Prices'!B43-1 -> 0.050114475 | I62: =I61*(1+B62) -> 3389.7743 | J62: =J61*(1+C62) -> 31392.587 | K62: =K61*(1+D62) -> 221.22115 | L62: =L61*(1+E62) -> 272.71406 | M62: =M61*(1+F62) -> 602.89933 | N62: =N61*(1+G62) -> 321.16063 | O62: =O61*(1+H62) -> 200 | P62: =B62-D62 -> -0.14909839 | Q62: =B62-E62 -> -0.032273218 | R62: =DamodaranUS!$C62-DamodaranUS!$B62 -> -0.24708629 | S62: =B62-F62 -> -0.062162068 | T62: =((I62/100)^(1/(A62-$A$21+1)))-((L62/100)^(1/(A62-$A$21+1))) -> 0.063333873 | U62: ='[1]Inflation Rate'!C67 -> 0.0619718 | V62: =(1+B62)/(1+$U62)-1 -> -0.13595984 | W62: =(1+C62)/(1+$U62)-1 -> -0.3686273 | X62: =(1+D62)/(1+$U62)-1 -> 0.0044378555 | Y62: =(1+E62)/(1+$U62)-1 -> -0.10556993 | Z62: =(1+F62)/(1+$U62)-1 -> -0.07742526 | AA62: =(1+G62)/(1+$U62)-1 -> 0.0075063097 | AB62: =(1+H62)/(1+$U62)-1 -> -0.011165386 | AC62: =AC61*(1+V62) -> 1555.5201 | AD62: =AD61*(1+W62) -> 14607.412 | AE62: =AE61*(1+X62) -> 101.5153 | AF62: =AF61*(1+Y62) -> 125.14468 | AG62: =AG61*(1+Z62) -> 276.66209 | AH62: =AH61*(1+AA62) -> 147.37613 | AI62: =AI61*(1+AB62) -> 91.777211 | AJ62: =DamodaranUS!$V62-DamodaranUS!$X62 -> -0.14039769 | AK62: =DamodaranUS!$V62-DamodaranUS!$Y62 -> -0.030389901
A63: 1970 | B63: =('[1]S&P 500 & Raw Data'!B46-'[1]S&P 500 & Raw Data'!B45+'[1]S&P 500 & Raw Data'!C46)/'[1]S&P 500 & Raw Data'!B45 -> 0.035611449 | C63: ='[1]Small Cap'!B44 -> -0.1878 | D63: ='[1]T. Bill rates'!C48 -> 0.06391 | E63: ='[1]S&P 500 & Raw Data'!F46 -> 0.16754737 | F63: ='[1]S&P 500 & Raw Data'!J46 -> 0.056495677 | G63: ='[1]Home Prices'!B46/'[1]Home Prices'!B45-1 -> 0.082155477 | H63: ='[1]Gold Prices'!B45/'[1]Gold Prices'!B44-1 -> -0.094476744 | I63: =I62*(1+B63) -> 3510.4891 | J63: =J62*(1+C63) -> 25497.059 | K63: =K62*(1+D63) -> 235.35939 | L63: =L62*(1+E63) -> 318.40658 | M63: =M62*(1+F63) -> 636.96054 | N63: =N62*(1+G63) -> 347.54573 | O63: =O62*(1+H63) -> 181.10465 | P63: =B63-D63 -> -0.028298551 | Q63: =B63-E63 -> -0.13193592 | R63: =DamodaranUS!$C63-DamodaranUS!$B63 -> -0.22341145 | S63: =B63-F63 -> -0.020884228 | T63: =((I63/100)^(1/(A63-$A$21+1)))-((L63/100)^(1/(A63-$A$21+1))) -> 0.058972567 | U63: ='[1]Inflation Rate'!C68 -> 0.0557029 | V63: =(1+B63)/(1+$U63)-1 -> -0.01903135 | W63: =(1+C63)/(1+$U63)-1 -> -0.23065476 | X63: =(1+D63)/(1+$U63)-1 -> 0.0077740622 | Y63: =(1+E63)/(1+$U63)-1 -> 0.10594313 | Z63: =(1+F63)/(1+$U63)-1 -> 0.00075094666 | AA63: =(1+G63)/(1+$U63)-1 -> 0.025056838 | AB63: =(1+H63)/(1+$U63)-1 -> -0.1422556 | AC63: =AC62*(1+V63) -> 1525.9165 | AD63: =AD62*(1+W63) -> 11238.143 | AE63: =AE62*(1+X63) -> 102.30449 | AF63: =AF62*(1+Y63) -> 138.4029 | AG63: =AG62*(1+Z63) -> 276.86985 | AH63: =AH62*(1+AA63) -> 151.06891 | AI63: =AI62*(1+AB63) -> 78.721389 | AJ63: =DamodaranUS!$V63-DamodaranUS!$X63 -> -0.026805412 | AK63: =DamodaranUS!$V63-DamodaranUS!$Y63 -> -0.12497448
A64: 1971 | B64: =('[1]S&P 500 & Raw Data'!B47-'[1]S&P 500 & Raw Data'!B46+'[1]S&P 500 & Raw Data'!C47)/'[1]S&P 500 & Raw Data'!B46 -> 0.1422115 | C64: ='[1]Small Cap'!B45 -> 0.1596 | D64: ='[1]T. Bill rates'!C49 -> 0.04334257 | E64: ='[1]S&P 500 & Raw Data'!F47 -> 0.097868966 | F64: ='[1]S&P 500 & Raw Data'!J47 -> 0.14001466 | G64: ='[1]Home Prices'!B47/'[1]Home Prices'!B46-1 -> 0.04244898 | H64: ='[1]Gold Prices'!B46/'[1]Gold Prices'!B45-1 -> 0.16693419 | I64: =I63*(1+B64) -> 4009.721 | J64: =J63*(1+C64) -> 29566.389 | K64: =K63*(1+D64) -> 245.56047 | L64: =L63*(1+E64) -> 349.5687 | M64: =M63*(1+F64) -> 726.14435 | N64: =N63*(1+G64) -> 362.29869 | O64: =O63*(1+H64) -> 211.33721 | P64: =B64-D64 -> 0.098868933 | Q64: =B64-E64 -> 0.044342537 | R64: =DamodaranUS!$C64-DamodaranUS!$B64 -> 0.017388497 | S64: =B64-F64 -> 0.0021968412 | T64: =((I64/100)^(1/(A64-$A$21+1)))-((L64/100)^(1/(A64-$A$21+1))) -> 0.058660637 | U64: ='[1]Inflation Rate'!C69 -> 0.0326633 | V64: =(1+B64)/(1+$U64)-1 -> 0.10608318 | W64: =(1+C64)/(1+$U64)-1 -> 0.12292167 | X64: =(1+D64)/(1+$U64)-1 -> 0.010341483 | Y64: =(1+E64)/(1+$U64)-1 -> 0.063143201 | Z64: =(1+F64)/(1+$U64)-1 -> 0.10395582 | AA64: =(1+G64)/(1+$U64)-1 -> 0.009476157 | AB64: =(1+H64)/(1+$U64)-1 -> 0.13002388 | AC64: =AC63*(1+V64) -> 1687.7906 | AD64: =AD63*(1+W64) -> 12619.554 | AE64: =AE63*(1+X64) -> 103.36247 | AF64: =AF63*(1+Y64) -> 147.1421 | AG64: =AG63*(1+Z64) -> 305.65209 | AH64: =AH63*(1+AA64) -> 152.50046 | AI64: =AI63*(1+AB64) -> 88.957049 | AJ64: =DamodaranUS!$V64-DamodaranUS!$X64 -> 0.095741693 | AK64: =DamodaranUS!$V64-DamodaranUS!$Y64 -> 0.042939975
... A118: 2025 | B118: =('[1]S&P 500 & Raw Data'!B101-'[1]S&P 500 & Raw Data'!B100+'[1]S&P 500 & Raw Data'!C101)/'[1]S&P 500 & Raw Data'!B100 -> 0.17723658 | C118: ='[1]Small Cap'!B99 -> 0.1653 | D118: ='[1]T. Bill rates'!C103 -> 0.0421 | E118: ='[1]S&P 500 & Raw Data'!F101 -> 0.077954809 | F118: ='[1]S&P 500 & Raw Data'!J101 -> 0.069627321 | G118: ='[1]Home Prices'!B101/'[1]Home Prices'!B100-1 -> 0.015757066 | H118: ='[1]Gold Prices'!B100/'[1]Gold Prices'!B99-1 -> 0.66215792 | I118: =I117*(1+B118) -> 1157009.1 | J118: =J117*(1+C118) -> 6462598.5 | K118: =K117*(1+D118) -> 2578.2961 | L118: =L117*(1+E118) -> 7717.5629 | M118: =M117*(1+F118) -> 53952.414 | N118: =N117*(1+G118) -> 5626.0181 | O118: =O117*(1+H118) -> 21025.412 | P118: =B118-D118 -> 0.13513658 | Q118: =B118-E118 -> 0.099281774 | R118: =DamodaranUS!$C118-DamodaranUS!$B118 -> -0.011936582 | S118: =B118-F118 -> 0.10760926 | T118: =((I118/100)^(1/(A118-$A$21+1)))-((L118/100)^(1/(A118-$A$21+1))) -> 0.054831293 | U118: ='[1]Inflation Rate'!C123 -> 0.0273508 | V118: =(1+B118)/(1+$U118)-1 -> 0.14589543 | W118: =(1+C118)/(1+$U118)-1 -> 0.13427663 | X118: =(1+D118)/(1+$U118)-1 -> 0.014356537 | Y118: =(1+E118)/(1+$U118)-1 -> 0.049256796 | Z118: =(1+F118)/(1+$U118)-1 -> 0.041151008 | AA118: =(1+G118)/(1+$U118)-1 -> -0.011285078 | AB118: =(1+H118)/(1+$U118)-1 -> 0.61790687 | AC118: =AC117*(1+V118) -> 61733.438 | AD118: =AD117*(1+W118) -> 349648.92 | AE118: =AE117*(1+X118) -> 137.5677 | AF118: =AF117*(1+Y118) -> 411.77869 | AG118: =AG117*(1+Z118) -> 2878.6878 | AH118: =AH117*(1+AA118) -> 300.18212 | AI118: =AI117*(1+AB118) -> 1121.833 | AJ118: =DamodaranUS!$V118-DamodaranUS!$X118 -> 0.13153889 | AK118: =DamodaranUS!$V118-DamodaranUS!$Y118 -> 0.09663863
A120: Arithmetic Average Historical Return | L120: Equity Risk Premium (Arithmetic) | N120: Standard Error | Q120: Small Cap Premium (Arithmetic) | U120: Arithmetic Average Annual Real Return
A121: 1928-2025 | B121: =AVERAGE(B21:B118) -> 0.11854651 | C121: =AVERAGE(C21:C118) -> 0.17775204 | D121: =AVERAGE(D21:D118) -> 0.03414946 | E121: =AVERAGE(E21:E118) -> 0.048223617 | F121: =AVERAGE(F21:F118) -> 0.069019176 | G121: =AVERAGE(G21:G118) -> 0.043778034 | H121: =AVERAGE(H21:H118) -> 0.073609573 | L121: Stocks - T.Bills | M121: Stocks - T.Bonds | N121: Stocks - T.Bills | O121: Stocks - T.Bonds | Q121: S&P 500 minus Lowest Decile | R121: Standard Error | V121: S&P 500 (includes dividends)2 | W121: =DamodaranUS!$W$20 -> US Small cap (bottom decile)22 | X121: 3-month T. Bill (Real) | Y121: !0-year T.Bonds | Z121: Baa Corp Bonds | AA121: Real Estate3 | AB121: Gold | AH121: Standard Error
A122: 1976-2025 | B122: =AVERAGE(B69:B118) -> 0.13168705 | C122: =AVERAGE(C69:C118) -> 0.147852 | D122: =AVERAGE(D69:D118) -> 0.043697642 | E122: =AVERAGE(E69:E118) -> 0.066047219 | F122: =AVERAGE(F69:F118) -> 0.08859151 | G122: =AVERAGE(G69:G118) -> 0.053205468 | H122: =AVERAGE(H69:H118) -> 0.093791212 | L122: =B121-D121 -> 0.08439705 | M122: =B121-E121 -> 0.070322894 | N122: =STDEV(P21:P118)/(($A$117-$A$21+1)^0.5) -> 0.020006045 | O122: =STDEV(Q21:Q117)/(($A$117-$A$21+1)^0.5) -> 0.021243404 | Q122: =C121-B121 -> 0.05920553 | R122: =STDEV(R21:R118)/(($A$117-$A$21+1)^0.5) -> 0.027902961 | U122: 1928-2025 | V122: =AVERAGE(V21:V118) -> 0.086085266 | W122: =AVERAGE(W21:W118) -> 0.14376315 | X122: =AVERAGE(X21:X118) -> 0.0039827039 | Y122: =AVERAGE(Y21:Y118) -> 0.018335945 | Z122: =AVERAGE(Z21:Z118) -> 0.038559479 | AA122: =AVERAGE(AA21:AA118) -> 0.012503695 | AB122: =AVERAGE(AB21:AB118) -> 0.040701806 | AH122: Stocks - T.Bills | AI122: Stocks - T.Bonds
A123: 2016-2025 | B123: =AVERAGE(B109:B118) -> 0.15748088 | C123: =AVERAGE(C109:C118) -> 0.09195 | D123: =AVERAGE(D109:D118) -> 0.02251 | E123: =AVERAGE(E109:E118) -> 0.012237197 | F123: =AVERAGE(F109:F118) -> 0.046564713 | G123: =AVERAGE(G109:G118) -> 0.065875804 | H123: =AVERAGE(H109:H118) -> 0.16531354 | L123: =B122-D122 -> 0.087989409 | M123: =B122-E122 -> 0.065639832 | N123: =STDEV(P68:P117)/(($A$117-$A$68+1)^0.5) -> 0.0230134 | O123: =STDEV(Q68:Q117)/(($A$117-$A$68+1)^0.5) -> 0.02673559 | Q123: =C122-B122 -> 0.016164949 | R123: =STDEV(R68:R117)/(($A$117-$A$68+1)^0.5) -> 0.027623455 | U123: 1976-2025 | V123: =AVERAGE(V69:V118) -> 0.092659682 | W123: =AVERAGE(W69:W118) -> 0.10765174 | X123: =AVERAGE(X69:X118) -> 0.0072995086 | Y123: =AVERAGE(Y69:Y118) -> 0.029952737 | Z123: =AVERAGE(Z69:Z118) -> 0.051644447 | AA123: =AVERAGE(AA69:AA118) -> 0.016488194 | AB123: =AVERAGE(AB69:AB118) -> 0.054267297 | AH123: =STDEV(AJ22:AJ118)/(($A$118-$A$21+1)^0.5) -> 0.019417539 | AI123: =STDEV(AK22:AK118)/(($A$118-$A$21+1)^0.5) -> 0.0204592
L124: =B123-D123 -> 0.13497088 | M124: =B123-E123 -> 0.14524368 | N124: =STDEV(P108:P117)/(($A$117-$A$108+1)^0.5) -> 0.050359055 | O124: =STDEV(Q108:Q117)/(($A$117-$A$108+1)^0.5) -> 0.040102345 | Q124: =C123-B123 -> -0.065530875 | R124: =STDEV(R108:R117)/(($A$117-$A$108+1)^0.5) -> 0.035800241 | U124: 2016-2025 | V124: =AVERAGE(V109:V118) -> 0.12224209 | W124: =AVERAGE(W109:W118) -> 0.059033042 | X124: =AVERAGE(X109:X118) -> -0.0090627833 | Y124: =AVERAGE(Y109:Y118) -> -0.018017791 | Z124: =AVERAGE(Z109:Z118) -> 0.015157405 | AA124: =AVERAGE(AA109:AA118) -> 0.032512805 | AB124: =AVERAGE(AB109:AB118) -> 0.13054597 | AH124: =STDEV(AJ69:AJ118)/(($A$118-$A$69+1)^0.5) -> 0.021924373 | AI124: =STDEV(AK69:AK118)/(($A$118-$A$69+1)^0.5) -> 0.025445638
A125: Geometric Average Historical Return | L125: Equity Risk Premium (Geometric) | Q125: Small Cap Premium (Geometric) | U125: Geometric Average Historical Return | AH125: =STDEV(AJ109:AJ118)/(($A$118-$A$109+1)^0.5) -> 0.046760655 | AI125: =STDEV(AK109:AK118)/(($A$118-$A$109+1)^0.5) -> 0.035861149
A126: 1928-2025 | B126: =(I118/100)^(1/($A$118-$A$21+1))-1 -> 0.10017715 | C126: =(J118/100)^(1/($A$118-$A$21+1))-1 -> 0.11965903 | D126: =(K118/100)^(1/($A$118-$A$21+1))-1 -> 0.033716278 | E126: =(L118/100)^(1/($A$118-$A$21+1))-1 -> 0.045345856 | F126: =(M118/100)^(1/($A$118-$A$21+1))-1 -> 0.06629571 | G126: =(N118/100)^(1/($A$118-$A$21+1))-1 -> 0.041979549 | H126: =(O118/100)^(1/($A$118-$A$21+1))-1 -> 0.056091323 | L126: Stocks - T.Bills | M126: Stocks - T.Bonds | Q126: S&P 500 minus Lowest Decile | U126: 1928-2025 | V126: =(AC118/100)^(1/($A$118-$A$21+1))-1 -> 0.067762584 | W126: =(AD118/100)^(1/($A$118-$A$21+1))-1 -> 0.086824731 | X126: =(AE118/100)^(1/($A$118-$A$21+1))-1 -> 0.0032598528 | Y126: =(AF118/100)^(1/($A$118-$A$21+1))-1 -> 0.014546788 | Z126: =(AG118/100)^(1/($A$118-$A$21+1))-1 -> 0.034879396 | AA126: =(AH118/100)^(1/($A$118-$A$21+1))-1 -> 0.011279663 | AB126: =(AI118/100)^(1/($A$118-$A$21+1))-1 -> 0.024975662
A127: 1976-2025 | B127: =(I118/I68)^(1/($A$118-$A$68))-1 -> 0.1192377 | C127: =(J118/J68)^(1/($A$118-$A$68))-1 -> 0.12124341 | D127: =(K118/K68)^(1/($A$118-$A$68))-1 -> 0.043139631 | E127: =(L118/L68)^(1/($A$118-$A$68))-1 -> 0.061320983 | F127: =(M118/M68)^(1/($A$118-$A$68))-1 -> 0.085407653 | G127: =(N118/N68)^(1/($A$118-$A$68))-1 -> 0.051653769 | H127: =(O118/O68)^(1/($A$118-$A$68))-1 -> 0.07105316 | L127: =B126-D126 -> 0.066460871 | M127: =B126-E126 -> 0.054831293 | Q127: =C126-B126 -> 0.019481883 | U127: 1976-2025 | V127: =(AC118/AC68)^(1/($A$118-$A$68))-1 -> 0.080415829 | W127: =(AD118/AD68)^(1/($A$118-$A$68))-1 -> 0.082351976 | X127: =(AE118/AE68)^(1/($A$118-$A$68))-1 -> 0.0069573001 | Y127: =(AF118/AF68)^(1/($A$118-$A$68))-1 -> 0.024508014 | Z127: =(AG118/AG68)^(1/($A$118-$A$68))-1 -> 0.047759214 | AA127: =(AH118/AH68)^(1/($A$118-$A$68))-1 -> 0.015176116 | AB127: =(AI118/AI68)^(1/($A$118-$A$68))-1 -> 0.03390262
A128: 2016-2025 | B128: =(I118/I108)^(1/($A$118-$A$108))-1 -> 0.14678457 | C128: =(J118/J108)^(1/($A$118-$A$108))-1 -> 0.078619969 | D128: =(K118/K108)^(1/($A$118-$A$108))-1 -> 0.022336937 | E128: =(L118/L108)^(1/($A$118-$A$108))-1 -> 0.0089181555 | F128: =(M118/M108)^(1/($A$118-$A$108))-1 -> 0.042909742 | G128: =(N118/N108)^(1/($A$118-$A$108))-1 -> 0.064920056 | H128: =(O118/O108)^(1/($A$118-$A$108))-1 -> 0.1513698 | L128: =B127-D127 -> 0.076098066 | M128: =B127-E127 -> 0.057916714 | Q128: =C127-B127 -> 0.0020057169 | U128: 2016-2025 | V128: =(AC118/AC108)^(1/($A$118-$A$108))-1 -> 0.11117711 | W128: =(AD118/AD108)^(1/($A$118-$A$108))-1 -> 0.045129 | X128: =(AE118/AE108)^(1/($A$118-$A$108))-1 -> -0.0094064532 | Y128: =(AF118/AF108)^(1/($A$118-$A$108))-1 -> -0.022408584 | Z128: =(AG118/AG108)^(1/($A$118-$A$108))-1 -> 0.01052757 | AA128: =(AH118/AH108)^(1/($A$118-$A$108))-1 -> 0.031854467 | AB128: =(AI118/AI108)^(1/($A$118-$A$108))-1 -> 0.11561996
L129: =B128-D128 -> 0.12444764 | M129: =B128-E128 -> 0.13786642 | Q129: =C128-B128 -> -0.068164606
A130: Note
A131: * Prior to 1971, gold prices were fixed and with the gold standard in place, and were mostly stable.

Sheet Tornado Chart Data
A1: Tornado Chart: Impact of each variable on the Buy-Rent net worth difference
A3: Variable | B3: Low value | C3: High value | D3: Baseline diff (CZK) | E3: Diff at low (CZK) | F3: Diff at high (CZK) | G3: Range (CZK)
A4: Rent growth | B4: 3% | C4: 7% | D4: 21323798 | E4: -19331040 | F4: 84342899 | G4: 103673939
A5: Investment return | B5: 6% | C5: 10% | D5: 21323798 | E5: 49071518 | F5: -34520334 | G5: 83591852
A6: RE price growth | B6: 3% | C6: 7% | D6: 21323798 | E6: 2697057 | F6: 68424873 | G6: 65727816
A7: Mortgage rate | B7: 2.5% | C7: 5.5% | D7: 21323798 | E7: 48373814 | F7: 5589489 | G7: 42784325
A8: Repairs | B8: 1.0% | C8: 1.5% | D8: 21323798 | E8: 32749637 | F8: 9923792 | G8: 22825845
A9: SVJ fees | B9: 2,000 | C9: 4,000 | D9: 21323798 | E9: 25685442 | F9: 16962155 | G9: 8723287
A11: Note: "Diff at low" = Buy NW minus Rent NW when the variable is at its low test value. Negative values mean renting wins.
A12: The Range column shows the total swing in the buy-rent difference across the tested range of each variable.

Sheet Cost Evolution Data
A1: Monthly cost evolution: Mortgage payment vs Rent (nominal)
A3: Year | B3: Monthly mortgage (CZK) | C3: Monthly rent (CZK) | D3: Monthly ownership costs ex-mortgage (CZK) | E3: Total monthly buy cost (CZK)
A4: 0 | B4: 39834 | C4: 25905 | D4: 15617 | E4: 55451
A5: 1 | B5: 39834 | C5: 27200 | D5: 16154 | E5: 55988
A6: 2 | B6: 39834 | C6: 28560 | D6: 16716 | E6: 56550
A7: 3 | B7: 39834 | C7: 29988 | D7: 17304 | E7: 57138
A8: 4 | B8: 39834 | C8: 31488 | D8: 17920 | E8: 57754
A9: 5 | B9: 39834 | C9: 33062 | D9: 18564 | E9: 58398
A10: 6 | B10: 39834 | C10: 34715 | D10: 19238 | E10: 59072
A11: 7 | B11: 39834 | C11: 36451 | D11: 19944 | E11: 59778
A12: 8 | B12: 39834 | C12: 38273 | D12: 20683 | E12: 60517
A13: 9 | B13: 39834 | C13: 40187 | D13: 21457 | E13: 61291
A14: 10 | B14: 39834 | C14: 42197 | D14: 22267 | E14: 62101
A15: 11 | B15: 39834 | C15: 44306 | D15: 23116 | E15: 62950
... A44: 40 | B44: 0 | C44: 46522 | D44: 73283 | E44: 73283
